Workbook

Sheet Resumen
C2: Actual | D2: Actual | E2: Actual | F2: Actual | G2: Actual | H2: Actual | I2: Actual | J2: Actual | K2: Actual | L2: Actual | M2: Actual | N2: Actual
B3: P&G | C3: 1 | D3: =C3+1 -> 2 | E3: =D3+1 -> 3 | F3: =E3+1 -> 4 | G3: =F3+1 -> 5 | H3: =G3+1 -> 6 | I3: =H3+1 -> 7 | J3: =I3+1 -> 8 | K3: =J3+1 -> 9 | ... N3: =M3+1 -> 12 | O3: YTD
B4: Ingresos (facturado) | C4: =SUMIFS(CxC!$H$11:$H$51,CxC!$T$11:$T$51,C$3) -> 0 | D4: =SUMIFS(CxC!$H$11:$H$51,CxC!$T$11:$T$51,D$3) -> 0 | E4: =SUMIFS(CxC!$H$11:$H$51,CxC!$T$11:$T$51,E$3) -> 0 | F4: =SUMIFS(CxC!$H$11:$H$51,CxC!$T$11:$T$51,F$3) -> 39970574 | G4: =SUMIFS(CxC!$H$11:$H$51,CxC!$T$11:$T$51,G$3) -> 257438378 | H4: =SUMIFS(CxC!$H$11:$H$51,CxC!$T$11:$T$51,H$3) -> 0 | I4: =SUMIFS(CxC!$H$11:$H$51,CxC!$T$11:$T$51,I$3) -> 42623908 | J4: =SUMIFS(CxC!$H$11:$H$51,CxC!$T$11:$T$51,J$3) -> 62704578 | ... N4: =SUMIFS(CxC!$H$11:$H$51,CxC!$T$11:$T$51,N$3) -> 0 | O4: =+SUM(C4:N4) -> 486681543
B5: Costo Ventas | C5: =-SUMIFS(CxP!$K$6:$K$163,CxP!$X$6:$X$163,$B5,CxP!$Y$6:$Y$163,"Si",CxP!$B$6:$B$163,">="&DATE(2026,C$3,1),CxP!$B$6:$B$163,"<="&EOMONTH(DATE(2026,C$3,1),0))-SUMIFS(CxP!$M$6:$M$163,CxP!$X$6:$X$163,$B5,CxP!$Y$6:$Y$163,"Si",CxP!$B$6:$B$163,">="&DATE(2026,C$3,1),CxP!$B$6:$B$163,"<="&EOMONTH(DATE(2026,C$3,1),0))+SUMIFS('Extractos bancarios - Manglar'!$C:$C,'Extractos bancarios - Manglar'!$G:$G,$B5,'Extractos bancarios - Manglar'!$L:$L,C$3,'Extractos bancarios - Manglar'!$M:$M,"")-SUMIFS('Extractos bancarios - Manglar'!$C:$C,'Extractos bancarios - Manglar'!$G:$G,$B5,'Extractos bancarios - Manglar'!$L:$L,C$3,'Extractos bancarios - Manglar'!$M:$M,"",'Extractos bancarios - Manglar'!$K:$K,"Si")*0.19/1.19 -> 0 | D5: =-SUMIFS(CxP!$K$6:$K$163,CxP!$X$6:$X$163,$B5,CxP!$Y$6:$Y$163,"Si",CxP!$B$6:$B$163,">="&DATE(2026,D$3,1),CxP!$B$6:$B$163,"<="&EOMONTH(DATE(2026,D$3,1),0))-SUMIFS(CxP!$M$6:$M$163,CxP!$X$6:$X$163,$B5,CxP!$Y$6:$Y$163,"Si",CxP!$B$6:$B$163,">="&DATE(2026,D$3,1),CxP!$B$6:$B$163,"<="&EOMONTH(DATE(2026,D$3,1),0))+SUMIFS('Extractos bancarios - Manglar'!$C:$C,'Extractos bancarios - Manglar'!$G:$G,$B5,'Extractos bancarios - Manglar'!$L:$L,D$3,'Extractos bancarios - Manglar'!$M:$M,"")-SUMIFS('Extractos bancarios - Manglar'!$C:$C,'Extractos bancarios - Manglar'!$G:$G,$B5,'Extractos bancarios - Manglar'!$L:$L,D$3,'Extractos bancarios - Manglar'!$M:$M,"",'Extractos bancarios - Manglar'!$K:$K,"Si")*0.19/1.19 -> 0 | E5: =-SUMIFS(CxP!$K$6:$K$163,CxP!$X$6:$X$163,$B5,CxP!$Y$6:$Y$163,"Si",CxP!$B$6:$B$163,">="&DATE(2026,E$3,1),CxP!$B$6:$B$163,"<="&EOMONTH(DATE(2026,E$3,1),0))-SUMIFS(CxP!$M$6:$M$163,CxP!$X$6:$X$163,$B5,CxP!$Y$6:$Y$163,"Si",CxP!$B$6:$B$163,">="&DATE(2026,E$3,1),CxP!$B$6:$B$163,"<="&EOMONTH(DATE(2026,E$3,1),0))+SUMIFS('Extractos bancarios - Manglar'!$C:$C,'Extractos bancarios - Manglar'!$G:$G,$B5,'Extractos bancarios - Manglar'!$L:$L,E$3,'Extractos bancarios - Manglar'!$M:$M,"")-SUMIFS('Extractos bancarios - Manglar'!$C:$C,'Extractos bancarios - Manglar'!$G:$G,$B5,'Extractos bancarios - Manglar'!$L:$L,E$3,'Extractos bancarios - Manglar'!$M:$M,"",'Extractos bancarios - Manglar'!$K:$K,"Si")*0.19/1.19 -> -96100 | F5: =-SUMIFS(CxP!$K$6:$K$163,CxP!$X$6:$X$163,$B5,CxP!$Y$6:$Y$163,"Si",CxP!$B$6:$B$163,">="&DATE(2026,F$3,1),CxP!$B$6:$B$163,"<="&EOMONTH(DATE(2026,F$3,1),0))-SUMIFS(CxP!$M$6:$M$163,CxP!$X$6:$X$163,$B5,CxP!$Y$6:$Y$163,"Si",CxP!$B$6:$B$163,">="&DATE(2026,F$3,1),CxP!$B$6:$B$163,"<="&EOMONTH(DATE(2026,F$3,1),0))+SUMIFS('Extractos bancarios - Manglar'!$C:$C,'Extractos bancarios - Manglar'!$G:$G,$B5,'Extractos bancarios - Manglar'!$L:$L,F$3,'Extractos bancarios - Manglar'!$M:$M,"")-SUMIFS('Extractos bancarios - Manglar'!$C:$C,'Extractos bancarios - Manglar'!$G:$G,$B5,'Extractos bancarios - Manglar'!$L:$L,F$3,'Extractos bancarios - Manglar'!$M:$M,"",'Extractos bancarios - Manglar'!$K:$K,"Si")*0.19/1.19 -> -11807899 | G5: =-SUMIFS(CxP!$K$6:$K$163,CxP!$X$6:$X$163,$B5,CxP!$Y$6:$Y$163,"Si",CxP!$B$6:$B$163,">="&DATE(2026,G$3,1),CxP!$B$6:$B$163,"<="&EOMONTH(DATE(2026,G$3,1),0))-SUMIFS(CxP!$M$6:$M$163,CxP!$X$6:$X$163,$B5,CxP!$Y$6:$Y$163,"Si",CxP!$B$6:$B$163,">="&DATE(2026,G$3,1),CxP!$B$6:$B$163,"<="&EOMONTH(DATE(2026,G$3,1),0))+SUMIFS('Extractos bancarios - Manglar'!$C:$C,'Extractos bancarios - Manglar'!$G:$G,$B5,'Extractos bancarios - Manglar'!$L:$L,G$3,'Extractos bancarios - Manglar'!$M:$M,"")-SUMIFS('Extractos bancarios - Manglar'!$C:$C,'Extractos bancarios - Manglar'!$G:$G,$B5,'Extractos bancarios - Manglar'!$L:$L,G$3,'Extractos bancarios - Manglar'!$M:$M,"",'Extractos bancarios - Manglar'!$K:$K,"Si")*0.19/1.19 -> -12820269 | H5: =-SUMIFS(CxP!$K$6:$K$163,CxP!$X$6:$X$163,$B5,CxP!$Y$6:$Y$163,"Si",CxP!$B$6:$B$163,">="&DATE(2026,H$3,1),CxP!$B$6:$B$163,"<="&EOMONTH(DATE(2026,H$3,1),0))-SUMIFS(CxP!$M$6:$M$163,CxP!$X$6:$X$163,$B5,CxP!$Y$6:$Y$163,"Si",CxP!$B$6:$B$163,">="&DATE(2026,H$3,1),CxP!$B$6:$B$163,"<="&EOMONTH(DATE(2026,H$3,1),0))+SUMIFS('Extractos bancarios - Manglar'!$C:$C,'Extractos bancarios - Manglar'!$G:$G,$B5,'Extractos bancarios - Manglar'!$L:$L,H$3,'Extractos bancarios - Manglar'!$M:$M,"")-SUMIFS('Extractos bancarios - Manglar'!$C:$C,'Extractos bancarios - Manglar'!$G:$G,$B5,'Extractos bancarios - Manglar'!$L:$L,H$3,'Extractos bancarios - Manglar'!$M:$M,"",'Extractos bancarios - Manglar'!$K:$K,"Si")*0.19/1.19 -> -1.6523143e+08 | I5: =-SUMIFS(CxP!$K$6:$K$163,CxP!$X$6:$X$163,$B5,CxP!$Y$6:$Y$163,"Si",CxP!$B$6:$B$163,">="&DATE(2026,I$3,1),CxP!$B$6:$B$163,"<="&EOMONTH(DATE(2026,I$3,1),0))-SUMIFS(CxP!$M$6:$M$163,CxP!$X$6:$X$163,$B5,CxP!$Y$6:$Y$163,"Si",CxP!$B$6:$B$163,">="&DATE(2026,I$3,1),CxP!$B$6:$B$163,"<="&EOMONTH(DATE(2026,I$3,1),0))+SUMIFS('Extractos bancarios - Manglar'!$C:$C,'Extractos bancarios - Manglar'!$G:$G,$B5,'Extractos bancarios - Manglar'!$L:$L,I$3,'Extractos bancarios - Manglar'!$M:$M,"")-SUMIFS('Extractos bancarios - Manglar'!$C:$C,'Extractos bancarios - Manglar'!$G:$G,$B5,'Extractos bancarios - Manglar'!$L:$L,I$3,'Extractos bancarios - Manglar'!$M:$M,"",'Extractos bancarios - Manglar'!$K:$K,"Si")*0.19/1.19 -> -39675772 | J5: =-SUMIFS(CxP!$K$6:$K$163,CxP!$X$6:$X$163,$B5,CxP!$Y$6:$Y$163,"Si",CxP!$B$6:$B$163,">="&DATE(2026,J$3,1),CxP!$B$6:$B$163,"<="&EOMONTH(DATE(2026,J$3,1),0))-SUMIFS(CxP!$M$6:$M$163,CxP!$X$6:$X$163,$B5,CxP!$Y$6:$Y$163,"Si",CxP!$B$6:$B$163,">="&DATE(2026,J$3,1),CxP!$B$6:$B$163,"<="&EOMONTH(DATE(2026,J$3,1),0))+SUMIFS('Extractos bancarios - Manglar'!$C:$C,'Extractos bancarios - Manglar'!$G:$G,$B5,'Extractos bancarios - Manglar'!$L:$L,J$3,'Extractos bancarios - Manglar'!$M:$M,"")-SUMIFS('Extractos bancarios - Manglar'!$C:$C,'Extractos bancarios - Manglar'!$G:$G,$B5,'Extractos bancarios - Manglar'!$L:$L,J$3,'Extractos bancarios - Manglar'!$M:$M,"",'Extractos bancarios - Manglar'!$K:$K,"Si")*0.19/1.19 -> -18764243 | ... N5: =-SUMIFS(CxP!$K$6:$K$163,CxP!$X$6:$X$163,$B5,CxP!$Y$6:$Y$163,"Si",CxP!$B$6:$B$163,">="&DATE(2026,N$3,1),CxP!$B$6:$B$163,"<="&EOMONTH(DATE(2026,N$3,1),0))-SUMIFS(CxP!$M$6:$M$163,CxP!$X$6:$X$163,$B5,CxP!$Y$6:$Y$163,"Si",CxP!$B$6:$B$163,">="&DATE(2026,N$3,1),CxP!$B$6:$B$163,"<="&EOMONTH(DATE(2026,N$3,1),0))+SUMIFS('Extractos bancarios - Manglar'!$C:$C,'Extractos bancarios - Manglar'!$G:$G,$B5,'Extractos bancarios - Manglar'!$L:$L,N$3,'Extractos bancarios - Manglar'!$M:$M,"")-SUMIFS('Extractos bancarios - Manglar'!$C:$C,'Extractos bancarios - Manglar'!$G:$G,$B5,'Extractos bancarios - Manglar'!$L:$L,N$3,'Extractos bancarios - Manglar'!$M:$M,"",'Extractos bancarios - Manglar'!$K:$K,"Si")*0.19/1.19 -> 0 | O5: =+SUM(C5:N5) -> -3.5685309e+08
B6: Margen Bruto | C6: =+C4+C5 -> 0 | D6: =+D4+D5 -> 0 | E6: =+E4+E5 -> -96100 | F6: =+F4+F5 -> 28162675 | G6: =+G4+G5 -> 2.4461811e+08 | H6: =+H4+H5 -> -1.6523143e+08 | I6: =+I4+I5 -> 2948135.7 | J6: =+J4+J5 -> 43940335 | ... N6: =+N4+N5 -> 0 | O6: =+SUM(C6:N6) -> 1.2982845e+08
B7: Margen Bruto % | C7: =IFERROR(+C6/C$4,"-") -> - | D7: =IFERROR(+D6/D$4,"-") -> - | E7: =IFERROR(+E6/E$4,"-") -> - | F7: =IFERROR(+F6/F$4,"-") -> 0.70458521 | G7: =IFERROR(+G6/G$4,"-") -> 0.95020063 | H7: =IFERROR(+H6/H$4,"-") -> - | I7: =IFERROR(+I6/I$4,"-") -> 0.069166246 | J7: =IFERROR(+J6/J$4,"-") -> 0.70075163 | ... O7: =IFERROR(+O6/O$4,"-") -> 0.26676264
B8: Otros Ingresos | C8: =(SUMIFS('Extractos bancarios - Manglar'!$C:$C,'Extractos bancarios - Manglar'!$G:$G,$B8,'Extractos bancarios - Manglar'!$L:$L,C$3,'Extractos bancarios - Manglar'!$K:$K,"Si")/1.19)+SUMIFS('Extractos bancarios - Manglar'!$C:$C,'Extractos bancarios - Manglar'!$G:$G,$B8,'Extractos bancarios - Manglar'!$L:$L,C$3,'Extractos bancarios - Manglar'!$K:$K,"No") -> 0 | D8: =(SUMIFS('Extractos bancarios - Manglar'!$C:$C,'Extractos bancarios - Manglar'!$G:$G,$B8,'Extractos bancarios - Manglar'!$L:$L,D$3,'Extractos bancarios - Manglar'!$K:$K,"Si")/1.19)+SUMIFS('Extractos bancarios - Manglar'!$C:$C,'Extractos bancarios - Manglar'!$G:$G,$B8,'Extractos bancarios - Manglar'!$L:$L,D$3,'Extractos bancarios - Manglar'!$K:$K,"No") -> 0 | E8: =(SUMIFS('Extractos bancarios - Manglar'!$C:$C,'Extractos bancarios - Manglar'!$G:$G,$B8,'Extractos bancarios - Manglar'!$L:$L,E$3,'Extractos bancarios - Manglar'!$K:$K,"Si")/1.19)+SUMIFS('Extractos bancarios - Manglar'!$C:$C,'Extractos bancarios - Manglar'!$G:$G,$B8,'Extractos bancarios - Manglar'!$L:$L,E$3,'Extractos bancarios - Manglar'!$K:$K,"No") -> 0 | F8: =(SUMIFS('Extractos bancarios - Manglar'!$C:$C,'Extractos bancarios - Manglar'!$G:$G,$B8,'Extractos bancarios - Manglar'!$L:$L,F$3,'Extractos bancarios - Manglar'!$K:$K,"Si")/1.19)+SUMIFS('Extractos bancarios - Manglar'!$C:$C,'Extractos bancarios - Manglar'!$G:$G,$B8,'Extractos bancarios - Manglar'!$L:$L,F$3,'Extractos bancarios - Manglar'!$K:$K,"No") -> 0 | G8: =(SUMIFS('Extractos bancarios - Manglar'!$C:$C,'Extractos bancarios - Manglar'!$G:$G,$B8,'Extractos bancarios - Manglar'!$L:$L,G$3,'Extractos bancarios - Manglar'!$K:$K,"Si")/1.19)+SUMIFS('Extractos bancarios - Manglar'!$C:$C,'Extractos bancarios - Manglar'!$G:$G,$B8,'Extractos bancarios - Manglar'!$L:$L,G$3,'Extractos bancarios - Manglar'!$K:$K,"No") -> 0 | H8: =(SUMIFS('Extractos bancarios - Manglar'!$C:$C,'Extractos bancarios - Manglar'!$G:$G,$B8,'Extractos bancarios - Manglar'!$L:$L,H$3,'Extractos bancarios - Manglar'!$K:$K,"Si")/1.19)+SUMIFS('Extractos bancarios - Manglar'!$C:$C,'Extractos bancarios - Manglar'!$G:$G,$B8,'Extractos bancarios - Manglar'!$L:$L,H$3,'Extractos bancarios - Manglar'!$K:$K,"No") -> 0 | I8: =(SUMIFS('Extractos bancarios - Manglar'!$C:$C,'Extractos bancarios - Manglar'!$G:$G,$B8,'Extractos bancarios - Manglar'!$L:$L,I$3,'Extractos bancarios - Manglar'!$K:$K,"Si")/1.19)+SUMIFS('Extractos bancarios - Manglar'!$C:$C,'Extractos bancarios - Manglar'!$G:$G,$B8,'Extractos bancarios - Manglar'!$L:$L,I$3,'Extractos bancarios - Manglar'!$K:$K,"No") -> 0 | J8: =(SUMIFS('Extractos bancarios - Manglar'!$C:$C,'Extractos bancarios - Manglar'!$G:$G,$B8,'Extractos bancarios - Manglar'!$L:$L,J$3,'Extractos bancarios - Manglar'!$K:$K,"Si")/1.19)+SUMIFS('Extractos bancarios - Manglar'!$C:$C,'Extractos bancarios - Manglar'!$G:$G,$B8,'Extractos bancarios - Manglar'!$L:$L,J$3,'Extractos bancarios - Manglar'!$K:$K,"No") -> 0 | ... N8: =(SUMIFS('Extractos bancarios - Manglar'!$C:$C,'Extractos bancarios - Manglar'!$G:$G,$B8,'Extractos bancarios - Manglar'!$L:$L,N$3,'Extractos bancarios - Manglar'!$K:$K,"Si")/1.19)+SUMIFS('Extractos bancarios - Manglar'!$C:$C,'Extractos bancarios - Manglar'!$G:$G,$B8,'Extractos bancarios - Manglar'!$L:$L,N$3,'Extractos bancarios - Manglar'!$K:$K,"No") -> 0 | O8: =+SUM(C8:N8) -> 0
B9: Costos Fijos | C9: =-SUMIFS(CxP!$K$6:$K$163,CxP!$X$6:$X$163,$B9,CxP!$Y$6:$Y$163,"Si",CxP!$B$6:$B$163,">="&DATE(2026,C$3,1),CxP!$B$6:$B$163,"<="&EOMONTH(DATE(2026,C$3,1),0))-SUMIFS(CxP!$M$6:$M$163,CxP!$X$6:$X$163,$B9,CxP!$Y$6:$Y$163,"Si",CxP!$B$6:$B$163,">="&DATE(2026,C$3,1),CxP!$B$6:$B$163,"<="&EOMONTH(DATE(2026,C$3,1),0))+SUMIFS('Extractos bancarios - Manglar'!$C:$C,'Extractos bancarios - Manglar'!$G:$G,$B9,'Extractos bancarios - Manglar'!$L:$L,C$3,'Extractos bancarios - Manglar'!$M:$M,"")-SUMIFS('Extractos bancarios - Manglar'!$C:$C,'Extractos bancarios - Manglar'!$G:$G,$B9,'Extractos bancarios - Manglar'!$L:$L,C$3,'Extractos bancarios - Manglar'!$M:$M,"",'Extractos bancarios - Manglar'!$K:$K,"Si")*0.19/1.19 -> 0 | D9: =-SUMIFS(CxP!$K$6:$K$163,CxP!$X$6:$X$163,$B9,CxP!$Y$6:$Y$163,"Si",CxP!$B$6:$B$163,">="&DATE(2026,D$3,1),CxP!$B$6:$B$163,"<="&EOMONTH(DATE(2026,D$3,1),0))-SUMIFS(CxP!$M$6:$M$163,CxP!$X$6:$X$163,$B9,CxP!$Y$6:$Y$163,"Si",CxP!$B$6:$B$163,">="&DATE(2026,D$3,1),CxP!$B$6:$B$163,"<="&EOMONTH(DATE(2026,D$3,1),0))+SUMIFS('Extractos bancarios - Manglar'!$C:$C,'Extractos bancarios - Manglar'!$G:$G,$B9,'Extractos bancarios - Manglar'!$L:$L,D$3,'Extractos bancarios - Manglar'!$M:$M,"")-SUMIFS('Extractos bancarios - Manglar'!$C:$C,'Extractos bancarios - Manglar'!$G:$G,$B9,'Extractos bancarios - Manglar'!$L:$L,D$3,'Extractos bancarios - Manglar'!$M:$M,"",'Extractos bancarios - Manglar'!$K:$K,"Si")*0.19/1.19 -> 0 | E9: =-SUMIFS(CxP!$K$6:$K$163,CxP!$X$6:$X$163,$B9,CxP!$Y$6:$Y$163,"Si",CxP!$B$6:$B$163,">="&DATE(2026,E$3,1),CxP!$B$6:$B$163,"<="&EOMONTH(DATE(2026,E$3,1),0))-SUMIFS(CxP!$M$6:$M$163,CxP!$X$6:$X$163,$B9,CxP!$Y$6:$Y$163,"Si",CxP!$B$6:$B$163,">="&DATE(2026,E$3,1),CxP!$B$6:$B$163,"<="&EOMONTH(DATE(2026,E$3,1),0))+SUMIFS('Extractos bancarios - Manglar'!$C:$C,'Extractos bancarios - Manglar'!$G:$G,$B9,'Extractos bancarios - Manglar'!$L:$L,E$3,'Extractos bancarios - Manglar'!$M:$M,"")-SUMIFS('Extractos bancarios - Manglar'!$C:$C,'Extractos bancarios - Manglar'!$G:$G,$B9,'Extractos bancarios - Manglar'!$L:$L,E$3,'Extractos bancarios - Manglar'!$M:$M,"",'Extractos bancarios - Manglar'!$K:$K,"Si")*0.19/1.19 -> -18050 | F9: =-SUMIFS(CxP!$K$6:$K$163,CxP!$X$6:$X$163,$B9,CxP!$Y$6:$Y$163,"Si",CxP!$B$6:$B$163,">="&DATE(2026,F$3,1),CxP!$B$6:$B$163,"<="&EOMONTH(DATE(2026,F$3,1),0))-SUMIFS(CxP!$M$6:$M$163,CxP!$X$6:$X$163,$B9,CxP!$Y$6:$Y$163,"Si",CxP!$B$6:$B$163,">="&DATE(2026,F$3,1),CxP!$B$6:$B$163,"<="&EOMONTH(DATE(2026,F$3,1),0))+SUMIFS('Extractos bancarios - Manglar'!$C:$C,'Extractos bancarios - Manglar'!$G:$G,$B9,'Extractos bancarios - Manglar'!$L:$L,F$3,'Extractos bancarios - Manglar'!$M:$M,"")-SUMIFS('Extractos bancarios - Manglar'!$C:$C,'Extractos bancarios - Manglar'!$G:$G,$B9,'Extractos bancarios - Manglar'!$L:$L,F$3,'Extractos bancarios - Manglar'!$M:$M,"",'Extractos bancarios - Manglar'!$K:$K,"Si")*0.19/1.19 -> -18050 | G9: =-SUMIFS(CxP!$K$6:$K$163,CxP!$X$6:$X$163,$B9,CxP!$Y$6:$Y$163,"Si",CxP!$B$6:$B$163,">="&DATE(2026,G$3,1),CxP!$B$6:$B$163,"<="&EOMONTH(DATE(2026,G$3,1),0))-SUMIFS(CxP!$M$6:$M$163,CxP!$X$6:$X$163,$B9,CxP!$Y$6:$Y$163,"Si",CxP!$B$6:$B$163,">="&DATE(2026,G$3,1),CxP!$B$6:$B$163,"<="&EOMONTH(DATE(2026,G$3,1),0))+SUMIFS('Extractos bancarios - Manglar'!$C:$C,'Extractos bancarios - Manglar'!$G:$G,$B9,'Extractos bancarios - Manglar'!$L:$L,G$3,'Extractos bancarios - Manglar'!$M:$M,"")-SUMIFS('Extractos bancarios - Manglar'!$C:$C,'Extractos bancarios - Manglar'!$G:$G,$B9,'Extractos bancarios - Manglar'!$L:$L,G$3,'Extractos bancarios - Manglar'!$M:$M,"",'Extractos bancarios - Manglar'!$K:$K,"Si")*0.19/1.19 -> -18050 | H9: =-SUMIFS(CxP!$K$6:$K$163,CxP!$X$6:$X$163,$B9,CxP!$Y$6:$Y$163,"Si",CxP!$B$6:$B$163,">="&DATE(2026,H$3,1),CxP!$B$6:$B$163,"<="&EOMONTH(DATE(2026,H$3,1),0))-SUMIFS(CxP!$M$6:$M$163,CxP!$X$6:$X$163,$B9,CxP!$Y$6:$Y$163,"Si",CxP!$B$6:$B$163,">="&DATE(2026,H$3,1),CxP!$B$6:$B$163,"<="&EOMONTH(DATE(2026,H$3,1),0))+SUMIFS('Extractos bancarios - Manglar'!$C:$C,'Extractos bancarios - Manglar'!$G:$G,$B9,'Extractos bancarios - Manglar'!$L:$L,H$3,'Extractos bancarios - Manglar'!$M:$M,"")-SUMIFS('Extractos bancarios - Manglar'!$C:$C,'Extractos bancarios - Manglar'!$G:$G,$B9,'Extractos bancarios - Manglar'!$L:$L,H$3,'Extractos bancarios - Manglar'!$M:$M,"",'Extractos bancarios - Manglar'!$K:$K,"Si")*0.19/1.19 -> -18050 | I9: =-SUMIFS(CxP!$K$6:$K$163,CxP!$X$6:$X$163,$B9,CxP!$Y$6:$Y$163,"Si",CxP!$B$6:$B$163,">="&DATE(2026,I$3,1),CxP!$B$6:$B$163,"<="&EOMONTH(DATE(2026,I$3,1),0))-SUMIFS(CxP!$M$6:$M$163,CxP!$X$6:$X$163,$B9,CxP!$Y$6:$Y$163,"Si",CxP!$B$6:$B$163,">="&DATE(2026,I$3,1),CxP!$B$6:$B$163,"<="&EOMONTH(DATE(2026,I$3,1),0))+SUMIFS('Extractos bancarios - Manglar'!$C:$C,'Extractos bancarios - Manglar'!$G:$G,$B9,'Extractos bancarios - Manglar'!$L:$L,I$3,'Extractos bancarios - Manglar'!$M:$M,"")-SUMIFS('Extractos bancarios - Manglar'!$C:$C,'Extractos bancarios - Manglar'!$G:$G,$B9,'Extractos bancarios - Manglar'!$L:$L,I$3,'Extractos bancarios - Manglar'!$M:$M,"",'Extractos bancarios - Manglar'!$K:$K,"Si")*0.19/1.19 -> -18050 | J9: =-SUMIFS(CxP!$K$6:$K$163,CxP!$X$6:$X$163,$B9,CxP!$Y$6:$Y$163,"Si",CxP!$B$6:$B$163,">="&DATE(2026,J$3,1),CxP!$B$6:$B$163,"<="&EOMONTH(DATE(2026,J$3,1),0))-SUMIFS(CxP!$M$6:$M$163,CxP!$X$6:$X$163,$B9,CxP!$Y$6:$Y$163,"Si",CxP!$B$6:$B$163,">="&DATE(2026,J$3,1),CxP!$B$6:$B$163,"<="&EOMONTH(DATE(2026,J$3,1),0))+SUMIFS('Extractos bancarios - Manglar'!$C:$C,'Extractos bancarios - Manglar'!$G:$G,$B9,'Extractos bancarios - Manglar'!$L:$L,J$3,'Extractos bancarios - Manglar'!$M:$M,"")-SUMIFS('Extractos bancarios - Manglar'!$C:$C,'Extractos bancarios - Manglar'!$G:$G,$B9,'Extractos bancarios - Manglar'!$L:$L,J$3,'Extractos bancarios - Manglar'!$M:$M,"",'Extractos bancarios - Manglar'!$K:$K,"Si")*0.19/1.19 -> -18050 | ... N9: =-SUMIFS(CxP!$K$6:$K$163,CxP!$X$6:$X$163,$B9,CxP!$Y$6:$Y$163,"Si",CxP!$B$6:$B$163,">="&DATE(2026,N$3,1),CxP!$B$6:$B$163,"<="&EOMONTH(DATE(2026,N$3,1),0))-SUMIFS(CxP!$M$6:$M$163,CxP!$X$6:$X$163,$B9,CxP!$Y$6:$Y$163,"Si",CxP!$B$6:$B$163,">="&DATE(2026,N$3,1),CxP!$B$6:$B$163,"<="&EOMONTH(DATE(2026,N$3,1),0))+SUMIFS('Extractos bancarios - Manglar'!$C:$C,'Extractos bancarios - Manglar'!$G:$G,$B9,'Extractos bancarios - Manglar'!$L:$L,N$3,'Extractos bancarios - Manglar'!$M:$M,"")-SUMIFS('Extractos bancarios - Manglar'!$C:$C,'Extractos bancarios - Manglar'!$G:$G,$B9,'Extractos bancarios - Manglar'!$L:$L,N$3,'Extractos bancarios - Manglar'!$M:$M,"",'Extractos bancarios - Manglar'!$K:$K,"Si")*0.19/1.19 -> 0 | O9: =+SUM(C9:N9) -> -144400
B10: Costos Operacionales | C10: =-SUMIFS(CxP!$K$6:$K$163,CxP!$X$6:$X$163,$B10,CxP!$Y$6:$Y$163,"Si",CxP!$B$6:$B$163,">="&DATE(2026,C$3,1),CxP!$B$6:$B$163,"<="&EOMONTH(DATE(2026,C$3,1),0))-SUMIFS(CxP!$M$6:$M$163,CxP!$X$6:$X$163,$B10,CxP!$Y$6:$Y$163,"Si",CxP!$B$6:$B$163,">="&DATE(2026,C$3,1),CxP!$B$6:$B$163,"<="&EOMONTH(DATE(2026,C$3,1),0))+SUMIFS('Extractos bancarios - Manglar'!$C:$C,'Extractos bancarios - Manglar'!$G:$G,$B10,'Extractos bancarios - Manglar'!$L:$L,C$3,'Extractos bancarios - Manglar'!$M:$M,"")-SUMIFS('Extractos bancarios - Manglar'!$C:$C,'Extractos bancarios - Manglar'!$G:$G,$B10,'Extractos bancarios - Manglar'!$L:$L,C$3,'Extractos bancarios - Manglar'!$M:$M,"",'Extractos bancarios - Manglar'!$K:$K,"Si")*0.19/1.19 -> 0 | D10: =-SUMIFS(CxP!$K$6:$K$163,CxP!$X$6:$X$163,$B10,CxP!$Y$6:$Y$163,"Si",CxP!$B$6:$B$163,">="&DATE(2026,D$3,1),CxP!$B$6:$B$163,"<="&EOMONTH(DATE(2026,D$3,1),0))-SUMIFS(CxP!$M$6:$M$163,CxP!$X$6:$X$163,$B10,CxP!$Y$6:$Y$163,"Si",CxP!$B$6:$B$163,">="&DATE(2026,D$3,1),CxP!$B$6:$B$163,"<="&EOMONTH(DATE(2026,D$3,1),0))+SUMIFS('Extractos bancarios - Manglar'!$C:$C,'Extractos bancarios - Manglar'!$G:$G,$B10,'Extractos bancarios - Manglar'!$L:$L,D$3,'Extractos bancarios - Manglar'!$M:$M,"")-SUMIFS('Extractos bancarios - Manglar'!$C:$C,'Extractos bancarios - Manglar'!$G:$G,$B10,'Extractos bancarios - Manglar'!$L:$L,D$3,'Extractos bancarios - Manglar'!$M:$M,"",'Extractos bancarios - Manglar'!$K:$K,"Si")*0.19/1.19 -> 0 | E10: =-SUMIFS(CxP!$K$6:$K$163,CxP!$X$6:$X$163,$B10,CxP!$Y$6:$Y$163,"Si",CxP!$B$6:$B$163,">="&DATE(2026,E$3,1),CxP!$B$6:$B$163,"<="&EOMONTH(DATE(2026,E$3,1),0))-SUMIFS(CxP!$M$6:$M$163,CxP!$X$6:$X$163,$B10,CxP!$Y$6:$Y$163,"Si",CxP!$B$6:$B$163,">="&DATE(2026,E$3,1),CxP!$B$6:$B$163,"<="&EOMONTH(DATE(2026,E$3,1),0))+SUMIFS('Extractos bancarios - Manglar'!$C:$C,'Extractos bancarios - Manglar'!$G:$G,$B10,'Extractos bancarios - Manglar'!$L:$L,E$3,'Extractos bancarios - Manglar'!$M:$M,"")-SUMIFS('Extractos bancarios - Manglar'!$C:$C,'Extractos bancarios - Manglar'!$G:$G,$B10,'Extractos bancarios - Manglar'!$L:$L,E$3,'Extractos bancarios - Manglar'!$M:$M,"",'Extractos bancarios - Manglar'!$K:$K,"Si")*0.19/1.19 -> -667854 | F10: =-SUMIFS(CxP!$K$6:$K$163,CxP!$X$6:$X$163,$B10,CxP!$Y$6:$Y$163,"Si",CxP!$B$6:$B$163,">="&DATE(2026,F$3,1),CxP!$B$6:$B$163,"<="&EOMONTH(DATE(2026,F$3,1),0))-SUMIFS(CxP!$M$6:$M$163,CxP!$X$6:$X$163,$B10,CxP!$Y$6:$Y$163,"Si",CxP!$B$6:$B$163,">="&DATE(2026,F$3,1),CxP!$B$6:$B$163,"<="&EOMONTH(DATE(2026,F$3,1),0))+SUMIFS('Extractos bancarios - Manglar'!$C:$C,'Extractos bancarios - Manglar'!$G:$G,$B10,'Extractos bancarios - Manglar'!$L:$L,F$3,'Extractos bancarios - Manglar'!$M:$M,"")-SUMIFS('Extractos bancarios - Manglar'!$C:$C,'Extractos bancarios - Manglar'!$G:$G,$B10,'Extractos bancarios - Manglar'!$L:$L,F$3,'Extractos bancarios - Manglar'!$M:$M,"",'Extractos bancarios - Manglar'!$K:$K,"Si")*0.19/1.19 -> -222529 | G10: =-SUMIFS(CxP!$K$6:$K$163,CxP!$X$6:$X$163,$B10,CxP!$Y$6:$Y$163,"Si",CxP!$B$6:$B$163,">="&DATE(2026,G$3,1),CxP!$B$6:$B$163,"<="&EOMONTH(DATE(2026,G$3,1),0))-SUMIFS(CxP!$M$6:$M$163,CxP!$X$6:$X$163,$B10,CxP!$Y$6:$Y$163,"Si",CxP!$B$6:$B$163,">="&DATE(2026,G$3,1),CxP!$B$6:$B$163,"<="&EOMONTH(DATE(2026,G$3,1),0))+SUMIFS('Extractos bancarios - Manglar'!$C:$C,'Extractos bancarios - Manglar'!$G:$G,$B10,'Extractos bancarios - Manglar'!$L:$L,G$3,'Extractos bancarios - Manglar'!$M:$M,"")-SUMIFS('Extractos bancarios - Manglar'!$C:$C,'Extractos bancarios - Manglar'!$G:$G,$B10,'Extractos bancarios - Manglar'!$L:$L,G$3,'Extractos bancarios - Manglar'!$M:$M,"",'Extractos bancarios - Manglar'!$K:$K,"Si")*0.19/1.19 -> -339061 | H10: =-SUMIFS(CxP!$K$6:$K$163,CxP!$X$6:$X$163,$B10,CxP!$Y$6:$Y$163,"Si",CxP!$B$6:$B$163,">="&DATE(2026,H$3,1),CxP!$B$6:$B$163,"<="&EOMONTH(DATE(2026,H$3,1),0))-SUMIFS(CxP!$M$6:$M$163,CxP!$X$6:$X$163,$B10,CxP!$Y$6:$Y$163,"Si",CxP!$B$6:$B$163,">="&DATE(2026,H$3,1),CxP!$B$6:$B$163,"<="&EOMONTH(DATE(2026,H$3,1),0))+SUMIFS('Extractos bancarios - Manglar'!$C:$C,'Extractos bancarios - Manglar'!$G:$G,$B10,'Extractos bancarios - Manglar'!$L:$L,H$3,'Extractos bancarios - Manglar'!$M:$M,"")-SUMIFS('Extractos bancarios - Manglar'!$C:$C,'Extractos bancarios - Manglar'!$G:$G,$B10,'Extractos bancarios - Manglar'!$L:$L,H$3,'Extractos bancarios - Manglar'!$M:$M,"",'Extractos bancarios - Manglar'!$K:$K,"Si")*0.19/1.19 -> -1134601 | I10: =-SUMIFS(CxP!$K$6:$K$163,CxP!$X$6:$X$163,$B10,CxP!$Y$6:$Y$163,"Si",CxP!$B$6:$B$163,">="&DATE(2026,I$3,1),CxP!$B$6:$B$163,"<="&EOMONTH(DATE(2026,I$3,1),0))-SUMIFS(CxP!$M$6:$M$163,CxP!$X$6:$X$163,$B10,CxP!$Y$6:$Y$163,"Si",CxP!$B$6:$B$163,">="&DATE(2026,I$3,1),CxP!$B$6:$B$163,"<="&EOMONTH(DATE(2026,I$3,1),0))+SUMIFS('Extractos bancarios - Manglar'!$C:$C,'Extractos bancarios - Manglar'!$G:$G,$B10,'Extractos bancarios - Manglar'!$L:$L,I$3,'Extractos bancarios - Manglar'!$M:$M,"")-SUMIFS('Extractos bancarios - Manglar'!$C:$C,'Extractos bancarios - Manglar'!$G:$G,$B10,'Extractos bancarios - Manglar'!$L:$L,I$3,'Extractos bancarios - Manglar'!$M:$M,"",'Extractos bancarios - Manglar'!$K:$K,"Si")*0.19/1.19 -> -11200397 | J10: =-SUMIFS(CxP!$K$6:$K$163,CxP!$X$6:$X$163,$B10,CxP!$Y$6:$Y$163,"Si",CxP!$B$6:$B$163,">="&DATE(2026,J$3,1),CxP!$B$6:$B$163,"<="&EOMONTH(DATE(2026,J$3,1),0))-SUMIFS(CxP!$M$6:$M$163,CxP!$X$6:$X$163,$B10,CxP!$Y$6:$Y$163,"Si",CxP!$B$6:$B$163,">="&DATE(2026,J$3,1),CxP!$B$6:$B$163,"<="&EOMONTH(DATE(2026,J$3,1),0))+SUMIFS('Extractos bancarios - Manglar'!$C:$C,'Extractos bancarios - Manglar'!$G:$G,$B10,'Extractos bancarios - Manglar'!$L:$L,J$3,'Extractos bancarios - Manglar'!$M:$M,"")-SUMIFS('Extractos bancarios - Manglar'!$C:$C,'Extractos bancarios - Manglar'!$G:$G,$B10,'Extractos bancarios - Manglar'!$L:$L,J$3,'Extractos bancarios - Manglar'!$M:$M,"",'Extractos bancarios - Manglar'!$K:$K,"Si")*0.19/1.19 -> -531388.67 | ... N10: =-SUMIFS(CxP!$K$6:$K$163,CxP!$X$6:$X$163,$B10,CxP!$Y$6:$Y$163,"Si",CxP!$B$6:$B$163,">="&DATE(2026,N$3,1),CxP!$B$6:$B$163,"<="&EOMONTH(DATE(2026,N$3,1),0))-SUMIFS(CxP!$M$6:$M$163,CxP!$X$6:$X$163,$B10,CxP!$Y$6:$Y$163,"Si",CxP!$B$6:$B$163,">="&DATE(2026,N$3,1),CxP!$B$6:$B$163,"<="&EOMONTH(DATE(2026,N$3,1),0))+SUMIFS('Extractos bancarios - Manglar'!$C:$C,'Extractos bancarios - Manglar'!$G:$G,$B10,'Extractos bancarios - Manglar'!$L:$L,N$3,'Extractos bancarios - Manglar'!$M:$M,"")-SUMIFS('Extractos bancarios - Manglar'!$C:$C,'Extractos bancarios - Manglar'!$G:$G,$B10,'Extractos bancarios - Manglar'!$L:$L,N$3,'Extractos bancarios - Manglar'!$M:$M,"",'Extractos bancarios - Manglar'!$K:$K,"Si")*0.19/1.19 -> 0 | O10: =+SUM(C10:N10) -> -28173402
B11: Gastos Variables | C11: =-SUMIFS(CxP!$K$6:$K$163,CxP!$X$6:$X$163,$B11,CxP!$Y$6:$Y$163,"Si",CxP!$B$6:$B$163,">="&DATE(2026,C$3,1),CxP!$B$6:$B$163,"<="&EOMONTH(DATE(2026,C$3,1),0))-SUMIFS(CxP!$M$6:$M$163,CxP!$X$6:$X$163,$B11,CxP!$Y$6:$Y$163,"Si",CxP!$B$6:$B$163,">="&DATE(2026,C$3,1),CxP!$B$6:$B$163,"<="&EOMONTH(DATE(2026,C$3,1),0))+SUMIFS('Extractos bancarios - Manglar'!$C:$C,'Extractos bancarios - Manglar'!$G:$G,$B11,'Extractos bancarios - Manglar'!$L:$L,C$3,'Extractos bancarios - Manglar'!$M:$M,"")-SUMIFS('Extractos bancarios - Manglar'!$C:$C,'Extractos bancarios - Manglar'!$G:$G,$B11,'Extractos bancarios - Manglar'!$L:$L,C$3,'Extractos bancarios - Manglar'!$M:$M,"",'Extractos bancarios - Manglar'!$K:$K,"Si")*0.19/1.19 -> 0 | D11: =-SUMIFS(CxP!$K$6:$K$163,CxP!$X$6:$X$163,$B11,CxP!$Y$6:$Y$163,"Si",CxP!$B$6:$B$163,">="&DATE(2026,D$3,1),CxP!$B$6:$B$163,"<="&EOMONTH(DATE(2026,D$3,1),0))-SUMIFS(CxP!$M$6:$M$163,CxP!$X$6:$X$163,$B11,CxP!$Y$6:$Y$163,"Si",CxP!$B$6:$B$163,">="&DATE(2026,D$3,1),CxP!$B$6:$B$163,"<="&EOMONTH(DATE(2026,D$3,1),0))+SUMIFS('Extractos bancarios - Manglar'!$C:$C,'Extractos bancarios - Manglar'!$G:$G,$B11,'Extractos bancarios - Manglar'!$L:$L,D$3,'Extractos bancarios - Manglar'!$M:$M,"")-SUMIFS('Extractos bancarios - Manglar'!$C:$C,'Extractos bancarios - Manglar'!$G:$G,$B11,'Extractos bancarios - Manglar'!$L:$L,D$3,'Extractos bancarios - Manglar'!$M:$M,"",'Extractos bancarios - Manglar'!$K:$K,"Si")*0.19/1.19 -> 0 | E11: =-SUMIFS(CxP!$K$6:$K$163,CxP!$X$6:$X$163,$B11,CxP!$Y$6:$Y$163,"Si",CxP!$B$6:$B$163,">="&DATE(2026,E$3,1),CxP!$B$6:$B$163,"<="&EOMONTH(DATE(2026,E$3,1),0))-SUMIFS(CxP!$M$6:$M$163,CxP!$X$6:$X$163,$B11,CxP!$Y$6:$Y$163,"Si",CxP!$B$6:$B$163,">="&DATE(2026,E$3,1),CxP!$B$6:$B$163,"<="&EOMONTH(DATE(2026,E$3,1),0))+SUMIFS('Extractos bancarios - Manglar'!$C:$C,'Extractos bancarios - Manglar'!$G:$G,$B11,'Extractos bancarios - Manglar'!$L:$L,E$3,'Extractos bancarios - Manglar'!$M:$M,"")-SUMIFS('Extractos bancarios - Manglar'!$C:$C,'Extractos bancarios - Manglar'!$G:$G,$B11,'Extractos bancarios - Manglar'!$L:$L,E$3,'Extractos bancarios - Manglar'!$M:$M,"",'Extractos bancarios - Manglar'!$K:$K,"Si")*0.19/1.19 -> -7519.77 | F11: =-SUMIFS(CxP!$K$6:$K$163,CxP!$X$6:$X$163,$B11,CxP!$Y$6:$Y$163,"Si",CxP!$B$6:$B$163,">="&DATE(2026,F$3,1),CxP!$B$6:$B$163,"<="&EOMONTH(DATE(2026,F$3,1),0))-SUMIFS(CxP!$M$6:$M$163,CxP!$X$6:$X$163,$B11,CxP!$Y$6:$Y$163,"Si",CxP!$B$6:$B$163,">="&DATE(2026,F$3,1),CxP!$B$6:$B$163,"<="&EOMONTH(DATE(2026,F$3,1),0))+SUMIFS('Extractos bancarios - Manglar'!$C:$C,'Extractos bancarios - Manglar'!$G:$G,$B11,'Extractos bancarios - Manglar'!$L:$L,F$3,'Extractos bancarios - Manglar'!$M:$M,"")-SUMIFS('Extractos bancarios - Manglar'!$C:$C,'Extractos bancarios - Manglar'!$G:$G,$B11,'Extractos bancarios - Manglar'!$L:$L,F$3,'Extractos bancarios - Manglar'!$M:$M,"",'Extractos bancarios - Manglar'!$K:$K,"Si")*0.19/1.19 -> 8199.78 | G11: =-SUMIFS(CxP!$K$6:$K$163,CxP!$X$6:$X$163,$B11,CxP!$Y$6:$Y$163,"Si",CxP!$B$6:$B$163,">="&DATE(2026,G$3,1),CxP!$B$6:$B$163,"<="&EOMONTH(DATE(2026,G$3,1),0))-SUMIFS(CxP!$M$6:$M$163,CxP!$X$6:$X$163,$B11,CxP!$Y$6:$Y$163,"Si",CxP!$B$6:$B$163,">="&DATE(2026,G$3,1),CxP!$B$6:$B$163,"<="&EOMONTH(DATE(2026,G$3,1),0))+SUMIFS('Extractos bancarios - Manglar'!$C:$C,'Extractos bancarios - Manglar'!$G:$G,$B11,'Extractos bancarios - Manglar'!$L:$L,G$3,'Extractos bancarios - Manglar'!$M:$M,"")-SUMIFS('Extractos bancarios - Manglar'!$C:$C,'Extractos bancarios - Manglar'!$G:$G,$B11,'Extractos bancarios - Manglar'!$L:$L,G$3,'Extractos bancarios - Manglar'!$M:$M,"",'Extractos bancarios - Manglar'!$K:$K,"Si")*0.19/1.19 -> -114199 | H11: =-SUMIFS(CxP!$K$6:$K$163,CxP!$X$6:$X$163,$B11,CxP!$Y$6:$Y$163,"Si",CxP!$B$6:$B$163,">="&DATE(2026,H$3,1),CxP!$B$6:$B$163,"<="&EOMONTH(DATE(2026,H$3,1),0))-SUMIFS(CxP!$M$6:$M$163,CxP!$X$6:$X$163,$B11,CxP!$Y$6:$Y$163,"Si",CxP!$B$6:$B$163,">="&DATE(2026,H$3,1),CxP!$B$6:$B$163,"<="&EOMONTH(DATE(2026,H$3,1),0))+SUMIFS('Extractos bancarios - Manglar'!$C:$C,'Extractos bancarios - Manglar'!$G:$G,$B11,'Extractos bancarios - Manglar'!$L:$L,H$3,'Extractos bancarios - Manglar'!$M:$M,"")-SUMIFS('Extractos bancarios - Manglar'!$C:$C,'Extractos bancarios - Manglar'!$G:$G,$B11,'Extractos bancarios - Manglar'!$L:$L,H$3,'Extractos bancarios - Manglar'!$M:$M,"",'Extractos bancarios - Manglar'!$K:$K,"Si")*0.19/1.19 -> -382139.66 | I11: =-SUMIFS(CxP!$K$6:$K$163,CxP!$X$6:$X$163,$B11,CxP!$Y$6:$Y$163,"Si",CxP!$B$6:$B$163,">="&DATE(2026,I$3,1),CxP!$B$6:$B$163,"<="&EOMONTH(DATE(2026,I$3,1),0))-SUMIFS(CxP!$M$6:$M$163,CxP!$X$6:$X$163,$B11,CxP!$Y$6:$Y$163,"Si",CxP!$B$6:$B$163,">="&DATE(2026,I$3,1),CxP!$B$6:$B$163,"<="&EOMONTH(DATE(2026,I$3,1),0))+SUMIFS('Extractos bancarios - Manglar'!$C:$C,'Extractos bancarios - Manglar'!$G:$G,$B11,'Extractos bancarios - Manglar'!$L:$L,I$3,'Extractos bancarios - Manglar'!$M:$M,"")-SUMIFS('Extractos bancarios - Manglar'!$C:$C,'Extractos bancarios - Manglar'!$G:$G,$B11,'Extractos bancarios - Manglar'!$L:$L,I$3,'Extractos bancarios - Manglar'!$M:$M,"",'Extractos bancarios - Manglar'!$K:$K,"Si")*0.19/1.19 -> -386753.79 | J11: =-SUMIFS(CxP!$K$6:$K$163,CxP!$X$6:$X$163,$B11,CxP!$Y$6:$Y$163,"Si",CxP!$B$6:$B$163,">="&DATE(2026,J$3,1),CxP!$B$6:$B$163,"<="&EOMONTH(DATE(2026,J$3,1),0))-SUMIFS(CxP!$M$6:$M$163,CxP!$X$6:$X$163,$B11,CxP!$Y$6:$Y$163,"Si",CxP!$B$6:$B$163,">="&DATE(2026,J$3,1),CxP!$B$6:$B$163,"<="&EOMONTH(DATE(2026,J$3,1),0))+SUMIFS('Extractos bancarios - Manglar'!$C:$C,'Extractos bancarios - Manglar'!$G:$G,$B11,'Extractos bancarios - Manglar'!$L:$L,J$3,'Extractos bancarios - Manglar'!$M:$M,"")-SUMIFS('Extractos bancarios - Manglar'!$C:$C,'Extractos bancarios - Manglar'!$G:$G,$B11,'Extractos bancarios - Manglar'!$L:$L,J$3,'Extractos bancarios - Manglar'!$M:$M,"",'Extractos bancarios - Manglar'!$K:$K,"Si")*0.19/1.19 -> -159676.11 | ... N11: =-SUMIFS(CxP!$K$6:$K$163,CxP!$X$6:$X$163,$B11,CxP!$Y$6:$Y$163,"Si",CxP!$B$6:$B$163,">="&DATE(2026,N$3,1),CxP!$B$6:$B$163,"<="&EOMONTH(DATE(2026,N$3,1),0))-SUMIFS(CxP!$M$6:$M$163,CxP!$X$6:$X$163,$B11,CxP!$Y$6:$Y$163,"Si",CxP!$B$6:$B$163,">="&DATE(2026,N$3,1),CxP!$B$6:$B$163,"<="&EOMONTH(DATE(2026,N$3,1),0))+SUMIFS('Extractos bancarios - Manglar'!$C:$C,'Extractos bancarios - Manglar'!$G:$G,$B11,'Extractos bancarios - Manglar'!$L:$L,N$3,'Extractos bancarios - Manglar'!$M:$M,"")-SUMIFS('Extractos bancarios - Manglar'!$C:$C,'Extractos bancarios - Manglar'!$G:$G,$B11,'Extractos bancarios - Manglar'!$L:$L,N$3,'Extractos bancarios - Manglar'!$M:$M,"",'Extractos bancarios - Manglar'!$K:$K,"Si")*0.19/1.19 -> 0 | O11: =+SUM(C11:N11) -> -1666908.3
B12: Otros Gastos | C12: =SUMIFS('Extractos bancarios - Manglar'!$C:$C,'Extractos bancarios - Manglar'!$G:$G,$B12,'Extractos bancarios - Manglar'!$L:$L,C$3) -> 0 | D12: =SUMIFS('Extractos bancarios - Manglar'!$C:$C,'Extractos bancarios - Manglar'!$G:$G,$B12,'Extractos bancarios - Manglar'!$L:$L,D$3) -> 0 | E12: =SUMIFS('Extractos bancarios - Manglar'!$C:$C,'Extractos bancarios - Manglar'!$G:$G,$B12,'Extractos bancarios - Manglar'!$L:$L,E$3) -> 0 | F12: =SUMIFS('Extractos bancarios - Manglar'!$C:$C,'Extractos bancarios - Manglar'!$G:$G,$B12,'Extractos bancarios - Manglar'!$L:$L,F$3) -> 0 | G12: =SUMIFS('Extractos bancarios - Manglar'!$C:$C,'Extractos bancarios - Manglar'!$G:$G,$B12,'Extractos bancarios - Manglar'!$L:$L,G$3) -> 0 | H12: =SUMIFS('Extractos bancarios - Manglar'!$C:$C,'Extractos bancarios - Manglar'!$G:$G,$B12,'Extractos bancarios - Manglar'!$L:$L,H$3) -> 0 | I12: =SUMIFS('Extractos bancarios - Manglar'!$C:$C,'Extractos bancarios - Manglar'!$G:$G,$B12,'Extractos bancarios - Manglar'!$L:$L,I$3) -> 0 | J12: =SUMIFS('Extractos bancarios - Manglar'!$C:$C,'Extractos bancarios - Manglar'!$G:$G,$B12,'Extractos bancarios - Manglar'!$L:$L,J$3) -> 0 | ... N12: =SUMIFS('Extractos bancarios - Manglar'!$C:$C,'Extractos bancarios - Manglar'!$G:$G,$B12,'Extractos bancarios - Manglar'!$L:$L,N$3) -> 0 | O12: =+SUM(C12:N12) -> 0
B13: Resultado Final | C13: =C6+SUM(C8:C12) -> 0 | D13: =D6+SUM(D8:D12) -> 0 | E13: =E6+SUM(E8:E12) -> -789523.77 | F13: =F6+SUM(F8:F12) -> 27930296 | G13: =G6+SUM(G8:G12) -> 2.441468e+08 | H13: =H6+SUM(H8:H12) -> -1.6676622e+08 | I13: =I6+SUM(I8:I12) -> -8657065.1 | J13: =J6+SUM(J8:J12) -> 43231220 | ... N13: =N6+SUM(N8:N12) -> 0 | O13: =+SUM(C13:N13) -> 99843742
B14: Margen % | C14: =IFERROR(+C13/C$4,"-") -> - | D14: =IFERROR(+D13/D$4,"-") -> - | E14: =IFERROR(+E13/E$4,"-") -> - | F14: =IFERROR(+F13/F$4,"-") -> 0.69877145 | G14: =IFERROR(+G13/G$4,"-") -> 0.94836986 | H14: =IFERROR(+H13/H$4,"-") -> - | I14: =IFERROR(+I13/I$4,"-") -> -0.20310351 | J14: =IFERROR(+J13/J$4,"-") -> 0.68944281 | ... O14: =IFERROR(+O13/O$4,"-") -> 0.2051521
B16: Flujo de Caja
B17: Saldo Inicial | C17: 0 | D17: =C27 -> 0 | E17: =D27 -> 0 | F17: =E27 -> 3628284.1 | G17: =F27 -> 46685528 | H17: =G27 -> 2.514566e+08 | I17: =H27 -> 1.9504544e+08 | J17: =I27 -> 1.0426245e+08 | K17: =J27 -> 75999625 | ... N17: =M27 -> 63360593
B18: Ingresos | C18: =SUMIFS('Extractos bancarios - Manglar'!$C:$C,'Extractos bancarios - Manglar'!$G:$G,$B18,'Extractos bancarios - Manglar'!$F:$F,C$3) -> 0 | D18: =SUMIFS('Extractos bancarios - Manglar'!$C:$C,'Extractos bancarios - Manglar'!$G:$G,$B18,'Extractos bancarios - Manglar'!$F:$F,D$3) -> 0 | E18: =SUMIFS('Extractos bancarios - Manglar'!$C:$C,'Extractos bancarios - Manglar'!$G:$G,$B18,'Extractos bancarios - Manglar'!$F:$F,E$3) -> 0 | F18: =SUMIFS('Extractos bancarios - Manglar'!$C:$C,'Extractos bancarios - Manglar'!$G:$G,$B18,'Extractos bancarios - Manglar'!$F:$F,F$3) -> 46656750 | G18: =SUMIFS('Extractos bancarios - Manglar'!$C:$C,'Extractos bancarios - Manglar'!$G:$G,$B18,'Extractos bancarios - Manglar'!$F:$F,G$3) -> 247410429 | H18: =SUMIFS('Extractos bancarios - Manglar'!$C:$C,'Extractos bancarios - Manglar'!$G:$G,$B18,'Extractos bancarios - Manglar'!$F:$F,H$3) -> 47109266 | I18: =SUMIFS('Extractos bancarios - Manglar'!$C:$C,'Extractos bancarios - Manglar'!$G:$G,$B18,'Extractos bancarios - Manglar'!$F:$F,I$3) -> 20102227 | J18: =SUMIFS('Extractos bancarios - Manglar'!$C:$C,'Extractos bancarios - Manglar'!$G:$G,$B18,'Extractos bancarios - Manglar'!$F:$F,J$3) -> 28009175 | ... N18: =SUMIFS('Extractos bancarios - Manglar'!$C:$C,'Extractos bancarios - Manglar'!$G:$G,$B18,'Extractos bancarios - Manglar'!$F:$F,N$3) -> 0
B19: Otros Ingresos | C19: =SUMIFS('Extractos bancarios - Manglar'!$C:$C,'Extractos bancarios - Manglar'!$G:$G,$B19,'Extractos bancarios - Manglar'!$F:$F,C$3) -> 0 | D19: =SUMIFS('Extractos bancarios - Manglar'!$C:$C,'Extractos bancarios - Manglar'!$G:$G,$B19,'Extractos bancarios - Manglar'!$F:$F,D$3) -> 0 | E19: =SUMIFS('Extractos bancarios - Manglar'!$C:$C,'Extractos bancarios - Manglar'!$G:$G,$B19,'Extractos bancarios - Manglar'!$F:$F,E$3) -> 4500000 | F19: =SUMIFS('Extractos bancarios - Manglar'!$C:$C,'Extractos bancarios - Manglar'!$G:$G,$B19,'Extractos bancarios - Manglar'!$F:$F,F$3) -> 6500000 | G19: =SUMIFS('Extractos bancarios - Manglar'!$C:$C,'Extractos bancarios - Manglar'!$G:$G,$B19,'Extractos bancarios - Manglar'!$F:$F,G$3) -> 0 | H19: =SUMIFS('Extractos bancarios - Manglar'!$C:$C,'Extractos bancarios - Manglar'!$G:$G,$B19,'Extractos bancarios - Manglar'!$F:$F,H$3) -> 0 | I19: =SUMIFS('Extractos bancarios - Manglar'!$C:$C,'Extractos bancarios - Manglar'!$G:$G,$B19,'Extractos bancarios - Manglar'!$F:$F,I$3) -> 0 | J19: =SUMIFS('Extractos bancarios - Manglar'!$C:$C,'Extractos bancarios - Manglar'!$G:$G,$B19,'Extractos bancarios - Manglar'!$F:$F,J$3) -> 0 | ... N19: =SUMIFS('Extractos bancarios - Manglar'!$C:$C,'Extractos bancarios - Manglar'!$G:$G,$B19,'Extractos bancarios - Manglar'!$F:$F,N$3) -> 0
B20: Costo Ventas | C20: =SUMIFS('Extractos bancarios - Manglar'!$C:$C,'Extractos bancarios - Manglar'!$G:$G,$B20,'Extractos bancarios - Manglar'!$F:$F,C$3) -> 0 | D20: =SUMIFS('Extractos bancarios - Manglar'!$C:$C,'Extractos bancarios - Manglar'!$G:$G,$B20,'Extractos bancarios - Manglar'!$F:$F,D$3) -> 0 | E20: =SUMIFS('Extractos bancarios - Manglar'!$C:$C,'Extractos bancarios - Manglar'!$G:$G,$B20,'Extractos bancarios - Manglar'!$F:$F,E$3) -> 0 | F20: =SUMIFS('Extractos bancarios - Manglar'!$C:$C,'Extractos bancarios - Manglar'!$G:$G,$B20,'Extractos bancarios - Manglar'!$F:$F,F$3) -> -9862800 | G20: =SUMIFS('Extractos bancarios - Manglar'!$C:$C,'Extractos bancarios - Manglar'!$G:$G,$B20,'Extractos bancarios - Manglar'!$F:$F,G$3) -> -35504330 | H20: =SUMIFS('Extractos bancarios - Manglar'!$C:$C,'Extractos bancarios - Manglar'!$G:$G,$B20,'Extractos bancarios - Manglar'!$F:$F,H$3) -> -98158229 | I20: =SUMIFS('Extractos bancarios - Manglar'!$C:$C,'Extractos bancarios - Manglar'!$G:$G,$B20,'Extractos bancarios - Manglar'!$F:$F,I$3) -> -90085008 | J20: =SUMIFS('Extractos bancarios - Manglar'!$C:$C,'Extractos bancarios - Manglar'!$G:$G,$B20,'Extractos bancarios - Manglar'!$F:$F,J$3) -> -36896839 | ... N20: =SUMIFS('Extractos bancarios - Manglar'!$C:$C,'Extractos bancarios - Manglar'!$G:$G,$B20,'Extractos bancarios - Manglar'!$F:$F,N$3) -> 0
B21: Costos Fijos | C21: =SUMIFS('Extractos bancarios - Manglar'!$C:$C,'Extractos bancarios - Manglar'!$G:$G,$B21,'Extractos bancarios - Manglar'!$F:$F,C$3) -> 0 | D21: =SUMIFS('Extractos bancarios - Manglar'!$C:$C,'Extractos bancarios - Manglar'!$G:$G,$B21,'Extractos bancarios - Manglar'!$F:$F,D$3) -> 0 | E21: =SUMIFS('Extractos bancarios - Manglar'!$C:$C,'Extractos bancarios - Manglar'!$G:$G,$B21,'Extractos bancarios - Manglar'!$F:$F,E$3) -> -18050 | F21: =SUMIFS('Extractos bancarios - Manglar'!$C:$C,'Extractos bancarios - Manglar'!$G:$G,$B21,'Extractos bancarios - Manglar'!$F:$F,F$3) -> -18050 | G21: =SUMIFS('Extractos bancarios - Manglar'!$C:$C,'Extractos bancarios - Manglar'!$G:$G,$B21,'Extractos bancarios - Manglar'!$F:$F,G$3) -> -18050 | H21: =SUMIFS('Extractos bancarios - Manglar'!$C:$C,'Extractos bancarios - Manglar'!$G:$G,$B21,'Extractos bancarios - Manglar'!$F:$F,H$3) -> -18050 | I21: =SUMIFS('Extractos bancarios - Manglar'!$C:$C,'Extractos bancarios - Manglar'!$G:$G,$B21,'Extractos bancarios - Manglar'!$F:$F,I$3) -> -18050 | J21: =SUMIFS('Extractos bancarios - Manglar'!$C:$C,'Extractos bancarios - Manglar'!$G:$G,$B21,'Extractos bancarios - Manglar'!$F:$F,J$3) -> -18050 | ... N21: =SUMIFS('Extractos bancarios - Manglar'!$C:$C,'Extractos bancarios - Manglar'!$G:$G,$B21,'Extractos bancarios - Manglar'!$F:$F,N$3) -> 0
B22: Costos Operacionales | C22: =SUMIFS('Extractos bancarios - Manglar'!$C:$C,'Extractos bancarios - Manglar'!$G:$G,$B22,'Extractos bancarios - Manglar'!$F:$F,C$3) -> 0 | D22: =SUMIFS('Extractos bancarios - Manglar'!$C:$C,'Extractos bancarios - Manglar'!$G:$G,$B22,'Extractos bancarios - Manglar'!$F:$F,D$3) -> 0 | E22: =SUMIFS('Extractos bancarios - Manglar'!$C:$C,'Extractos bancarios - Manglar'!$G:$G,$B22,'Extractos bancarios - Manglar'!$F:$F,E$3) -> -844704 | F22: =SUMIFS('Extractos bancarios - Manglar'!$C:$C,'Extractos bancarios - Manglar'!$G:$G,$B22,'Extractos bancarios - Manglar'!$F:$F,F$3) -> -222529 | G22: =SUMIFS('Extractos bancarios - Manglar'!$C:$C,'Extractos bancarios - Manglar'!$G:$G,$B22,'Extractos bancarios - Manglar'!$F:$F,G$3) -> -679448 | H22: =SUMIFS('Extractos bancarios - Manglar'!$C:$C,'Extractos bancarios - Manglar'!$G:$G,$B22,'Extractos bancarios - Manglar'!$F:$F,H$3) -> -1136030 | I22: =SUMIFS('Extractos bancarios - Manglar'!$C:$C,'Extractos bancarios - Manglar'!$G:$G,$B22,'Extractos bancarios - Manglar'!$F:$F,I$3) -> -12831543 | J22: =SUMIFS('Extractos bancarios - Manglar'!$C:$C,'Extractos bancarios - Manglar'!$G:$G,$B22,'Extractos bancarios - Manglar'!$F:$F,J$3) -> -788548.33 | ... N22: =SUMIFS('Extractos bancarios - Manglar'!$C:$C,'Extractos bancarios - Manglar'!$G:$G,$B22,'Extractos bancarios - Manglar'!$F:$F,N$3) -> 0
B23: Gastos Variables | C23: =SUMIFS('Extractos bancarios - Manglar'!$C:$C,'Extractos bancarios - Manglar'!$G:$G,$B23,'Extractos bancarios - Manglar'!$F:$F,C$3) -> 0 | D23: =SUMIFS('Extractos bancarios - Manglar'!$C:$C,'Extractos bancarios - Manglar'!$G:$G,$B23,'Extractos bancarios - Manglar'!$F:$F,D$3) -> 0 | E23: =SUMIFS('Extractos bancarios - Manglar'!$C:$C,'Extractos bancarios - Manglar'!$G:$G,$B23,'Extractos bancarios - Manglar'!$F:$F,E$3) -> -7519.77 | F23: =SUMIFS('Extractos bancarios - Manglar'!$C:$C,'Extractos bancarios - Manglar'!$G:$G,$B23,'Extractos bancarios - Manglar'!$F:$F,F$3) -> 8199.78 | G23: =SUMIFS('Extractos bancarios - Manglar'!$C:$C,'Extractos bancarios - Manglar'!$G:$G,$B23,'Extractos bancarios - Manglar'!$F:$F,G$3) -> -114199 | H23: =SUMIFS('Extractos bancarios - Manglar'!$C:$C,'Extractos bancarios - Manglar'!$G:$G,$B23,'Extractos bancarios - Manglar'!$F:$F,H$3) -> -382139.66 | I23: =SUMIFS('Extractos bancarios - Manglar'!$C:$C,'Extractos bancarios - Manglar'!$G:$G,$B23,'Extractos bancarios - Manglar'!$F:$F,I$3) -> -386753.79 | J23: =SUMIFS('Extractos bancarios - Manglar'!$C:$C,'Extractos bancarios - Manglar'!$G:$G,$B23,'Extractos bancarios - Manglar'!$F:$F,J$3) -> -159676.11 | ... N23: =SUMIFS('Extractos bancarios - Manglar'!$C:$C,'Extractos bancarios - Manglar'!$G:$G,$B23,'Extractos bancarios - Manglar'!$F:$F,N$3) -> 0
B24: Otros Gastos | C24: =SUMIFS('Extractos bancarios - Manglar'!$C:$C,'Extractos bancarios - Manglar'!$G:$G,$B24,'Extractos bancarios - Manglar'!$F:$F,C$3) -> 0 | D24: =SUMIFS('Extractos bancarios - Manglar'!$C:$C,'Extractos bancarios - Manglar'!$G:$G,$B24,'Extractos bancarios - Manglar'!$F:$F,D$3) -> 0 | E24: =SUMIFS('Extractos bancarios - Manglar'!$C:$C,'Extractos bancarios - Manglar'!$G:$G,$B24,'Extractos bancarios - Manglar'!$F:$F,E$3) -> 0 | F24: =SUMIFS('Extractos bancarios - Manglar'!$C:$C,'Extractos bancarios - Manglar'!$G:$G,$B24,'Extractos bancarios - Manglar'!$F:$F,F$3) -> 0 | G24: =SUMIFS('Extractos bancarios - Manglar'!$C:$C,'Extractos bancarios - Manglar'!$G:$G,$B24,'Extractos bancarios - Manglar'!$F:$F,G$3) -> -2500000 | H24: =SUMIFS('Extractos bancarios - Manglar'!$C:$C,'Extractos bancarios - Manglar'!$G:$G,$B24,'Extractos bancarios - Manglar'!$F:$F,H$3) -> 0 | I24: =SUMIFS('Extractos bancarios - Manglar'!$C:$C,'Extractos bancarios - Manglar'!$G:$G,$B24,'Extractos bancarios - Manglar'!$F:$F,I$3) -> -7553270 | J24: =SUMIFS('Extractos bancarios - Manglar'!$C:$C,'Extractos bancarios - Manglar'!$G:$G,$B24,'Extractos bancarios - Manglar'!$F:$F,J$3) -> 0 | ... N24: =SUMIFS('Extractos bancarios - Manglar'!$C:$C,'Extractos bancarios - Manglar'!$G:$G,$B24,'Extractos bancarios - Manglar'!$F:$F,N$3) -> 0
B25: (-) Distribución Socios | C25: =SUMIFS('Extractos bancarios - Manglar'!$C:$C,'Extractos bancarios - Manglar'!$G:$G,$B25,'Extractos bancarios - Manglar'!$F:$F,C$3) -> 0 | D25: =SUMIFS('Extractos bancarios - Manglar'!$C:$C,'Extractos bancarios - Manglar'!$G:$G,$B25,'Extractos bancarios - Manglar'!$F:$F,D$3) -> 0 | E25: =SUMIFS('Extractos bancarios - Manglar'!$C:$C,'Extractos bancarios - Manglar'!$G:$G,$B25,'Extractos bancarios - Manglar'!$F:$F,E$3) -> 0 | F25: =SUMIFS('Extractos bancarios - Manglar'!$C:$C,'Extractos bancarios - Manglar'!$G:$G,$B25,'Extractos bancarios - Manglar'!$F:$F,F$3) -> 0 | G25: =SUMIFS('Extractos bancarios - Manglar'!$C:$C,'Extractos bancarios - Manglar'!$G:$G,$B25,'Extractos bancarios - Manglar'!$F:$F,G$3) -> 0 | H25: =SUMIFS('Extractos bancarios - Manglar'!$C:$C,'Extractos bancarios - Manglar'!$G:$G,$B25,'Extractos bancarios - Manglar'!$F:$F,H$3) -> 0 | I25: =SUMIFS('Extractos bancarios - Manglar'!$C:$C,'Extractos bancarios - Manglar'!$G:$G,$B25,'Extractos bancarios - Manglar'!$F:$F,I$3) -> 0 | J25: =SUMIFS('Extractos bancarios - Manglar'!$C:$C,'Extractos bancarios - Manglar'!$G:$G,$B25,'Extractos bancarios - Manglar'!$F:$F,J$3) -> 0 | ... N25: =SUMIFS('Extractos bancarios - Manglar'!$C:$C,'Extractos bancarios - Manglar'!$G:$G,$B25,'Extractos bancarios - Manglar'!$F:$F,N$3) -> 0 | O25: =SUM(C25:N25) -> 0
B26: (-) Impuestos y IVA pagados | C26: =SUMIFS('Extractos bancarios - Manglar'!$C:$C,'Extractos bancarios - Manglar'!$G:$G,"Impuestos",'Extractos bancarios - Manglar'!$F:$F,C$3)+SUMIFS('Extractos bancarios - Manglar'!$C:$C,'Extractos bancarios - Manglar'!$G:$G,"Imp x Pagar - IVA",'Extractos bancarios - Manglar'!$F:$F,C$3) -> 0 | D26: =SUMIFS('Extractos bancarios - Manglar'!$C:$C,'Extractos bancarios - Manglar'!$G:$G,"Impuestos",'Extractos bancarios - Manglar'!$F:$F,D$3)+SUMIFS('Extractos bancarios - Manglar'!$C:$C,'Extractos bancarios - Manglar'!$G:$G,"Imp x Pagar - IVA",'Extractos bancarios - Manglar'!$F:$F,D$3) -> 0 | E26: =SUMIFS('Extractos bancarios - Manglar'!$C:$C,'Extractos bancarios - Manglar'!$G:$G,"Impuestos",'Extractos bancarios - Manglar'!$F:$F,E$3)+SUMIFS('Extractos bancarios - Manglar'!$C:$C,'Extractos bancarios - Manglar'!$G:$G,"Imp x Pagar - IVA",'Extractos bancarios - Manglar'!$F:$F,E$3) -> -1442.1 | F26: =SUMIFS('Extractos bancarios - Manglar'!$C:$C,'Extractos bancarios - Manglar'!$G:$G,"Impuestos",'Extractos bancarios - Manglar'!$F:$F,F$3)+SUMIFS('Extractos bancarios - Manglar'!$C:$C,'Extractos bancarios - Manglar'!$G:$G,"Imp x Pagar - IVA",'Extractos bancarios - Manglar'!$F:$F,F$3) -> -4326.3 | G26: =SUMIFS('Extractos bancarios - Manglar'!$C:$C,'Extractos bancarios - Manglar'!$G:$G,"Impuestos",'Extractos bancarios - Manglar'!$F:$F,G$3)+SUMIFS('Extractos bancarios - Manglar'!$C:$C,'Extractos bancarios - Manglar'!$G:$G,"Imp x Pagar - IVA",'Extractos bancarios - Manglar'!$F:$F,G$3) -> -3823326 | H26: =SUMIFS('Extractos bancarios - Manglar'!$C:$C,'Extractos bancarios - Manglar'!$G:$G,"Impuestos",'Extractos bancarios - Manglar'!$F:$F,H$3)+SUMIFS('Extractos bancarios - Manglar'!$C:$C,'Extractos bancarios - Manglar'!$G:$G,"Imp x Pagar - IVA",'Extractos bancarios - Manglar'!$F:$F,H$3) -> -3825978.3 | I26: =SUMIFS('Extractos bancarios - Manglar'!$C:$C,'Extractos bancarios - Manglar'!$G:$G,"Impuestos",'Extractos bancarios - Manglar'!$F:$F,I$3)+SUMIFS('Extractos bancarios - Manglar'!$C:$C,'Extractos bancarios - Manglar'!$G:$G,"Imp x Pagar - IVA",'Extractos bancarios - Manglar'!$F:$F,I$3) -> -10598.1 | J26: =SUMIFS('Extractos bancarios - Manglar'!$C:$C,'Extractos bancarios - Manglar'!$G:$G,"Impuestos",'Extractos bancarios - Manglar'!$F:$F,J$3)+SUMIFS('Extractos bancarios - Manglar'!$C:$C,'Extractos bancarios - Manglar'!$G:$G,"Imp x Pagar - IVA",'Extractos bancarios - Manglar'!$F:$F,J$3) -> -18408884 | ... N26: =SUMIFS('Extractos bancarios - Manglar'!$C:$C,'Extractos bancarios - Manglar'!$G:$G,"Impuestos",'Extractos bancarios - Manglar'!$F:$F,N$3)+SUMIFS('Extractos bancarios - Manglar'!$C:$C,'Extractos bancarios - Manglar'!$G:$G,"Imp x Pagar - IVA",'Extractos bancarios - Manglar'!$F:$F,N$3) -> 0 | O26: =SUM(C26:N26) -> -44299223
B27: Saldo Final | C27: =C17+C18+C19+SUM(C20:C24)+C25+C26 -> 0 | D27: =D17+D18+D19+SUM(D20:D24)+D25+D26 -> 0 | E27: =E17+E18+E19+SUM(E20:E24)+E25+E26 -> 3628284.1 | F27: =F17+F18+F19+SUM(F20:F24)+F25+F26 -> 46685528 | G27: =G17+G18+G19+SUM(G20:G24)+G25+G26 -> 2.514566e+08 | H27: =H17+H18+H19+SUM(H20:H24)+H25+H26 -> 1.9504544e+08 | I27: =I17+I18+I19+SUM(I20:I24)+I25+I26 -> 1.0426245e+08 | J27: =J17+J18+J19+SUM(J20:J24)+J25+J26 -> 75999625 | ... N27: =N17+N18+N19+SUM(N20:N24)+N25+N26 -> 63360593
B32: Punto de Equilibrio
B33: Gastos Fijos Mensuales Proyectados | M33: ='Costos Fijos'!P4 -> 8329123.3 | N33: ='Costos Fijos'!Q4 -> 8329123.3
B34: Margen Bruto objetivo | M34: 0.2 | N34: 0.2
B35: Ventas Miinimas Requeridas | M35: =M33/M34 -> 41645617 | N35: =N33/N34 -> 41645617
B36: Costo de Ventas Implicito | M36: =M35*(1-M34) -> 33316493 | N36: =N35*(1-N34) -> 33316493
B39: Check
B40: Suma de todos los movimientos | C40: =SUM('Extractos bancarios - Manglar'!$C:$C) -> 63360593
B41: Capturado por el flujo de caja | C41: =SUM(C18:N24)+SUM(C25:N26) -> 63360593
B42: Diferencia (debe ser 0) | C42: =C40-C41 -> 0
B43: Movimientos en cuenta "Revisar" | C43: =SUMIFS('Extractos bancarios - Manglar'!$C:$C,'Extractos bancarios - Manglar'!$G:$G,"Revisar") -> 0
B45: Ingresos facturados (P&G) | C45: =O4 -> 486681543
B46: Ingresos cobrados (neto de IVA) | C46: =(SUMIFS('Extractos bancarios - Manglar'!$C:$C,'Extractos bancarios - Manglar'!$G:$G,"Ingresos",'Extractos bancarios - Manglar'!$K:$K,"Si")/1.19)+SUMIFS('Extractos bancarios - Manglar'!$C:$C,'Extractos bancarios - Manglar'!$G:$G,"Ingresos",'Extractos bancarios - Manglar'!$K:$K,"No")+SUMIFS('Extractos bancarios - Manglar'!$C:$C,'Extractos bancarios - Manglar'!$G:$G,"Ingresos",'Extractos bancarios - Manglar'!$K:$K,"NA") -> 4.5509889e+08
B47: Diferencia (cartera y retenciones) | C47: =C45-C46 -> 31582650
B50: Cobertura de costos
B51: Costo total del P&G | C51: =O5+O9+O10+O11 -> -3.868378e+08
B52: de facturas del CxP | C52: =-(SUMIFS(CxP!$K$6:$K$163,CxP!$X$6:$X$163,"Costo Ventas",CxP!$Y$6:$Y$163,"Si",CxP!$B$6:$B$163,">="&DATE(2026,1,1),CxP!$B$6:$B$163,"<="&DATE(2026,12,31))+SUMIFS(CxP!$K$6:$K$163,CxP!$X$6:$X$163,"Costos Fijos",CxP!$Y$6:$Y$163,"Si",CxP!$B$6:$B$163,">="&DATE(2026,1,1),CxP!$B$6:$B$163,"<="&DATE(2026,12,31))+SUMIFS(CxP!$K$6:$K$163,CxP!$X$6:$X$163,"Costos Operacionales",CxP!$Y$6:$Y$163,"Si",CxP!$B$6:$B$163,">="&DATE(2026,1,1),CxP!$B$6:$B$163,"<="&DATE(2026,12,31))+SUMIFS(CxP!$K$6:$K$163,CxP!$X$6:$X$163,"Gastos Variables",CxP!$Y$6:$Y$163,"Si",CxP!$B$6:$B$163,">="&DATE(2026,1,1),CxP!$B$6:$B$163,"<="&DATE(2026,12,31)))-(SUMIFS(CxP!$M$6:$M$163,CxP!$X$6:$X$163,"Costo Ventas",CxP!$Y$6:$Y$163,"Si",CxP!$B$6:$B$163,">="&DATE(2026,1,1),CxP!$B$6:$B$163,"<="&DATE(2026,12,31))+SUMIFS(CxP!$M$6:$M$163,CxP!$X$6:$X$163,"Costos Fijos",CxP!$Y$6:$Y$163,"Si",CxP!$B$6:$B$163,">="&DATE(2026,1,1),CxP!$B$6:$B$163,"<="&DATE(2026,12,31))+SUMIFS(CxP!$M$6:$M$163,CxP!$X$6:$X$163,"Costos Operacionales",CxP!$Y$6:$Y$163,"Si",CxP!$B$6:$B$163,">="&DATE(2026,1,1),CxP!$B$6:$B$163,"<="&DATE(2026,12,31))+SUMIFS(CxP!$M$6:$M$163,CxP!$X$6:$X$163,"Gastos Variables",CxP!$Y$6:$Y$163,"Si",CxP!$B$6:$B$163,">="&DATE(2026,1,1),CxP!$B$6:$B$163,"<="&DATE(2026,12,31))) -> -3.5070587e+08
B53: de movimientos sin factura | C53: =C51-C52 -> -36131934
B55: Costos que no llegan al P&G
B56: Facturas sin cliente asignado | C56: =-SUMIFS(CxP!$K$6:$K$163,CxP!$X$6:$X$163,"Por clasificar")-SUMIFS(CxP!$M$6:$M$163,CxP!$X$6:$X$163,"Por clasificar") -> -9257047.1
B57: Facturas excluidas del P&G a mano | C57: =-(SUMIFS(CxP!$K$6:$K$163,CxP!$X$6:$X$163,"Costo Ventas",CxP!$B$6:$B$163,">="&DATE(2026,1,1),CxP!$B$6:$B$163,"<="&DATE(2026,12,31))+SUMIFS(CxP!$K$6:$K$163,CxP!$X$6:$X$163,"Costos Fijos",CxP!$B$6:$B$163,">="&DATE(2026,1,1),CxP!$B$6:$B$163,"<="&DATE(2026,12,31))+SUMIFS(CxP!$K$6:$K$163,CxP!$X$6:$X$163,"Costos Operacionales",CxP!$B$6:$B$163,">="&DATE(2026,1,1),CxP!$B$6:$B$163,"<="&DATE(2026,12,31))+SUMIFS(CxP!$K$6:$K$163,CxP!$X$6:$X$163,"Gastos Variables",CxP!$B$6:$B$163,">="&DATE(2026,1,1),CxP!$B$6:$B$163,"<="&DATE(2026,12,31)))-(SUMIFS(CxP!$M$6:$M$163,CxP!$X$6:$X$163,"Costo Ventas",CxP!$B$6:$B$163,">="&DATE(2026,1,1),CxP!$B$6:$B$163,"<="&DATE(2026,12,31))+SUMIFS(CxP!$M$6:$M$163,CxP!$X$6:$X$163,"Costos Fijos",CxP!$B$6:$B$163,">="&DATE(2026,1,1),CxP!$B$6:$B$163,"<="&DATE(2026,12,31))+SUMIFS(CxP!$M$6:$M$163,CxP!$X$6:$X$163,"Costos Operacionales",CxP!$B$6:$B$163,">="&DATE(2026,1,1),CxP!$B$6:$B$163,"<="&DATE(2026,12,31))+SUMIFS(CxP!$M$6:$M$163,CxP!$X$6:$X$163,"Gastos Variables",CxP!$B$6:$B$163,">="&DATE(2026,1,1),CxP!$B$6:$B$163,"<="&DATE(2026,12,31)))+(SUMIFS(CxP!$K$6:$K$163,CxP!$X$6:$X$163,"Costo Ventas",CxP!$Y$6:$Y$163,"Si",CxP!$B$6:$B$163,">="&DATE(2026,1,1),CxP!$B$6:$B$163,"<="&DATE(2026,12,31))+SUMIFS(CxP!$K$6:$K$163,CxP!$X$6:$X$163,"Costos Fijos",CxP!$Y$6:$Y$163,"Si",CxP!$B$6:$B$163,">="&DATE(2026,1,1),CxP!$B$6:$B$163,"<="&DATE(2026,12,31))+SUMIFS(CxP!$K$6:$K$163,CxP!$X$6:$X$163,"Costos Operacionales",CxP!$Y$6:$Y$163,"Si",CxP!$B$6:$B$163,">="&DATE(2026,1,1),CxP!$B$6:$B$163,"<="&DATE(2026,12,31))+SUMIFS(CxP!$K$6:$K$163,CxP!$X$6:$X$163,"Gastos Variables",CxP!$Y$6:$Y$163,"Si",CxP!$B$6:$B$163,">="&DATE(2026,1,1),CxP!$B$6:$B$163,"<="&DATE(2026,12,31)))+(SUMIFS(CxP!$M$6:$M$163,CxP!$X$6:$X$163,"Costo Ventas",CxP!$Y$6:$Y$163,"Si",CxP!$B$6:$B$163,">="&DATE(2026,1,1),CxP!$B$6:$B$163,"<="&DATE(2026,12,31))+SUMIFS(CxP!$M$6:$M$163,CxP!$X$6:$X$163,"Costos Fijos",CxP!$Y$6:$Y$163,"Si",CxP!$B$6:$B$163,">="&DATE(2026,1,1),CxP!$B$6:$B$163,"<="&DATE(2026,12,31))+SUMIFS(CxP!$M$6:$M$163,CxP!$X$6:$X$163,"Costos Operacionales",CxP!$Y$6:$Y$163,"Si",CxP!$B$6:$B$163,">="&DATE(2026,1,1),CxP!$B$6:$B$163,"<="&DATE(2026,12,31))+SUMIFS(CxP!$M$6:$M$163,CxP!$X$6:$X$163,"Gastos Variables",CxP!$Y$6:$Y$163,"Si",CxP!$B$6:$B$163,">="&DATE(2026,1,1),CxP!$B$6:$B$163,"<="&DATE(2026,12,31))) -> -2782113.5
B58: Total por resolver | C58: =C56+C57 -> -12039161
B60: Cada costo entra una sola vez: si la factura está en el CxP, el movimiento que la paga no se cuenta.
B61: Los movimientos sin factura son cargos del banco, licencias del exterior y pagos que aún no tienen soporte.
B67: To Do`s
B68: Agregar factura de 1.500 sep 29 (ver chat contabilidad)
B69: Agregar split de cuenta de cobro Juan (ver correo facturacion)
B75: CONCEPTO VALOR
B76: Bono amazon AXIS 319.760 | C76: M260110
B77: Bono amazon AXIS 336.280 | C77: M260111
B78: Rappi refrigerio Kasperksy 151.860 | C78: M260401
B79: Uber Cali aeropuerto 55.072 | C79: M260802
B80: Uber Medellin aeropuerto 83.154 | C80: M260803
B81: Uber Medellin aeropuerto 93.996 | C81: M260803
B82: Tiquete Cali (factura en correo de manglar) 424.370 | C82: Ver si esta factura

Sheet Extractos bancarios - Manglar
A1: Fecha | B1: Descripción banco | C1: Valor | D1: Categoría | E1: Descripción interna | F1: Mes Caja | G1: Cuenta | H1: Centro de costo | I1: Cliente | J1: Proyecto | K1: IVA? | L1: Mes (Causación P&G) | M1: Factura | N1: Comentarios | O1: Link | P1: https://docs.google.com/spreadsheets/d/18Om0REh-zkuZNfu-JHQBKEZbUhkMH-UE_ZbSgjpWadU/edit?gid=527771349#gid=527771349
A2: 46091 | B2: CONSIG LOCAL CAJ | C2: 2000000 | D2: Abono capital | E2: Abono Juan David | F2: 3 | G2: =IFERROR(VLOOKUP(D2,Data!$A:$B,2,0),"Revisar") -> Otros Ingresos | H2: NA | I2: {=_xlfn.XLOOKUP($H2,Data!$E:$E,Data!$F:$F,"Revisar",0)} -> NA | J2: {=_xlfn.XLOOKUP($H2,Data!$E:$E,Data!$G:$G,"Revisar",0)} -> NA | K2: No
A3: 46093 | B3: ABONO INTERESES AHORROS | C3: 8.19 | D3: Intereses | E3: Intereses | F3: 3 | G3: =IFERROR(VLOOKUP(D3,Data!$A:$B,2,0),"Revisar") -> Gastos Variables | H3: NA | I3: {=_xlfn.XLOOKUP($H3,Data!$E:$E,Data!$F:$F,"Revisar",0)} -> NA | J3: {=_xlfn.XLOOKUP($H3,Data!$E:$E,Data!$G:$G,"Revisar",0)} -> NA | K3: NA | L3: =F3 -> 3
A4: 46093 | B4: MANEJO TARJETA DEB 03 26 | C4: -18050 | D4: Cuota de manejo | E4: Cuota de manejo | F4: 3 | G4: =IFERROR(VLOOKUP(D4,Data!$A:$B,2,0),"Revisar") -> Costos Fijos | H4: NA | I4: {=_xlfn.XLOOKUP($H4,Data!$E:$E,Data!$F:$F,"Revisar",0)} -> NA | J4: {=_xlfn.XLOOKUP($H4,Data!$E:$E,Data!$G:$G,"Revisar",0)} -> NA | K4: NA | L4: =F4 -> 3
A5: 46093 | B5: AJUSTE INTERES AHORROS DB | C5: -0.02 | D5: Intereses | E5: Intereses | F5: 3 | G5: =IFERROR(VLOOKUP(D5,Data!$A:$B,2,0),"Revisar") -> Gastos Variables | H5: NA | I5: {=_xlfn.XLOOKUP($H5,Data!$E:$E,Data!$F:$F,"Revisar",0)} -> NA | J5: {=_xlfn.XLOOKUP($H5,Data!$E:$E,Data!$G:$G,"Revisar",0)} -> NA | K5: NA | L5: =F5 -> 3
A6: 46099 | B6: ABONO INTERESES AHORROS | C6: 16.26 | D6: Intereses | E6: Intereses | F6: 3 | G6: =IFERROR(VLOOKUP(D6,Data!$A:$B,2,0),"Revisar") -> Gastos Variables | H6: NA | I6: {=_xlfn.XLOOKUP($H6,Data!$E:$E,Data!$F:$F,"Revisar",0)} -> NA | J6: {=_xlfn.XLOOKUP($H6,Data!$E:$E,Data!$G:$G,"Revisar",0)} -> NA | K6: NA | L6: =F6 -> 3
A7: 46100 | B7: COMPRA EN EL ALTILLO | C7: -96100 | D7: Gastos representación | E7: Desayuno Kaspersky | F7: 3 | G7: =IFERROR(VLOOKUP(D7,Data!$A:$B,2,0),"Revisar") -> Costos Operacionales | I7: Kaspersky | J7: Gastos Representacion | K7: NA | L7: =F7 -> 3 | M7: FEST-4442
A8: 46104 | B8: ABONO INTERESES AHORROS | C8: 12.9 | D8: Intereses | E8: Intereses | F8: 3 | G8: =IFERROR(VLOOKUP(D8,Data!$A:$B,2,0),"Revisar") -> Gastos Variables | H8: NA | I8: {=_xlfn.XLOOKUP($H8,Data!$E:$E,Data!$F:$F,"Revisar",0)} -> NA | J8: {=_xlfn.XLOOKUP($H8,Data!$E:$E,Data!$G:$G,"Revisar",0)} -> NA | K8: NA | L8: =F8 -> 3
A9: 46104 | B9: SERVICIO TRANSFERENCIA VIRTUAL | C9: -7590 | D9: Costo transferencias | E9: Costo transferencias | F9: 3 | G9: =IFERROR(VLOOKUP(D9,Data!$A:$B,2,0),"Revisar") -> Gastos Variables | H9: NA | I9: {=_xlfn.XLOOKUP($H9,Data!$E:$E,Data!$F:$F,"Revisar",0)} -> NA | J9: {=_xlfn.XLOOKUP($H9,Data!$E:$E,Data!$G:$G,"Revisar",0)} -> NA | K9: NA | L9: =F9 -> 3
A10: 46104 | B10: TRANSFERENCIA VIRTUAL | C10: -748604 | D10: Servicios Prof | E10: Lexgra abogados | F10: 3 | G10: =IFERROR(VLOOKUP(D10,Data!$A:$B,2,0),"Revisar") -> Costos Operacionales | H10: NA | I10: {=_xlfn.XLOOKUP($H10,Data!$E:$E,Data!$F:$F,"Revisar",0)} -> NA | J10: {=_xlfn.XLOOKUP($H10,Data!$E:$E,Data!$G:$G,"Revisar",0)} -> NA | K10: NA | L10: =F10 -> 3 | M10: LXFE-420
A11: 46104 | B11: COBRO IVA PAGOS AUTOMATICOS | C11: -1442.1 | D11: IVA Descontable | E11: IVA Descontable | F11: 3 | G11: =IFERROR(VLOOKUP(D11,Data!$A:$B,2,0),"Revisar") -> Imp x Pagar - IVA | H11: NA | I11: {=_xlfn.XLOOKUP($H11,Data!$E:$E,Data!$F:$F,"Revisar",0)} -> NA | J11: {=_xlfn.XLOOKUP($H11,Data!$E:$E,Data!$G:$G,"Revisar",0)} -> NA | K11: NA | L11: =F11 -> 3
A12: 46106 | B12: ABONO INTERESES AHORROS | C12: 3.08 | D12: Intereses | E12: Intereses | F12: 3 | G12: =IFERROR(VLOOKUP(D12,Data!$A:$B,2,0),"Revisar") -> Gastos Variables | H12: NA | I12: {=_xlfn.XLOOKUP($H12,Data!$E:$E,Data!$F:$F,"Revisar",0)} -> NA | J12: {=_xlfn.XLOOKUP($H12,Data!$E:$E,Data!$G:$G,"Revisar",0)} -> NA | K12: NA | L12: =F12 -> 3
A13: 46107 | B13: TRANSFERENCIA CTA SUC VIRTUAL | C13: 2500000 | D13: Abono capital | E13: Abono Veronica | F13: 3 | G13: =IFERROR(VLOOKUP(D13,Data!$A:$B,2,0),"Revisar") -> Otros Ingresos | H13: NA | I13: {=_xlfn.XLOOKUP($H13,Data!$E:$E,Data!$F:$F,"Revisar",0)} -> NA | J13: {=_xlfn.XLOOKUP($H13,Data!$E:$E,Data!$G:$G,"Revisar",0)} -> NA | K13: No
A14: 46112 | B14: ABONO INTERESES AHORROS | C14: 29.82 | D14: Intereses | E14: Intereses | F14: 3 | G14: =IFERROR(VLOOKUP(D14,Data!$A:$B,2,0),"Revisar") -> Gastos Variables | H14: NA | I14: {=_xlfn.XLOOKUP($H14,Data!$E:$E,Data!$F:$F,"Revisar",0)} -> NA | J14: {=_xlfn.XLOOKUP($H14,Data!$E:$E,Data!$G:$G,"Revisar",0)} -> NA | K14: NA | L14: =F14 -> 3
A15: 46142 | B15: ABONO INTERESES AHORROS | C15: 255.64 | D15: Intereses | E15: Intereses | F15: 4 | G15: =IFERROR(VLOOKUP(D15,Data!$A:$B,2,0),"Revisar") -> Gastos Variables | H15: NA | I15: {=_xlfn.XLOOKUP($H15,Data!$E:$E,Data!$F:$F,"Revisar",0)} -> NA | J15: {=_xlfn.XLOOKUP($H15,Data!$E:$E,Data!$G:$G,"Revisar",0)} -> NA | K15: NA | L15: =F15 -> 4
A16: 46139 | B16: TRANSFERENCIA CTA SUC VIRTUAL | C16: -728875 | D16: Pago proveedores | E16: Smart Design - Innovaitors | F16: 4 | G16: =IFERROR(VLOOKUP(D16,Data!$A:$B,2,0),"Revisar") -> Costo Ventas | H16: M260301 | I16: {=_xlfn.XLOOKUP($H16,Data!$E:$E,Data!$F:$F,"Revisar",0)} -> Innovaitors | J16: {=_xlfn.XLOOKUP($H16,Data!$E:$E,Data!$G:$G,"Revisar",0)} -> Kits Innovaitors | K16: Si | L16: =F16 -> 4 | M16: SD-404
A17: 46138 | B17: ABONO INTERESES AHORROS | C17: 194.7 | D17: Intereses | E17: Intereses | F17: 4 | G17: =IFERROR(VLOOKUP(D17,Data!$A:$B,2,0),"Revisar") -> Gastos Variables | H17: NA | I17: {=_xlfn.XLOOKUP($H17,Data!$E:$E,Data!$F:$F,"Revisar",0)} -> NA | J17: {=_xlfn.XLOOKUP($H17,Data!$E:$E,Data!$G:$G,"Revisar",0)} -> NA | K17: NA | L17: =F17 -> 4
A18: 46136 | B18: COBRO IVA PAGOS AUTOMATICOS | C18: -1442.1 | D18: IVA Descontable | E18: IVA Descontable | F18: 4 | G18: =IFERROR(VLOOKUP(D18,Data!$A:$B,2,0),"Revisar") -> Imp x Pagar - IVA | H18: NA | I18: {=_xlfn.XLOOKUP($H18,Data!$E:$E,Data!$F:$F,"Revisar",0)} -> NA | J18: {=_xlfn.XLOOKUP($H18,Data!$E:$E,Data!$G:$G,"Revisar",0)} -> NA | K18: NA | L18: =F18 -> 4
A19: 46136 | B19: COBRO IVA PAGOS AUTOMATICOS | C19: -1442.1 | D19: IVA Descontable | E19: IVA Descontable | F19: 4 | G19: =IFERROR(VLOOKUP(D19,Data!$A:$B,2,0),"Revisar") -> Imp x Pagar - IVA | H19: NA | I19: {=_xlfn.XLOOKUP($H19,Data!$E:$E,Data!$F:$F,"Revisar",0)} -> NA | J19: {=_xlfn.XLOOKUP($H19,Data!$E:$E,Data!$G:$G,"Revisar",0)} -> NA | K19: NA | L19: =F19 -> 4
A20: 46136 | B20: TRANSFERENCIA VIRTUAL | C20: -38000 | D20: Pago proveedores | E20: KAS - Vasos | F20: 4 | G20: =IFERROR(VLOOKUP(D20,Data!$A:$B,2,0),"Revisar") -> Costo Ventas | H20: M260201 | I20: {=_xlfn.XLOOKUP($H20,Data!$E:$E,Data!$F:$F,"Revisar",0)} -> Konrad Adenauer Stiftung | J20: {=_xlfn.XLOOKUP($H20,Data!$E:$E,Data!$G:$G,"Revisar",0)} -> Material KAS - Tacos y pocillos | K20: Si | L20: =F20 -> 4 | M20: AOG-810
A21: 46136 | B21: TRANSFERENCIA VIRTUAL | C21: -200000 | D21: Pago proveedores | E21: KAS - Vasos | F21: 4 | G21: =IFERROR(VLOOKUP(D21,Data!$A:$B,2,0),"Revisar") -> Costo Ventas | H21: M260201 | I21: {=_xlfn.XLOOKUP($H21,Data!$E:$E,Data!$F:$F,"Revisar",0)} -> Konrad Adenauer Stiftung | J21: {=_xlfn.XLOOKUP($H21,Data!$E:$E,Data!$G:$G,"Revisar",0)} -> Material KAS - Tacos y pocillos | K21: Si | L21: =F21 -> 4 | M21: AOG-810
A22: 46136 | B22: SERVICIO TRANSFERENCIA VIRTUAL | C22: 7590 | D22: Costo transferencias | E22: Comisión transferencia | F22: 4 | G22: =IFERROR(VLOOKUP(D22,Data!$A:$B,2,0),"Revisar") -> Gastos Variables | H22: NA | I22: {=_xlfn.XLOOKUP($H22,Data!$E:$E,Data!$F:$F,"Revisar",0)} -> NA | J22: {=_xlfn.XLOOKUP($H22,Data!$E:$E,Data!$G:$G,"Revisar",0)} -> NA | K22: NA | L22: =F22 -> 4
A23: 46136 | B23: SERVICIO TRANSFERENCIA VIRTUAL | C23: 7590 | D23: Costo transferencias | E23: Comisión transferencia | F23: 4 | G23: =IFERROR(VLOOKUP(D23,Data!$A:$B,2,0),"Revisar") -> Gastos Variables | H23: NA | I23: {=_xlfn.XLOOKUP($H23,Data!$E:$E,Data!$F:$F,"Revisar",0)} -> NA | J23: {=_xlfn.XLOOKUP($H23,Data!$E:$E,Data!$G:$G,"Revisar",0)} -> NA | K23: NA | L23: =F23 -> 4
A24: 46135 | B24: ABONO INTERESES AHORROS | C24: 65.25 | D24: Intereses | E24: Intreses | F24: 4 | G24: =IFERROR(VLOOKUP(D24,Data!$A:$B,2,0),"Revisar") -> Gastos Variables | H24: NA | I24: {=_xlfn.XLOOKUP($H24,Data!$E:$E,Data!$F:$F,"Revisar",0)} -> NA | J24: {=_xlfn.XLOOKUP($H24,Data!$E:$E,Data!$G:$G,"Revisar",0)} -> NA | K24: NA | L24: =F24 -> 4
A25: 46135 | B25: PAGO INTERBANC Axis Communicat | C25: 37014469 | D25: Pago clientes | E25: Axis | F25: 4 | G25: =IFERROR(VLOOKUP(D25,Data!$A:$B,2,0),"Revisar") -> Ingresos | H25: M260101 | I25: {=_xlfn.XLOOKUP($H25,Data!$E:$E,Data!$F:$F,"Revisar",0)} -> AXIS | J25: {=_xlfn.XLOOKUP($H25,Data!$E:$E,Data!$G:$G,"Revisar",0)} -> Evento mundial de fútbol y merchandising | K25: Si | L25: 6 | M25: DAFE 1
A26: 46135 | B26: TRANSFERENCIA CTA SUC VIRTUAL | C26: -728875 | D26: Pago proveedores | E26: Smart Design - Innovaitors | F26: 4 | G26: =IFERROR(VLOOKUP(D26,Data!$A:$B,2,0),"Revisar") -> Costo Ventas | H26: M260301 | I26: {=_xlfn.XLOOKUP($H26,Data!$E:$E,Data!$F:$F,"Revisar",0)} -> Innovaitors | J26: {=_xlfn.XLOOKUP($H26,Data!$E:$E,Data!$G:$G,"Revisar",0)} -> Kits Innovaitors | K26: Si | L26: =F26 -> 4 | M26: SD-404
A27: 46134 | B27: ABONO INTERESES AHORROS | C27: 31.1 | D27: Intereses | E27: Intreses | F27: 4 | G27: =IFERROR(VLOOKUP(D27,Data!$A:$B,2,0),"Revisar") -> Gastos Variables | H27: NA | I27: {=_xlfn.XLOOKUP($H27,Data!$E:$E,Data!$F:$F,"Revisar",0)} -> NA | J27: {=_xlfn.XLOOKUP($H27,Data!$E:$E,Data!$G:$G,"Revisar",0)} -> NA | K27: NA | L27: =F27 -> 4
A28: 46133 | B28: COBRO IVA PAGOS AUTOMATICOS | C28: -1442.1 | D28: IVA Descontable | E28: IVA Descontable | F28: 4 | G28: =IFERROR(VLOOKUP(D28,Data!$A:$B,2,0),"Revisar") -> Imp x Pagar - IVA | H28: NA | I28: {=_xlfn.XLOOKUP($H28,Data!$E:$E,Data!$F:$F,"Revisar",0)} -> NA | J28: {=_xlfn.XLOOKUP($H28,Data!$E:$E,Data!$G:$G,"Revisar",0)} -> NA | K28: NA | L28: =F28 -> 4
A29: 46133 | B29: SERVICIO TRANSFERENCIA VIRTUAL | C29: -7590 | D29: Costo transferencias | E29: Intreses | F29: 4 | G29: =IFERROR(VLOOKUP(D29,Data!$A:$B,2,0),"Revisar") -> Gastos Variables | H29: NA | I29: {=_xlfn.XLOOKUP($H29,Data!$E:$E,Data!$F:$F,"Revisar",0)} -> NA | J29: {=_xlfn.XLOOKUP($H29,Data!$E:$E,Data!$G:$G,"Revisar",0)} -> NA | K29: NA | L29: =F29 -> 4
A30: 46133 | B30: TRANSFERENCIA VIRTUAL | C30: -327377.99 | D30: Pago proveedores | E30: Abono Monaco 500k, dividio para alinearse a las facturas - Axis | F30: 4 | G30: =IFERROR(VLOOKUP(D30,Data!$A:$B,2,0),"Revisar") -> Costo Ventas | H30: M260101 | I30: {=_xlfn.XLOOKUP($H30,Data!$E:$E,Data!$F:$F,"Revisar",0)} -> AXIS | J30: {=_xlfn.XLOOKUP($H30,Data!$E:$E,Data!$G:$G,"Revisar",0)} -> Evento mundial de fútbol y merchandising | K30: Si | L30: 6 | M30: FVSE-28291
A31: 46133 | B31: TRANSFERENCIA VIRTUAL | C31: =-500000-C30 -> -172622.01 | D31: Pago proveedores | E31: Abono Monaco 500k, dividio para alinearse a las facturas - Axis | F31: 4 | G31: =IFERROR(VLOOKUP(D31,Data!$A:$B,2,0),"Revisar") -> Costo Ventas | H31: M260101 | I31: {=_xlfn.XLOOKUP($H31,Data!$E:$E,Data!$F:$F,"Revisar",0)} -> AXIS | J31: {=_xlfn.XLOOKUP($H31,Data!$E:$E,Data!$G:$G,"Revisar",0)} -> Evento mundial de fútbol y merchandising | K31: Si | L31: 6 | M31: FVMR-18762
A32: 46132 | B32: PAGO INTERBANC KONRAD ADENAUER | C32: 9642280.8 | D32: Pago clientes | E32: Pago KAS | F32: 4 | G32: =IFERROR(VLOOKUP(D32,Data!$A:$B,2,0),"Revisar") -> Ingresos | H32: M260201 | I32: {=_xlfn.XLOOKUP($H32,Data!$E:$E,Data!$F:$F,"Revisar",0)} -> Konrad Adenauer Stiftung | J32: {=_xlfn.XLOOKUP($H32,Data!$E:$E,Data!$G:$G,"Revisar",0)} -> Material KAS - Tacos y pocillos | K32: Si | L32: =F32 -> 4 | M32: DAFE 3
A33: 46132 | B33: ABONO INTERESES AHORROS | C33: 16.25 | D33: Intereses | E33: Intreses | F33: 4 | G33: =IFERROR(VLOOKUP(D33,Data!$A:$B,2,0),"Revisar") -> Gastos Variables | H33: NA | I33: {=_xlfn.XLOOKUP($H33,Data!$E:$E,Data!$F:$F,"Revisar",0)} -> NA | J33: {=_xlfn.XLOOKUP($H33,Data!$E:$E,Data!$G:$G,"Revisar",0)} -> NA | K33: NA | L33: =F33 -> 4
A34: 46132 | B34: SERVICIOS ELCTR. | C34: -285650 | D34: Pago proveedores | E34: Ikea - Mugs Konrad adenauer | F34: 4 | G34: =IFERROR(VLOOKUP(D34,Data!$A:$B,2,0),"Revisar") -> Costo Ventas | H34: M260201 | I34: {=_xlfn.XLOOKUP($H34,Data!$E:$E,Data!$F:$F,"Revisar",0)} -> Konrad Adenauer Stiftung | J34: {=_xlfn.XLOOKUP($H34,Data!$E:$E,Data!$G:$G,"Revisar",0)} -> Material KAS - Tacos y pocillos | K34: Si | L34: =F34 -> 4 | M34: F109-118706
A35: 46131 | B35: ABONO INTERESES AHORROS | C35: 20.58 | D35: Intereses | E35: Intreses | F35: 4 | G35: =IFERROR(VLOOKUP(D35,Data!$A:$B,2,0),"Revisar") -> Gastos Variables | H35: NA | I35: {=_xlfn.XLOOKUP($H35,Data!$E:$E,Data!$F:$F,"Revisar",0)} -> NA | J35: {=_xlfn.XLOOKUP($H35,Data!$E:$E,Data!$G:$G,"Revisar",0)} -> NA | K35: NA | L35: =F35 -> 4
A36: 46126 | B36: PAGO LLAVE JUAN DAVID | C36: 2500000 | D36: Abono capital | E36: Aporte Juanda | F36: 4 | G36: =IFERROR(VLOOKUP(D36,Data!$A:$B,2,0),"Revisar") -> Otros Ingresos | H36: NA | I36: {=_xlfn.XLOOKUP($H36,Data!$E:$E,Data!$F:$F,"Revisar",0)} -> NA | J36: {=_xlfn.XLOOKUP($H36,Data!$E:$E,Data!$G:$G,"Revisar",0)} -> NA | K36: No | N36: no tiene mes PyG dado que es un movimiento que no lo afecta
A37: 46126 | B37: TRANSFERENCIA CTA SUC VIRTUAL | C37: 1000000 | D37: Abono capital | E37: Aporte Vero - cuenta TPC | F37: 4 | G37: =IFERROR(VLOOKUP(D37,Data!$A:$B,2,0),"Revisar") -> Otros Ingresos | H37: NA | I37: {=_xlfn.XLOOKUP($H37,Data!$E:$E,Data!$F:$F,"Revisar",0)} -> NA | J37: {=_xlfn.XLOOKUP($H37,Data!$E:$E,Data!$G:$G,"Revisar",0)} -> NA | K37: No | N37: no tiene mes PyG dado que es un movimiento que no lo afecta
A38: 46126 | B38: TRANSFERENCIA CTA SUC VIRTUAL | C38: 3000000 | D38: Abono capital | E38: Aporte Vero - cuenta TPC | F38: 4 | G38: =IFERROR(VLOOKUP(D38,Data!$A:$B,2,0),"Revisar") -> Otros Ingresos | H38: NA | I38: {=_xlfn.XLOOKUP($H38,Data!$E:$E,Data!$F:$F,"Revisar",0)} -> NA | J38: {=_xlfn.XLOOKUP($H38,Data!$E:$E,Data!$G:$G,"Revisar",0)} -> NA | K38: No | N38: no tiene mes PyG dado que es un movimiento que no lo afecta
A39: 46126 | B39: COMPRA EN RCS-CO BOG | C39: -6158400 | D39: Pago proveedores | E39: Adidas - Axis | F39: 4 | G39: =IFERROR(VLOOKUP(D39,Data!$A:$B,2,0),"Revisar") -> Costo Ventas | H39: M260101 | I39: {=_xlfn.XLOOKUP($H39,Data!$E:$E,Data!$F:$F,"Revisar",0)} -> AXIS | J39: {=_xlfn.XLOOKUP($H39,Data!$E:$E,Data!$G:$G,"Revisar",0)} -> Evento mundial de fútbol y merchandising | K39: Si | L39: 6 | M39: 030A-47518
A40: 46125 | B40: ABONO INTERESES AHORROS | C40: 11.84 | D40: Intereses | E40: Intreses | F40: 4 | G40: =IFERROR(VLOOKUP(D40,Data!$A:$B,2,0),"Revisar") -> Gastos Variables | H40: NA | I40: {=_xlfn.XLOOKUP($H40,Data!$E:$E,Data!$F:$F,"Revisar",0)} -> NA | J40: {=_xlfn.XLOOKUP($H40,Data!$E:$E,Data!$G:$G,"Revisar",0)} -> NA | K40: NA | L40: =F40 -> 4
A41: 46121 | B41: C MANEJO TARJ DEB 1192 04 26 | C41: -18050 | D41: Cuota de manejo | E41: Cuota de manejo | F41: 4 | G41: =IFERROR(VLOOKUP(D41,Data!$A:$B,2,0),"Revisar") -> Costos Fijos | H41: NA | I41: {=_xlfn.XLOOKUP($H41,Data!$E:$E,Data!$F:$F,"Revisar",0)} -> NA | J41: {=_xlfn.XLOOKUP($H41,Data!$E:$E,Data!$G:$G,"Revisar",0)} -> NA | K41: NA | L41: =F41 -> 4
A42: 46121 | B42: AJUSTE INTERES AHORROS DB | C42: -0.03 | D42: Intereses | E42: Intreses | F42: 4 | G42: =IFERROR(VLOOKUP(D42,Data!$A:$B,2,0),"Revisar") -> Gastos Variables | H42: NA | I42: {=_xlfn.XLOOKUP($H42,Data!$E:$E,Data!$F:$F,"Revisar",0)} -> NA | J42: {=_xlfn.XLOOKUP($H42,Data!$E:$E,Data!$G:$G,"Revisar",0)} -> NA | K42: NA | L42: =F42 -> 4
A43: 46121 | B43: ABONO INTERESES AHORROS | C43: 2.99 | D43: Intereses | E43: Intreses | F43: 4 | G43: =IFERROR(VLOOKUP(D43,Data!$A:$B,2,0),"Revisar") -> Gastos Variables | H43: NA | I43: {=_xlfn.XLOOKUP($H43,Data!$E:$E,Data!$F:$F,"Revisar",0)} -> NA | J43: {=_xlfn.XLOOKUP($H43,Data!$E:$E,Data!$G:$G,"Revisar",0)} -> NA | K43: NA | L43: =F43 -> 4
A44: 46121 | B44: TRANSFERENCIA CTA SUC VIRTUAL | C44: -611500 | D44: Pago proveedores | E44: Kojak - Llaveros Axis | F44: 4 | G44: =IFERROR(VLOOKUP(D44,Data!$A:$B,2,0),"Revisar") -> Costo Ventas | H44: M260101 | I44: {=_xlfn.XLOOKUP($H44,Data!$E:$E,Data!$F:$F,"Revisar",0)} -> AXIS | J44: {=_xlfn.XLOOKUP($H44,Data!$E:$E,Data!$G:$G,"Revisar",0)} -> Evento mundial de fútbol y merchandising | K44: Si | L44: 6 | M44: 2604
A45: 46120 | B45: ABONO INTERESES AHORROS | C45: 11.46 | D45: Intereses | E45: Intreses | F45: 4 | G45: =IFERROR(VLOOKUP(D45,Data!$A:$B,2,0),"Revisar") -> Gastos Variables | H45: NA | I45: {=_xlfn.XLOOKUP($H45,Data!$E:$E,Data!$F:$F,"Revisar",0)} -> NA | J45: {=_xlfn.XLOOKUP($H45,Data!$E:$E,Data!$G:$G,"Revisar",0)} -> NA | K45: NA | L45: =F45 -> 4
A46: 46118 | B46: TRANSFERENCIA CTA SUC VIRTUAL | C46: -611500 | D46: Pago proveedores | E46: Kojak - Llaveros Axis | F46: 4 | G46: =IFERROR(VLOOKUP(D46,Data!$A:$B,2,0),"Revisar") -> Costo Ventas | H46: M260101 | I46: {=_xlfn.XLOOKUP($H46,Data!$E:$E,Data!$F:$F,"Revisar",0)} -> AXIS | J46: {=_xlfn.XLOOKUP($H46,Data!$E:$E,Data!$G:$G,"Revisar",0)} -> Evento mundial de fútbol y merchandising | K46: Si | L46: 6 | M46: 2604
A47: 46118 | B47: COMPRA EN INFORMATIC | C47: -222529 | D47: Licencias | E47: Siigo | F47: 4 | G47: =IFERROR(VLOOKUP(D47,Data!$A:$B,2,0),"Revisar") -> Costos Operacionales | H47: NA | I47: {=_xlfn.XLOOKUP($H47,Data!$E:$E,Data!$F:$F,"Revisar",0)} -> NA | J47: {=_xlfn.XLOOKUP($H47,Data!$E:$E,Data!$G:$G,"Revisar",0)} -> NA | K47: NA | L47: =F47 -> 4 | M47: 93-
A48: 46117 | B48: ABONO INTERESES AHORROS | C48: 24.85 | D48: Intereses | E48: Intreses | F48: 4 | G48: =IFERROR(VLOOKUP(D48,Data!$A:$B,2,0),"Revisar") -> Gastos Variables | H48: NA | I48: {=_xlfn.XLOOKUP($H48,Data!$E:$E,Data!$F:$F,"Revisar",0)} -> NA | J48: {=_xlfn.XLOOKUP($H48,Data!$E:$E,Data!$G:$G,"Revisar",0)} -> NA | K48: NA | L48: =F48 -> 4
A49: 46167 | B49: COBRO IVA PAGOS AUTOMATICOS | C49: -1442 | D49: IVA Descontable | E49: IVA Descontable | F49: 5 | G49: =IFERROR(VLOOKUP(D49,Data!$A:$B,2,0),"Revisar") -> Imp x Pagar - IVA | H49: NA | I49: {=_xlfn.XLOOKUP($H49,Data!$E:$E,Data!$F:$F,"Revisar",0)} -> NA | J49: {=_xlfn.XLOOKUP($H49,Data!$E:$E,Data!$G:$G,"Revisar",0)} -> NA | K49: NA | L49: =F49 -> 5
A50: 46167 | B50: COBRO IVA PAGOS AUTOMATICOS | C50: -1442 | D50: IVA Descontable | E50: IVA Descontable | F50: 5 | G50: =IFERROR(VLOOKUP(D50,Data!$A:$B,2,0),"Revisar") -> Imp x Pagar - IVA | H50: NA | I50: {=_xlfn.XLOOKUP($H50,Data!$E:$E,Data!$F:$F,"Revisar",0)} -> NA | J50: {=_xlfn.XLOOKUP($H50,Data!$E:$E,Data!$G:$G,"Revisar",0)} -> NA | K50: NA | L50: =F50 -> 5
A51: 46167 | B51: SERVICIO TRANSFERENCIA VIRTUAL | C51: -7590 | D51: Costo transferencias | E51: Costo transferencias | F51: 5 | G51: =IFERROR(VLOOKUP(D51,Data!$A:$B,2,0),"Revisar") -> Gastos Variables | H51: NA | I51: {=_xlfn.XLOOKUP($H51,Data!$E:$E,Data!$F:$F,"Revisar",0)} -> NA | J51: {=_xlfn.XLOOKUP($H51,Data!$E:$E,Data!$G:$G,"Revisar",0)} -> NA | K51: NA | L51: =F51 -> 5
A52: 46167 | B52: SERVICIO TRANSFERENCIA VIRTUAL | C52: -7590 | D52: Costo transferencias | E52: Costo transferencias | F52: 5 | G52: =IFERROR(VLOOKUP(D52,Data!$A:$B,2,0),"Revisar") -> Gastos Variables | H52: NA | I52: {=_xlfn.XLOOKUP($H52,Data!$E:$E,Data!$F:$F,"Revisar",0)} -> NA | J52: {=_xlfn.XLOOKUP($H52,Data!$E:$E,Data!$G:$G,"Revisar",0)} -> NA | K52: NA | L52: =F52 -> 5
A53: 46167 | B53: TRANSFERENCIA VIRTUAL | C53: -4830000 | D53: Pago proveedores | E53: Pago Transparente Digital (Portatacos - Envio) | F53: 5 | G53: =IFERROR(VLOOKUP(D53,Data!$A:$B,2,0),"Revisar") -> Costo Ventas | H53: M260201 | I53: {=_xlfn.XLOOKUP($H53,Data!$E:$E,Data!$F:$F,"Revisar",0)} -> Konrad Adenauer Stiftung | J53: {=_xlfn.XLOOKUP($H53,Data!$E:$E,Data!$G:$G,"Revisar",0)} -> Material KAS - Tacos y pocillos | K53: Si | L53: 4 | M53: FE-285
A54: 46167 | B54: TRANSFERENCIA VIRTUAL | C54: -214200 | D54: Pago proveedores | E54: Pago Transparente Digital (Rollup) | F54: 5 | G54: =IFERROR(VLOOKUP(D54,Data!$A:$B,2,0),"Revisar") -> Costo Ventas | H54: M260302 | I54: {=_xlfn.XLOOKUP($H54,Data!$E:$E,Data!$F:$F,"Revisar",0)} -> Innovaitors | J54: {=_xlfn.XLOOKUP($H54,Data!$E:$E,Data!$G:$G,"Revisar",0)} -> Banners Rollup | K54: Si | L54: =F54 -> 5 | M54: FE-285
A55: 46167 | B55: TRANSFERENCIA VIRTUAL | C55: -1071000 | D55: Pago proveedores | E55: Pago Transparente Digital (Carpeta - Rollup - Stickers) | F55: 5 | G55: =IFERROR(VLOOKUP(D55,Data!$A:$B,2,0),"Revisar") -> Costo Ventas | H55: M260401 | I55: {=_xlfn.XLOOKUP($H55,Data!$E:$E,Data!$F:$F,"Revisar",0)} -> Kaspersky | J55: {=_xlfn.XLOOKUP($H55,Data!$E:$E,Data!$G:$G,"Revisar",0)} -> Bolsa Incentivos 2026 | K55: Si | L55: =F55 -> 5 | M55: FE-285
A56: 46167 | B56: TRANSFERENCIA VIRTUAL | C56: -11565200 | D56: Pago proveedores | E56: Abono 1 - Logist / Evento CCB | F56: 5 | G56: =IFERROR(VLOOKUP(D56,Data!$A:$B,2,0),"Revisar") -> Costo Ventas | H56: M260501 | I56: {=_xlfn.XLOOKUP($H56,Data!$E:$E,Data!$F:$F,"Revisar",0)} -> Psiconometrics | J56: {=_xlfn.XLOOKUP($H56,Data!$E:$E,Data!$G:$G,"Revisar",0)} -> Evento Camara Comercio | K56: Si | L56: 6 | M56: FV-1537
A57: 46167 | B57: IMPTO GOBIERNO 4X1000 | C57: -63497 | D57: GMF 4x1000 | E57: 4x1000 | F57: 5 | G57: =IFERROR(VLOOKUP(D57,Data!$A:$B,2,0),"Revisar") -> Gastos Variables | H57: NA | I57: {=_xlfn.XLOOKUP($H57,Data!$E:$E,Data!$F:$F,"Revisar",0)} -> NA | J57: {=_xlfn.XLOOKUP($H57,Data!$E:$E,Data!$G:$G,"Revisar",0)} -> NA | K57: NA | L57: =F57 -> 5
A58: 46166 | B58: ABONO INTERESES AHORROS | C58: 165 | D58: Intereses | E58: Intereses | F58: 5 | G58: =IFERROR(VLOOKUP(D58,Data!$A:$B,2,0),"Revisar") -> Gastos Variables | H58: NA | I58: {=_xlfn.XLOOKUP($H58,Data!$E:$E,Data!$F:$F,"Revisar",0)} -> NA | J58: {=_xlfn.XLOOKUP($H58,Data!$E:$E,Data!$G:$G,"Revisar",0)} -> NA | K58: NA | L58: =F58 -> 5
A59: 46163 | B59: TRANSFERENCIA CTA SUC VIRTUAL | C59: -4688600 | D59: Pago proveedores | E59: Line Marketing | F59: 5 | G59: =IFERROR(VLOOKUP(D59,Data!$A:$B,2,0),"Revisar") -> Costo Ventas | H59: M260101 | I59: {=_xlfn.XLOOKUP($H59,Data!$E:$E,Data!$F:$F,"Revisar",0)} -> AXIS | J59: {=_xlfn.XLOOKUP($H59,Data!$E:$E,Data!$G:$G,"Revisar",0)} -> Evento mundial de fútbol y merchandising | K59: Si | L59: 6 | M59: FE-538
A60: 46162 | B60: ABONO INTERESES AHORROS | C60: 48 | D60: Intereses | E60: Intereses | F60: 5 | G60: =IFERROR(VLOOKUP(D60,Data!$A:$B,2,0),"Revisar") -> Gastos Variables | H60: NA | I60: {=_xlfn.XLOOKUP($H60,Data!$E:$E,Data!$F:$F,"Revisar",0)} -> NA | J60: {=_xlfn.XLOOKUP($H60,Data!$E:$E,Data!$G:$G,"Revisar",0)} -> NA | K60: NA | L60: =F60 -> 5
A61: 46162 | B61: COMPRA EN DISTRIBUID | C61: -237214 | D61: Gastos representación | E61: Gasolina | F61: 5 | G61: =IFERROR(VLOOKUP(D61,Data!$A:$B,2,0),"Revisar") -> Costos Operacionales | H61: NA | I61: {=_xlfn.XLOOKUP($H61,Data!$E:$E,Data!$F:$F,"Revisar",0)} -> NA | J61: {=_xlfn.XLOOKUP($H61,Data!$E:$E,Data!$G:$G,"Revisar",0)} -> NA | K61: NA | L61: =F61 -> 5 | M61: TSFB-145699
A62: 46161 | B62: ABONO INTERESES AHORROS | C62: 48 | D62: Intereses | E62: Intereses | F62: 5 | G62: =IFERROR(VLOOKUP(D62,Data!$A:$B,2,0),"Revisar") -> Gastos Variables | H62: NA | I62: {=_xlfn.XLOOKUP($H62,Data!$E:$E,Data!$F:$F,"Revisar",0)} -> NA | J62: {=_xlfn.XLOOKUP($H62,Data!$E:$E,Data!$G:$G,"Revisar",0)} -> NA | K62: NA | L62: =F62 -> 5
A63: 46161 | B63: PAGO PSE DIAN PSE | C63: -3819000 | D63: Impuestos | E63: Pago Impuestos | F63: 5 | G63: =IFERROR(VLOOKUP(D63,Data!$A:$B,2,0),"Revisar") -> Impuestos | H63: NA | I63: {=_xlfn.XLOOKUP($H63,Data!$E:$E,Data!$F:$F,"Revisar",0)} -> NA | J63: {=_xlfn.XLOOKUP($H63,Data!$E:$E,Data!$G:$G,"Revisar",0)} -> NA | K63: NA | L63: =F63 -> 5
A64: 46160 | B64: ABONO INTERESES AHORROS | C64: 213 | D64: Intereses | E64: Intereses | F64: 5 | G64: =IFERROR(VLOOKUP(D64,Data!$A:$B,2,0),"Revisar") -> Gastos Variables | H64: NA | I64: {=_xlfn.XLOOKUP($H64,Data!$E:$E,Data!$F:$F,"Revisar",0)} -> NA | J64: {=_xlfn.XLOOKUP($H64,Data!$E:$E,Data!$G:$G,"Revisar",0)} -> NA | K64: NA | L64: =F64 -> 5
A65: 46156 | B65: C MANEJO TARJ DEB 1192 05 26 | C65: -18050 | D65: Cuota de manejo | E65: Cuota de Manejo | F65: 5 | G65: =IFERROR(VLOOKUP(D65,Data!$A:$B,2,0),"Revisar") -> Costos Fijos | H65: NA | I65: {=_xlfn.XLOOKUP($H65,Data!$E:$E,Data!$F:$F,"Revisar",0)} -> NA | J65: {=_xlfn.XLOOKUP($H65,Data!$E:$E,Data!$G:$G,"Revisar",0)} -> NA | K65: NA | L65: =F65 -> 5
A66: 46156 | B66: AJUSTE INTERES AHORROS DB | C66: 0 | D66: Intereses | E66: Intereses | F66: 5 | G66: =IFERROR(VLOOKUP(D66,Data!$A:$B,2,0),"Revisar") -> Gastos Variables | H66: NA | I66: {=_xlfn.XLOOKUP($H66,Data!$E:$E,Data!$F:$F,"Revisar",0)} -> NA | J66: {=_xlfn.XLOOKUP($H66,Data!$E:$E,Data!$G:$G,"Revisar",0)} -> NA | K66: NA | L66: =F66 -> 5
A67: 46156 | B67: ABONO INTERESES AHORROS | C67: 533 | D67: Intereses | E67: Intereses | F67: 5 | G67: =IFERROR(VLOOKUP(D67,Data!$A:$B,2,0),"Revisar") -> Gastos Variables | H67: NA | I67: {=_xlfn.XLOOKUP($H67,Data!$E:$E,Data!$F:$F,"Revisar",0)} -> NA | J67: {=_xlfn.XLOOKUP($H67,Data!$E:$E,Data!$G:$G,"Revisar",0)} -> NA | K67: NA | L67: =F67 -> 5
A68: 46147 | B68: TRANSFERENCIA CTA SUC VIRTUAL | C68: -32000 | D68: Pago proveedores | E68: Dulces - Commscope | F68: 5 | G68: =IFERROR(VLOOKUP(D68,Data!$A:$B,2,0),"Revisar") -> Costo Ventas | H68: M260701 | I68: {=_xlfn.XLOOKUP($H68,Data!$E:$E,Data!$F:$F,"Revisar",0)} -> Commscope | J68: {=_xlfn.XLOOKUP($H68,Data!$E:$E,Data!$G:$G,"Revisar",0)} -> Regalos Cartagena | K68: Si | L68: =F68 -> 5 | M68: MAL-108728
A69: 46146 | B69: ABONO INTERESES AHORROS | C69: 53 | D69: Intereses | E69: Intereses | F69: 5 | G69: =IFERROR(VLOOKUP(D69,Data!$A:$B,2,0),"Revisar") -> Gastos Variables | H69: NA | I69: {=_xlfn.XLOOKUP($H69,Data!$E:$E,Data!$F:$F,"Revisar",0)} -> NA | J69: {=_xlfn.XLOOKUP($H69,Data!$E:$E,Data!$G:$G,"Revisar",0)} -> NA | K69: NA | L69: =F69 -> 5
A70: 46146 | B70: TRANSFERENCIA CTA SUC VIRTUAL | C70: -3000000 | D70: Pago proveedores | E70: Dulces - Commscope | F70: 5 | G70: =IFERROR(VLOOKUP(D70,Data!$A:$B,2,0),"Revisar") -> Costo Ventas | H70: M260701 | I70: {=_xlfn.XLOOKUP($H70,Data!$E:$E,Data!$F:$F,"Revisar",0)} -> Commscope | J70: {=_xlfn.XLOOKUP($H70,Data!$E:$E,Data!$G:$G,"Revisar",0)} -> Regalos Cartagena | K70: Si | L70: =F70 -> 5 | M70: MAL-108728
A71: 46146 | B71: COMPRA EN K TRONIX 9 | C71: -1490000 | D71: Pago proveedores | E71: Albunes Mundial Axis | F71: 5 | G71: =IFERROR(VLOOKUP(D71,Data!$A:$B,2,0),"Revisar") -> Costo Ventas | H71: M260101 | I71: {=_xlfn.XLOOKUP($H71,Data!$E:$E,Data!$F:$F,"Revisar",0)} -> AXIS | J71: {=_xlfn.XLOOKUP($H71,Data!$E:$E,Data!$G:$G,"Revisar",0)} -> Evento mundial de fútbol y merchandising | K71: Si | L71: 6 | M71: X711-2506067
A72: 46146 | B72: COMPRA EN K TRONIX 9 | C72: -3120000 | D72: Pago proveedores | E72: Cajas Laminas Mundial Axis | F72: 5 | G72: =IFERROR(VLOOKUP(D72,Data!$A:$B,2,0),"Revisar") -> Costo Ventas | H72: M260101 | I72: {=_xlfn.XLOOKUP($H72,Data!$E:$E,Data!$F:$F,"Revisar",0)} -> AXIS | J72: {=_xlfn.XLOOKUP($H72,Data!$E:$E,Data!$G:$G,"Revisar",0)} -> Evento mundial de fútbol y merchandising | K72: Si | L72: 6 | M72: X711-2506066
A73: 46145 | B73: ABONO INTERESES AHORROS | C73: 191 | D73: Intereses | E73: Intereses | F73: 5 | G73: =IFERROR(VLOOKUP(D73,Data!$A:$B,2,0),"Revisar") -> Gastos Variables | H73: NA | I73: {=_xlfn.XLOOKUP($H73,Data!$E:$E,Data!$F:$F,"Revisar",0)} -> NA | J73: {=_xlfn.XLOOKUP($H73,Data!$E:$E,Data!$G:$G,"Revisar",0)} -> NA | K73: NA | L73: =F73 -> 5
A74: 46143 | B74: COMPRA INTL GOOGLE Workspace | C74: -101847 | D74: Licencias | E74: Google Workspace | F74: 5 | G74: =IFERROR(VLOOKUP(D74,Data!$A:$B,2,0),"Revisar") -> Costos Operacionales | H74: NA | I74: {=_xlfn.XLOOKUP($H74,Data!$E:$E,Data!$F:$F,"Revisar",0)} -> NA | J74: {=_xlfn.XLOOKUP($H74,Data!$E:$E,Data!$G:$G,"Revisar",0)} -> NA | K74: NA | L74: =F74 -> 5 | N74: Va haber factura?
A75: 46168 | B75: ABONO INTERESES AHORROS | C75: 34 | D75: Intereses | E75: Intereses | F75: 5 | G75: =IFERROR(VLOOKUP(D75,Data!$A:$B,2,0),"Revisar") -> Gastos Variables | H75: NA | I75: {=_xlfn.XLOOKUP($H75,Data!$E:$E,Data!$F:$F,"Revisar",0)} -> NA | J75: {=_xlfn.XLOOKUP($H75,Data!$E:$E,Data!$G:$G,"Revisar",0)} -> NA | K75: NA | L75: =F75 -> 5
A76: 46169 | B76: ABONO INTERESES AHORROS | C76: 11 | D76: Intereses | E76: Intereses | F76: 5 | G76: =IFERROR(VLOOKUP(D76,Data!$A:$B,2,0),"Revisar") -> Gastos Variables | H76: NA | I76: {=_xlfn.XLOOKUP($H76,Data!$E:$E,Data!$F:$F,"Revisar",0)} -> NA | J76: {=_xlfn.XLOOKUP($H76,Data!$E:$E,Data!$G:$G,"Revisar",0)} -> NA | K76: NA | L76: =F76 -> 5
A77: 46169 | B77: SERVICIO TRANSFERENCIA VIRTUAL | C77: -7590 | D77: Costo transferencias | E77: Costo transferencias | F77: 5 | G77: =IFERROR(VLOOKUP(D77,Data!$A:$B,2,0),"Revisar") -> Gastos Variables | H77: NA | I77: {=_xlfn.XLOOKUP($H77,Data!$E:$E,Data!$F:$F,"Revisar",0)} -> NA | J77: {=_xlfn.XLOOKUP($H77,Data!$E:$E,Data!$G:$G,"Revisar",0)} -> NA | K77: NA | L77: =F77 -> 5
A78: 46169 | B78: TRANSFERENCIA VIRTUAL | C78: -3711610 | D78: Pago proveedores | E78: Proveedor Eventi (Muebles) | F78: 5 | G78: =IFERROR(VLOOKUP(D78,Data!$A:$B,2,0),"Revisar") -> Costo Ventas | H78: M260501 | I78: {=_xlfn.XLOOKUP($H78,Data!$E:$E,Data!$F:$F,"Revisar",0)} -> Psiconometrics | J78: {=_xlfn.XLOOKUP($H78,Data!$E:$E,Data!$G:$G,"Revisar",0)} -> Evento Camara Comercio | K78: Si | L78: 6 | M78: FVP-1218
A79: 46169 | B79: IMPTO GOBIERNO 4X1000 | C79: -16244 | D79: GMF 4x1000 | E79: 4x1000 | F79: 5 | G79: =IFERROR(VLOOKUP(D79,Data!$A:$B,2,0),"Revisar") -> Gastos Variables | H79: NA | I79: {=_xlfn.XLOOKUP($H79,Data!$E:$E,Data!$F:$F,"Revisar",0)} -> NA | J79: {=_xlfn.XLOOKUP($H79,Data!$E:$E,Data!$G:$G,"Revisar",0)} -> NA | K79: NA | L79: =F79 -> 5
A80: 46169 | B80: COMPRA EN SEKUSHI SK | C80: -340387 | D80: Gastos representación | E80: Cliente Axis | F80: 5 | G80: =IFERROR(VLOOKUP(D80,Data!$A:$B,2,0),"Revisar") -> Costos Operacionales | I80: AXIS | J80: Gastos Representacion | K80: NA | L80: =F80 -> 5 | M80: FVSE-27735
A81: 46169 | B81: COBRO IVA PAGOS AUTOMATICOS | C81: -1442 | D81: IVA Descontable | E81: IVA Descontable | F81: 5 | G81: =IFERROR(VLOOKUP(D81,Data!$A:$B,2,0),"Revisar") -> Imp x Pagar - IVA | H81: NA | I81: {=_xlfn.XLOOKUP($H81,Data!$E:$E,Data!$F:$F,"Revisar",0)} -> NA | J81: {=_xlfn.XLOOKUP($H81,Data!$E:$E,Data!$G:$G,"Revisar",0)} -> NA | K81: NA | L81: =F81 -> 5
A82: 46170 | B82: ABONO INTERESES AHORROS | C82: 9 | D82: Intereses | E82: Intereses | F82: 5 | G82: =IFERROR(VLOOKUP(D82,Data!$A:$B,2,0),"Revisar") -> Gastos Variables | H82: NA | I82: {=_xlfn.XLOOKUP($H82,Data!$E:$E,Data!$F:$F,"Revisar",0)} -> NA | J82: {=_xlfn.XLOOKUP($H82,Data!$E:$E,Data!$G:$G,"Revisar",0)} -> NA | K82: NA | L82: =F82 -> 5
A83: 46170 | B83: IMPTO GOBIERNO 4X1000 | C83: -6647 | D83: GMF 4x1000 | E83: 4x1000 | F83: 5 | G83: =IFERROR(VLOOKUP(D83,Data!$A:$B,2,0),"Revisar") -> Gastos Variables | H83: NA | I83: {=_xlfn.XLOOKUP($H83,Data!$E:$E,Data!$F:$F,"Revisar",0)} -> NA | J83: {=_xlfn.XLOOKUP($H83,Data!$E:$E,Data!$G:$G,"Revisar",0)} -> NA | K83: NA | L83: =F83 -> 5
A84: 46170 | B84: COMPRA EN IKEA NQS | C84: -1416870 | D84: Pago proveedores | E84: Biblioteca Evento Camara Comercio Bogota | F84: 5 | G84: =IFERROR(VLOOKUP(D84,Data!$A:$B,2,0),"Revisar") -> Costo Ventas | H84: M260501 | I84: {=_xlfn.XLOOKUP($H84,Data!$E:$E,Data!$F:$F,"Revisar",0)} -> Psiconometrics | J84: {=_xlfn.XLOOKUP($H84,Data!$E:$E,Data!$G:$G,"Revisar",0)} -> Evento Camara Comercio | K84: Si | L84: 6 | M84: F107-106503
A85: 46170 | B85: COMPRA EN IKEA NQS | C85: -245000 | D85: Pago proveedores | E85: Lamparas Evento Camara Comercio Bogota | F85: 5 | G85: =IFERROR(VLOOKUP(D85,Data!$A:$B,2,0),"Revisar") -> Costo Ventas | H85: M260501 | I85: {=_xlfn.XLOOKUP($H85,Data!$E:$E,Data!$F:$F,"Revisar",0)} -> Psiconometrics | J85: {=_xlfn.XLOOKUP($H85,Data!$E:$E,Data!$G:$G,"Revisar",0)} -> Evento Camara Comercio | K85: Si | L85: 6 | M85: F107-106504
A86: 46171 | B86: PAGO INTERBANC KASPERSKY COLOM | C86: 70154606 | D86: Pago clientes | E86: Kaspersky | F86: 5 | G86: =IFERROR(VLOOKUP(D86,Data!$A:$B,2,0),"Revisar") -> Ingresos | H86: M260401 | I86: {=_xlfn.XLOOKUP($H86,Data!$E:$E,Data!$F:$F,"Revisar",0)} -> Kaspersky | J86: {=_xlfn.XLOOKUP($H86,Data!$E:$E,Data!$G:$G,"Revisar",0)} -> Bolsa Incentivos 2026 | K86: Si | L86: =F86 -> 5 | M86: DAFE 5
A87: 46171 | B87: PAGO DE PROV PSYCONOMETRICS | C87: 177255823 | D87: Pago clientes | E87: Evento Camara Comercio Bogota | F87: 5 | G87: =IFERROR(VLOOKUP(D87,Data!$A:$B,2,0),"Revisar") -> Ingresos | H87: M260501 | I87: {=_xlfn.XLOOKUP($H87,Data!$E:$E,Data!$F:$F,"Revisar",0)} -> Psiconometrics | J87: {=_xlfn.XLOOKUP($H87,Data!$E:$E,Data!$G:$G,"Revisar",0)} -> Evento Camara Comercio | K87: Si | L87: 6 | M87: DAFE 9
A88: 46171 | B88: ABONO INTERESES AHORROS | C88: 1378 | D88: Intereses | E88: Intereses | F88: 5 | G88: =IFERROR(VLOOKUP(D88,Data!$A:$B,2,0),"Revisar") -> Gastos Variables | H88: NA | I88: {=_xlfn.XLOOKUP($H88,Data!$E:$E,Data!$F:$F,"Revisar",0)} -> NA | J88: {=_xlfn.XLOOKUP($H88,Data!$E:$E,Data!$G:$G,"Revisar",0)} -> NA | K88: NA | L88: =F88 -> 5
A89: 46171 | B89: IMPTO GOBIERNO 4X1000 | C89: -10207 | D89: GMF 4x1000 | E89: 4x1000 | F89: 5 | G89: =IFERROR(VLOOKUP(D89,Data!$A:$B,2,0),"Revisar") -> Gastos Variables | H89: NA | I89: {=_xlfn.XLOOKUP($H89,Data!$E:$E,Data!$F:$F,"Revisar",0)} -> NA | J89: {=_xlfn.XLOOKUP($H89,Data!$E:$E,Data!$G:$G,"Revisar",0)} -> NA | K89: NA | L89: =F89 -> 5
A90: 46171 | B90: COMPRA EN COMERCIAL | C90: -51850 | D90: Pago proveedores | E90: Impresion certificados Comercial Papelera - Kaspersky | F90: 5 | G90: =IFERROR(VLOOKUP(D90,Data!$A:$B,2,0),"Revisar") -> Costo Ventas | H90: M260401 | I90: {=_xlfn.XLOOKUP($H90,Data!$E:$E,Data!$F:$F,"Revisar",0)} -> Kaspersky | J90: {=_xlfn.XLOOKUP($H90,Data!$E:$E,Data!$G:$G,"Revisar",0)} -> Bolsa Incentivos 2026 | K90: Si | L90: =F90 -> 5 | M90: FE04-509903
A91: 46171 | B91: RETIRO CAJERO ATM UNICENTRO L | C91: -2500000 | D91: Deuda Socios | E91: Pago prestamo Juan David Cruz | F91: 5 | G91: =IFERROR(VLOOKUP(D91,Data!$A:$B,2,0),"Revisar") -> Otros Gastos | H91: NA | I91: {=_xlfn.XLOOKUP($H91,Data!$E:$E,Data!$F:$F,"Revisar",0)} -> NA | J91: {=_xlfn.XLOOKUP($H91,Data!$E:$E,Data!$G:$G,"Revisar",0)} -> NA | K91: NA
A92: 46172 | B92: IMPTO GOBIERNO 4X1000 | C92: -272 | D92: GMF 4x1000 | E92: 4x1000 | F92: 5 | G92: =IFERROR(VLOOKUP(D92,Data!$A:$B,2,0),"Revisar") -> Gastos Variables | H92: NA | I92: {=_xlfn.XLOOKUP($H92,Data!$E:$E,Data!$F:$F,"Revisar",0)} -> NA | J92: {=_xlfn.XLOOKUP($H92,Data!$E:$E,Data!$G:$G,"Revisar",0)} -> NA | K92: NA | L92: =F92 -> 5
A93: 46172 | B93: COMPRA EN COMERCIAL | C93: -68000 | D93: Pago proveedores | E93: Impresion certificados Comercial Papelera - Kaspersky | F93: 5 | G93: =IFERROR(VLOOKUP(D93,Data!$A:$B,2,0),"Revisar") -> Costo Ventas | H93: M260401 | I93: {=_xlfn.XLOOKUP($H93,Data!$E:$E,Data!$F:$F,"Revisar",0)} -> Kaspersky | J93: {=_xlfn.XLOOKUP($H93,Data!$E:$E,Data!$G:$G,"Revisar",0)} -> Bolsa Incentivos 2026 | K93: Si | L93: =F93 -> 5 | M93: FE03-392527
A94: 46173 | B94: ABONO INTERESES AHORROS | C94: 2755 | D94: Intereses | E94: Intereses | F94: 5 | G94: =IFERROR(VLOOKUP(D94,Data!$A:$B,2,0),"Revisar") -> Gastos Variables | H94: NA | I94: {=_xlfn.XLOOKUP($H94,Data!$E:$E,Data!$F:$F,"Revisar",0)} -> NA | J94: {=_xlfn.XLOOKUP($H94,Data!$E:$E,Data!$G:$G,"Revisar",0)} -> NA | K94: NA | L94: =F94 -> 5
A95: 46174 | B95: COBRO IVA PAGOS AUTOMATICOS | C95: -1442 | D95: IVA Descontable | E95: IVA servicios banco | F95: 6 | G95: =IFERROR(VLOOKUP(D95,Data!$A:$B,2,0),"Revisar") -> Imp x Pagar - IVA | H95: NA | I95: {=_xlfn.XLOOKUP($H95,Data!$E:$E,Data!$F:$F,"Revisar",0)} -> NA | J95: {=_xlfn.XLOOKUP($H95,Data!$E:$E,Data!$G:$G,"Revisar",0)} -> NA | K95: NA | L95: =F95 -> 6
A96: 46174 | B96: SERVICIO TRANSFERENCIA VIRTUAL | C96: -7590 | D96: Costo transferencias | E96: Costo transferencia | F96: 6 | G96: =IFERROR(VLOOKUP(D96,Data!$A:$B,2,0),"Revisar") -> Gastos Variables | H96: NA | I96: {=_xlfn.XLOOKUP($H96,Data!$E:$E,Data!$F:$F,"Revisar",0)} -> NA | J96: {=_xlfn.XLOOKUP($H96,Data!$E:$E,Data!$G:$G,"Revisar",0)} -> NA | K96: NA | L96: =F96 -> 6
A97: 46174 | B97: TRANSFERENCIA VIRTUAL | C97: -19000000 | D97: Pago proveedores | E97: Abono 2 - Logist / Evento CCB | F97: 6 | G97: =IFERROR(VLOOKUP(D97,Data!$A:$B,2,0),"Revisar") -> Costo Ventas | H97: M260501 | I97: {=_xlfn.XLOOKUP($H97,Data!$E:$E,Data!$F:$F,"Revisar",0)} -> Psiconometrics | J97: {=_xlfn.XLOOKUP($H97,Data!$E:$E,Data!$G:$G,"Revisar",0)} -> Evento Camara Comercio | K97: Si | L97: =F97 -> 6 | M97: FV-1537
A98: 46174 | B98: ABONO INTERESES AHORROS | C98: 951 | D98: Intereses | E98: Intereses ahorros | F98: 6 | G98: =IFERROR(VLOOKUP(D98,Data!$A:$B,2,0),"Revisar") -> Gastos Variables | H98: NA | I98: {=_xlfn.XLOOKUP($H98,Data!$E:$E,Data!$F:$F,"Revisar",0)} -> NA | J98: {=_xlfn.XLOOKUP($H98,Data!$E:$E,Data!$G:$G,"Revisar",0)} -> NA | K98: NA | L98: =F98 -> 6
A99: 46174 | B99: TRANSFERENCIA CTA SUC VIRTUAL | C99: -932000 | D99: Pago proveedores | E99: Abono pago cuadernos KASPERSKY | F99: 6 | G99: =IFERROR(VLOOKUP(D99,Data!$A:$B,2,0),"Revisar") -> Costo Ventas | H99: M260401 | I99: {=_xlfn.XLOOKUP($H99,Data!$E:$E,Data!$F:$F,"Revisar",0)} -> Kaspersky | J99: {=_xlfn.XLOOKUP($H99,Data!$E:$E,Data!$G:$G,"Revisar",0)} -> Bolsa Incentivos 2026 | K99: Si | L99: =F99 -> 6 | M99: SD-457
A100: 46174 | B100: IMPTO GOBIERNO 4X1000 | C100: -6948 | D100: GMF 4x1000 | E100: 4x1000 | F100: 6 | G100: =IFERROR(VLOOKUP(D100,Data!$A:$B,2,0),"Revisar") -> Gastos Variables | H100: NA | I100: {=_xlfn.XLOOKUP($H100,Data!$E:$E,Data!$F:$F,"Revisar",0)} -> NA | J100: {=_xlfn.XLOOKUP($H100,Data!$E:$E,Data!$G:$G,"Revisar",0)} -> NA | K100: NA | L100: =F100 -> 6
...

Sheet CxC
B1: CUENTAS POR COBRAR (CxC) — MANGLAR | F1: 3115790113 | G1: Revisar con Ferney
B2: Una fila por factura emitida. El saldo es lo que falta cobrar despues de las retenciones.
B4: Resumen
B5: Total facturado (con IVA) | E5: Retenciones aplicadas | G5: Cobrado en banco | I5: Cartera pendiente
B6: =J52 -> 5.7915104e+08 | E6: =K52 -> 13189919 | G6: =M52 -> 5.4156595e+08 | I6: =N52 -> 24395166
B9: Facturas
B10: Folio | C10: Fecha | D10: Centro de costo | E10: Cliente | F10: Proyecto | G10: Concepto | H10: Base sin IVA | I10: IVA 19% | J10: Total Facturado | K10: Retenciones | L10: Neto a Cobrar | M10: Cobrado | N10: Saldo Pendiente | O10: Fecha Vence | P10: Dias Venc. | Q10: Antiguedad | R10: Estado | S10: Notas | T10: Mes | U10: ReteIVA | V10: Retefuente
A11: =VLOOKUP(E11,$B$66:$B$80,1,0) -> AXIS | B11: DAFE 1 | C11: 46127 | D11: M260101 | E11: {=_xlfn.XLOOKUP($D11,Data!$E:$E,Data!$F:$F,"Revisar",0)} -> AXIS | F11: {=_xlfn.XLOOKUP($D11,Data!$E:$E,Data!$G:$G,"Revisar",0)} -> Evento mundial de fútbol y merchandising | G11: Evento mundial de futbol y merchandising | H11: 31867817 | I11: 6054885.2 | J11: =IF($B11="","",H11+I11) -> 37922702 | K11: 908233.23 | L11: =IF($B11="","",J11-K11) -> 37014469 | M11: =IF($B11="","",SUMIFS('Extractos bancarios - Manglar'!$C:$C,'Extractos bancarios - Manglar'!$M:$M,$B11)) -> 37014469 | N11: 0 | O11: 46146 | P11: =IF($B11="","",IF(N11<=0,0,MAX(0,TODAY()-O11))) -> 0 | Q11: =IF($B11="","",IF(N11<=0,"Al dia",IF(P11=0,"Vigente",IF(P11<=30,"1-30",IF(P11<=60,"31-60",IF(P11<=90,"61-90",">90")))))) -> Al dia | R11: =IF($B11="","",IF(N11<=0,"Cobrada",IF(M11=0,"Pendiente","Parcial"))) -> Cobrada | S11: ReteIVA 15% | T11: =IF($C11="","",MONTH($C11)) -> 4 | U11: =IF($B11="","",IF(ABS(K11-H11*0.04)<1000,0,IF(K11>=I11*0.15-1000,I11*0.15,0))) -> 908232.78 | V11: =IF($B11="","",K11-U11) -> 0.4455
A12: =VLOOKUP(E12,$B$66:$B$80,1,0) -> Konrad Adenauer Stiftung | B12: DAFE 3 | C12: 46129 | D12: M260201 | E12: {=_xlfn.XLOOKUP($D12,Data!$E:$E,Data!$F:$F,"Revisar",0)} -> Konrad Adenauer Stiftung | F12: {=_xlfn.XLOOKUP($D12,Data!$E:$E,Data!$G:$G,"Revisar",0)} -> Material KAS - Tacos y pocillos | G12: Tacos, mugs y tablas en bambu | H12: 8102757 | I12: 1539523.8 | J12: =IF($B12="","",H12+I12) -> 9642280.8 | K12: 0 | L12: =IF($B12="","",J12-K12) -> 9642280.8 | M12: =IF($B12="","",SUMIFS('Extractos bancarios - Manglar'!$C:$C,'Extractos bancarios - Manglar'!$M:$M,$B12)) -> 9642280.8 | N12: =IF($B12="","",L12-M12) -> 0 | O12: 46142 | P12: =IF($B12="","",IF(N12<=0,0,MAX(0,TODAY()-O12))) -> 0 | Q12: =IF($B12="","",IF(N12<=0,"Al dia",IF(P12=0,"Vigente",IF(P12<=30,"1-30",IF(P12<=60,"31-60",IF(P12<=90,"61-90",">90")))))) -> Al dia | R12: =IF($B12="","",IF(N12<=0,"Cobrada",IF(M12=0,"Pendiente","Parcial"))) -> Cobrada | S12: Cobrada sin retencion | T12: =IF($C12="","",MONTH($C12)) -> 4 | U12: =IF($B12="","",IF(ABS(K12-H12*0.04)<1000,0,IF(K12>=I12*0.15-1000,I12*0.15,0))) -> 0 | V12: =IF($B12="","",K12-U12) -> 0
A13: =VLOOKUP(E13,$B$66:$B$80,1,0) -> Innovaitors | B13: DAFE 4 | C13: 46147 | D13: M260301 | E13: {=_xlfn.XLOOKUP($D13,Data!$E:$E,Data!$F:$F,"Revisar",0)} -> Innovaitors | F13: {=_xlfn.XLOOKUP($D13,Data!$E:$E,Data!$G:$G,"Revisar",0)} -> Kits Innovaitors | G13: Kits premium agenda y esfero | H13: 1760000 | I13: 334400 | J13: =IF($B13="","",H13+I13) -> 2094400 | K13: 26630 | L13: =IF($B13="","",J13-K13) -> 2067770 | M13: =IF($B13="","",SUMIFS('Extractos bancarios - Manglar'!$C:$C,'Extractos bancarios - Manglar'!$M:$M,$B13)) -> 2067770 | N13: =IF($B13="","",L13-M13) -> 0 | O13: 46161 | P13: =IF($B13="","",IF(N13<=0,0,MAX(0,TODAY()-O13))) -> 0 | Q13: =IF($B13="","",IF(N13<=0,"Al dia",IF(P13=0,"Vigente",IF(P13<=30,"1-30",IF(P13<=60,"31-60",IF(P13<=90,"61-90",">90")))))) -> Al dia | R13: =IF($B13="","",IF(N13<=0,"Cobrada",IF(M13=0,"Pendiente","Parcial"))) -> Cobrada | S13: Verificar aplicacion del pago | T13: =IF($C13="","",MONTH($C13)) -> 5 | U13: =IF($B13="","",IF(ABS(K13-H13*0.04)<1000,0,IF(K13>=I13*0.15-1000,I13*0.15,0))) -> 0 | V13: =IF($B13="","",K13-U13) -> 26630
A14: =VLOOKUP(E14,$B$66:$B$80,1,0) -> Kaspersky | B14: DAFE 5 | C14: 46147 | D14: M260401 | E14: {=_xlfn.XLOOKUP($D14,Data!$E:$E,Data!$F:$F,"Revisar",0)} -> Kaspersky | F14: {=_xlfn.XLOOKUP($D14,Data!$E:$E,Data!$G:$G,"Revisar",0)} -> Bolsa Incentivos 2026 | G14: Incentives Campaign NOLA Q2 | H14: 60400005 | I14: 11476001 | J14: =IF($B14="","",H14+I14) -> 71876006 | K14: 1721399.9 | L14: =IF($B14="","",J14-K14) -> 70154606 | M14: =IF($B14="","",SUMIFS('Extractos bancarios - Manglar'!$C:$C,'Extractos bancarios - Manglar'!$M:$M,$B14)) -> 70154606 | N14: =IF($B14="","",L14-M14) -> 0 | O14: 46173 | P14: =IF($B14="","",IF(N14<=0,0,MAX(0,TODAY()-O14))) -> 0 | Q14: =IF($B14="","",IF(N14<=0,"Al dia",IF(P14=0,"Vigente",IF(P14<=30,"1-30",IF(P14<=60,"31-60",IF(P14<=90,"61-90",">90")))))) -> Al dia | R14: =IF($B14="","",IF(N14<=0,"Cobrada",IF(M14=0,"Pendiente","Parcial"))) -> Cobrada | S14: ReteIVA 15% | T14: =IF($C14="","",MONTH($C14)) -> 5 | U14: =IF($B14="","",IF(ABS(K14-H14*0.04)<1000,0,IF(K14>=I14*0.15-1000,I14*0.15,0))) -> 1721400.1 | V14: =IF($B14="","",K14-U14) -> -0.1925
A15: =VLOOKUP(E15,$B$66:$B$80,1,0) -> AXIS | B15: DAFE 6 | C15: 46154 | D15: M260102 | E15: {=_xlfn.XLOOKUP($D15,Data!$E:$E,Data!$F:$F,"Revisar",0)} -> AXIS | F15: {=_xlfn.XLOOKUP($D15,Data!$E:$E,Data!$G:$G,"Revisar",0)} -> Camisetas Academy | G15: Polos entrenadores academy | H15: 2349000 | I15: 446310 | J15: =IF($B15="","",H15+I15) -> 2795310 | K15: 0 | L15: =IF($B15="","",J15-K15) -> 2795310 | M15: =IF($B15="","",SUMIFS('Extractos bancarios - Manglar'!$C:$C,'Extractos bancarios - Manglar'!$M:$M,$B15)) -> 2795310 | N15: =IF($B15="","",L15-M15) -> 0 | O15: 46172 | P15: =IF($B15="","",IF(N15<=0,0,MAX(0,TODAY()-O15))) -> 0 | Q15: =IF($B15="","",IF(N15<=0,"Al dia",IF(P15=0,"Vigente",IF(P15<=30,"1-30",IF(P15<=60,"31-60",IF(P15<=90,"61-90",">90")))))) -> Al dia | R15: =IF($B15="","",IF(N15<=0,"Cobrada",IF(M15=0,"Pendiente","Parcial"))) -> Cobrada | S15: Cobrada sin retencion | T15: =IF($C15="","",MONTH($C15)) -> 5 | U15: =IF($B15="","",IF(ABS(K15-H15*0.04)<1000,0,IF(K15>=I15*0.15-1000,I15*0.15,0))) -> 0 | V15: =IF($B15="","",K15-U15) -> 0
A16: =VLOOKUP(E16,$B$66:$B$80,1,0) -> Innovaitors | B16: DAFE 7 | C16: 46161 | D16: M260302 | E16: {=_xlfn.XLOOKUP($D16,Data!$E:$E,Data!$F:$F,"Revisar",0)} -> Innovaitors | F16: {=_xlfn.XLOOKUP($D16,Data!$E:$E,Data!$G:$G,"Revisar",0)} -> Banners Rollup | G16: Banner roll up y transporte | H16: 260000 | I16: 49400 | J16: =IF($B16="","",H16+I16) -> 309400 | K16: 0 | L16: =IF($B16="","",J16-K16) -> 309400 | M16: =IF($B16="","",SUMIFS('Extractos bancarios - Manglar'!$C:$C,'Extractos bancarios - Manglar'!$M:$M,$B16)) -> 0 | N16: =IF($B16="","",L16-M16) -> 309400 | O16: 46172 | P16: =IF($B16="","",IF(N16<=0,0,MAX(0,TODAY()-O16))) -> 151 | Q16: =IF($B16="","",IF(N16<=0,"Al dia",IF(P16=0,"Vigente",IF(P16<=30,"1-30",IF(P16<=60,"31-60",IF(P16<=90,"61-90",">90")))))) -> >90 | R16: Cobrada | S16: Pago a TPC | T16: =IF($C16="","",MONTH($C16)) -> 5 | U16: =IF($B16="","",IF(ABS(K16-H16*0.04)<1000,0,IF(K16>=I16*0.15-1000,I16*0.15,0))) -> 0 | V16: =IF($B16="","",K16-U16) -> 0
A17: =VLOOKUP(E17,$B$66:$B$80,1,0) -> Psiconometrics | B17: DAFE 9 | C17: 46168 | D17: M260501 | E17: {=_xlfn.XLOOKUP($D17,Data!$E:$E,Data!$F:$F,"Revisar",0)} -> Psiconometrics | F17: {=_xlfn.XLOOKUP($D17,Data!$E:$E,Data!$G:$G,"Revisar",0)} -> Evento Camara Comercio | G17: Ejecucion evento CIMA 2026 | H17: 154135498 | I17: 29285745 | J17: =IF($B17="","",H17+I17) -> 1.8342124e+08 | K17: 3949721.6 | L17: =IF($B17="","",J17-K17) -> 179471521 | M17: =IF($B17="","",SUMIFS('Extractos bancarios - Manglar'!$C:$C,'Extractos bancarios - Manglar'!$M:$M,$B17)) -> 179471521 | N17: =IF($B17="","",L17-M17) -> 0 | O17: 46172 | P17: =IF($B17="","",IF(N17<=0,0,MAX(0,TODAY()-O17))) -> 0 | Q17: =IF($B17="","",IF(N17<=0,"Al dia",IF(P17=0,"Vigente",IF(P17<=30,"1-30",IF(P17<=60,"31-60",IF(P17<=90,"61-90",">90")))))) -> Al dia | R17: =IF($B17="","",IF(N17<=0,"Cobrada",IF(M17=0,"Pendiente","Parcial"))) -> Cobrada | S17: Retefuente 4% neta del reintegro de julio | T17: =IF($C17="","",MONTH($C17)) -> 5 | U17: =IF($B17="","",IF(ABS(K17-H17*0.04)<1000,0,IF(K17>=I17*0.15-1000,I17*0.15,0))) -> 0 | V17: =IF($B17="","",K17-U17) -> 3949721.6
A18: =VLOOKUP(E18,$B$66:$B$80,1,0) -> Psiconometrics | B18: DAFE 10 | C18: 46168 | D18: M260501 | E18: {=_xlfn.XLOOKUP($D18,Data!$E:$E,Data!$F:$F,"Revisar",0)} -> Psiconometrics | F18: {=_xlfn.XLOOKUP($D18,Data!$E:$E,Data!$G:$G,"Revisar",0)} -> Evento Camara Comercio | G18: Ejecucion evento CIMA 2026 | H18: 38533875 | I18: 7321436.2 | J18: =IF($B18="","",H18+I18) -> 45855311 | K18: 1541355.2 | L18: =IF($B18="","",J18-K18) -> 44313956 | M18: =IF($B18="","",SUMIFS('Extractos bancarios - Manglar'!$C:$C,'Extractos bancarios - Manglar'!$M:$M,$B18)) -> 44313956 | N18: =IF($B18="","",L18-M18) -> 0 | O18: 46183 | P18: =IF($B18="","",IF(N18<=0,0,MAX(0,TODAY()-O18))) -> 0 | Q18: =IF($B18="","",IF(N18<=0,"Al dia",IF(P18=0,"Vigente",IF(P18<=30,"1-30",IF(P18<=60,"31-60",IF(P18<=90,"61-90",">90")))))) -> Al dia | R18: =IF($B18="","",IF(N18<=0,"Cobrada",IF(M18=0,"Pendiente","Parcial"))) -> Cobrada | S18: Retefuente 4% | T18: =IF($C18="","",MONTH($C18)) -> 5 | U18: =IF($B18="","",IF(ABS(K18-H18*0.04)<1000,0,IF(K18>=I18*0.15-1000,I18*0.15,0))) -> 0 | V18: =IF($B18="","",K18-U18) -> 1541355.2
A19: =VLOOKUP(E19,$B$66:$B$80,1,0) -> AXIS | B19: DAFE 13 | C19: 46206 | D19: M260103 | E19: {=_xlfn.XLOOKUP($D19,Data!$E:$E,Data!$F:$F,"Revisar",0)} -> AXIS | F19: {=_xlfn.XLOOKUP($D19,Data!$E:$E,Data!$G:$G,"Revisar",0)} -> Hoodies Challenge | G19: Hoodies premio reto wellness | H19: 2744000 | I19: 521360 | J19: =IF($B19="","",H19+I19) -> 3265360 | K19: 0 | L19: =IF($B19="","",J19-K19) -> 3265360 | M19: =IF($B19="","",SUMIFS('Extractos bancarios - Manglar'!$C:$C,'Extractos bancarios - Manglar'!$M:$M,$B19)) -> 3265360 | N19: =IF($B19="","",L19-M19) -> 0 | O19: 46233 | P19: =IF($B19="","",IF(N19<=0,0,MAX(0,TODAY()-O19))) -> 0 | Q19: =IF($B19="","",IF(N19<=0,"Al dia",IF(P19=0,"Vigente",IF(P19<=30,"1-30",IF(P19<=60,"31-60",IF(P19<=90,"61-90",">90")))))) -> Al dia | R19: =IF($B19="","",IF(N19<=0,"Cobrada",IF(M19=0,"Pendiente","Parcial"))) -> Cobrada | S19: Reemplaza a DAFE 11 | T19: =IF($C19="","",MONTH($C19)) -> 7 | U19: =IF($B19="","",IF(ABS(K19-H19*0.04)<1000,0,IF(K19>=I19*0.15-1000,I19*0.15,0))) -> 0 | V19: =IF($B19="","",K19-U19) -> 0
A20: =VLOOKUP(E20,$B$66:$B$80,1,0) -> AXIS | B20: DAFE 14 | C20: 46206 | D20: M260104 | E20: {=_xlfn.XLOOKUP($D20,Data!$E:$E,Data!$F:$F,"Revisar",0)} -> AXIS | F20: {=_xlfn.XLOOKUP($D20,Data!$E:$E,Data!$G:$G,"Revisar",0)} -> Merch y transporte para Cena feria de seguridad | G20: Transporte y props cena Feria ESS | H20: 10875250 | I20: 2066297.5 | J20: =IF($B20="","",H20+I20) -> 12941548 | K20: 388148.5 | L20: =IF($B20="","",J20-K20) -> 12553399 | M20: =IF($B20="","",SUMIFS('Extractos bancarios - Manglar'!$C:$C,'Extractos bancarios - Manglar'!$M:$M,$B20)) -> 12553399 | N20: =IF($B20="","",L20-M20) -> 0 | O20: 46233 | P20: =IF($B20="","",IF(N20<=0,0,MAX(0,TODAY()-O20))) -> 0 | Q20: =IF($B20="","",IF(N20<=0,"Al dia",IF(P20=0,"Vigente",IF(P20<=30,"1-30",IF(P20<=60,"31-60",IF(P20<=90,"61-90",">90")))))) -> Al dia | R20: =IF($B20="","",IF(N20<=0,"Cobrada",IF(M20=0,"Pendiente","Parcial"))) -> Cobrada | S20: Reemplaza a DAFE 12. ReteIVA 15% | T20: =IF($C20="","",MONTH($C20)) -> 7 | U20: =IF($B20="","",IF(ABS(K20-H20*0.04)<1000,0,IF(K20>=I20*0.15-1000,I20*0.15,0))) -> 309944.62 | V20: =IF($B20="","",K20-U20) -> 78203.875
A21: =VLOOKUP(E21,$B$66:$B$80,1,0) -> ANIXTER | B21: DAFE 15 | C21: 46226 | D21: M260601 | E21: {=_xlfn.XLOOKUP($D21,Data!$E:$E,Data!$F:$F,"Revisar",0)} -> ANIXTER | F21: {=_xlfn.XLOOKUP($D21,Data!$E:$E,Data!$G:$G,"Revisar",0)} -> Evento BoB Datacenter Day - Bogotá | G21: Evento Datacenter Day Bogota | H21: 20054658 | I21: 3810385 | J21: =IF($B21="","",H21+I21) -> 23865043 | K21: 571557.75 | L21: =IF($B21="","",J21-K21) -> 23293485 | M21: =IF($B21="","",SUMIFS('Extractos bancarios - Manglar'!$C:$C,'Extractos bancarios - Manglar'!$M:$M,$B21)) -> 23293485 | N21: =IF($B21="","",L21-M21) -> 0 | O21: 46257 | P21: =IF($B21="","",IF(N21<=0,0,MAX(0,TODAY()-O21))) -> 0 | Q21: =IF($B21="","",IF(N21<=0,"Al dia",IF(P21=0,"Vigente",IF(P21<=30,"1-30",IF(P21<=60,"31-60",IF(P21<=90,"61-90",">90")))))) -> Al dia | R21: =IF($B21="","",IF(N21<=0,"Cobrada",IF(M21=0,"Pendiente","Parcial"))) -> Cobrada | S21: Por cobrar | T21: =IF($C21="","",MONTH($C21)) -> 7 | U21: =IF($B21="","",IF(ABS(K21-H21*0.04)<1000,0,IF(K21>=I21*0.15-1000,I21*0.15,0))) -> 571557.75 | V21: =IF($B21="","",K21-U21) -> -0.003
A22: =VLOOKUP(E22,$B$66:$B$80,1,0) -> ANIXTER | B22: DAFE 16 | C22: 46226 | D22: M260602 | E22: {=_xlfn.XLOOKUP($D22,Data!$E:$E,Data!$F:$F,"Revisar",0)} -> ANIXTER | F22: {=_xlfn.XLOOKUP($D22,Data!$E:$E,Data!$G:$G,"Revisar",0)} -> Tiquetes y alojamiento Pedro Rodriguez | G22: Speaker Datacenter Day Bogota | H22: 4890000 | I22: 929100 | J22: =IF($B22="","",H22+I22) -> 5819100 | K22: 139365 | L22: =IF($B22="","",J22-K22) -> 5679735 | M22: =IF($B22="","",SUMIFS('Extractos bancarios - Manglar'!$C:$C,'Extractos bancarios - Manglar'!$M:$M,$B22)) -> 5679735 | N22: =IF($B22="","",L22-M22) -> 0 | O22: 46257 | P22: =IF($B22="","",IF(N22<=0,0,MAX(0,TODAY()-O22))) -> 0 | Q22: =IF($B22="","",IF(N22<=0,"Al dia",IF(P22=0,"Vigente",IF(P22<=30,"1-30",IF(P22<=60,"31-60",IF(P22<=90,"61-90",">90")))))) -> Al dia | R22: =IF($B22="","",IF(N22<=0,"Cobrada",IF(M22=0,"Pendiente","Parcial"))) -> Cobrada | S22: Por cobrar | T22: =IF($C22="","",MONTH($C22)) -> 7 | U22: =IF($B22="","",IF(ABS(K22-H22*0.04)<1000,0,IF(K22>=I22*0.15-1000,I22*0.15,0))) -> 139365 | V22: =IF($B22="","",K22-U22) -> 0
A23: =VLOOKUP(E23,$B$66:$B$80,1,0) -> Commscope | B23: DAFE 17 | C23: 46226 | D23: M260701 | E23: {=_xlfn.XLOOKUP($D23,Data!$E:$E,Data!$F:$F,"Revisar",0)} -> Commscope | F23: {=_xlfn.XLOOKUP($D23,Data!$E:$E,Data!$G:$G,"Revisar",0)} -> Regalos Cartagena | G23: HSA Giveaways Elevate Pro Cartagena | H23: 4060000 | I23: 771400 | J23: =IF($B23="","",H23+I23) -> 4831400 | K23: 115710 | L23: =IF($B23="","",J23-K23) -> 4715690 | M23: =IF($B23="","",SUMIFS('Extractos bancarios - Manglar'!$C:$C,'Extractos bancarios - Manglar'!$M:$M,$B23)) -> 4715690 | N23: =IF($B23="","",L23-M23) -> 0 | O23: 46257 | P23: =IF($B23="","",IF(N23<=0,0,MAX(0,TODAY()-O23))) -> 0 | Q23: =IF($B23="","",IF(N23<=0,"Al dia",IF(P23=0,"Vigente",IF(P23<=30,"1-30",IF(P23<=60,"31-60",IF(P23<=90,"61-90",">90")))))) -> Al dia | R23: =IF($B23="","",IF(N23<=0,"Cobrada",IF(M23=0,"Pendiente","Parcial"))) -> Cobrada | S23: Por cobrar | T23: =IF($C23="","",MONTH($C23)) -> 7 | U23: =IF($B23="","",IF(ABS(K23-H23*0.04)<1000,0,IF(K23>=I23*0.15-1000,I23*0.15,0))) -> 115710 | V23: =IF($B23="","",K23-U23) -> 0
A24: =VLOOKUP(E24,$B$66:$B$80,1,0) -> Commscope | B24: DAFE 18 | C24: 46247 | D24: M260702 | E24: {=_xlfn.XLOOKUP($D24,Data!$E:$E,Data!$F:$F,"Revisar",0)} -> Commscope | F24: {=_xlfn.XLOOKUP($D24,Data!$E:$E,Data!$G:$G,"Revisar",0)} -> Brochures COMMSCOPE | G24: HSA - Brochures for Feria ESS | H24: 2185714 | I24: 415285.66 | J24: =IF($B24="","",H24+I24) -> 2600999.7 | K24: 62292.85 | L24: =IF($B24="","",J24-K24) -> 2538706.8 | M24: =IF($B24="","",SUMIFS('Extractos bancarios - Manglar'!$C:$C,'Extractos bancarios - Manglar'!$M:$M,$B24)) -> 2538706.8 | N24: =IF($B24="","",L24-M24) -> 0 | O24: 46277 | P24: =IF($B24="","",IF(N24<=0,0,MAX(0,TODAY()-O24))) -> 0 | Q24: =IF($B24="","",IF(N24<=0,"Al dia",IF(P24=0,"Vigente",IF(P24<=30,"1-30",IF(P24<=60,"31-60",IF(P24<=90,"61-90",">90")))))) -> Al dia | R24: =IF($B24="","",IF(N24<=0,"Cobrada",IF(M24=0,"Pendiente","Parcial"))) -> Cobrada | S24: Orden de compra PO 7000294156 | T24: =IF($C24="","",MONTH($C24)) -> 8 | U24: =IF($B24="","",IF(ABS(K24-H24*0.04)<1000,0,IF(K24>=I24*0.15-1000,I24*0.15,0))) -> 62292.849 | V24: =IF($B24="","",K24-U24) -> 0.0010000001
A25: =VLOOKUP(E25,$B$66:$B$80,1,0) -> AXIS | B25: DAFE 19 | C25: 46247 | D25: M260105 | E25: {=_xlfn.XLOOKUP($D25,Data!$E:$E,Data!$F:$F,"Revisar",0)} -> AXIS | F25: {=_xlfn.XLOOKUP($D25,Data!$E:$E,Data!$G:$G,"Revisar",0)} -> Tarjetas regalo AMAZON y Pantalla | G25: Datacenter Day Anixter Event Bogota | H25: 1500000 | I25: 285000 | J25: =IF($B25="","",H25+I25) -> 1785000 | K25: 0 | L25: =IF($B25="","",J25-K25) -> 1785000 | M25: =IF($B25="","",SUMIFS('Extractos bancarios - Manglar'!$C:$C,'Extractos bancarios - Manglar'!$M:$M,$B25)) -> 1785000 | N25: =IF($B25="","",L25-M25) -> 0 | O25: 46277 | P25: =IF($B25="","",IF(N25<=0,0,MAX(0,TODAY()-O25))) -> 0 | Q25: =IF($B25="","",IF(N25<=0,"Al dia",IF(P25=0,"Vigente",IF(P25<=30,"1-30",IF(P25<=60,"31-60",IF(P25<=90,"61-90",">90")))))) -> Al dia | R25: =IF($B25="","",IF(N25<=0,"Cobrada",IF(M25=0,"Pendiente","Parcial"))) -> Cobrada | T25: =IF($C25="","",MONTH($C25)) -> 8 | U25: =IF($B25="","",IF(ABS(K25-H25*0.04)<1000,0,IF(K25>=I25*0.15-1000,I25*0.15,0))) -> 0 | V25: =IF($B25="","",K25-U25) -> 0
A26: =VLOOKUP(E26,$B$66:$B$80,1,0) -> AXIS | B26: DAFE 20 | C26: 46252 | D26: M260106 | E26: {=_xlfn.XLOOKUP($D26,Data!$E:$E,Data!$F:$F,"Revisar",0)} -> AXIS | F26: {=_xlfn.XLOOKUP($D26,Data!$E:$E,Data!$G:$G,"Revisar",0)} -> Produccion gomas | G26: Gomas para evento de oficina | H26: 1980000 | I26: 376200 | J26: =IF($B26="","",H26+I26) -> 2356200 | K26: 0 | L26: =IF($B26="","",J26-K26) -> 2356200 | M26: =IF($B26="","",SUMIFS('Extractos bancarios - Manglar'!$C:$C,'Extractos bancarios - Manglar'!$M:$M,$B26)) -> 2356200 | N26: =IF($B26="","",L26-M26) -> 0 | O26: 46282 | P26: =IF($B26="","",IF(N26<=0,0,MAX(0,TODAY()-O26))) -> 0 | Q26: =IF($B26="","",IF(N26<=0,"Al dia",IF(P26=0,"Vigente",IF(P26<=30,"1-30",IF(P26<=60,"31-60",IF(P26<=90,"61-90",">90")))))) -> Al dia | R26: =IF($B26="","",IF(N26<=0,"Cobrada",IF(M26=0,"Pendiente","Parcial"))) -> Cobrada | T26: =IF($C26="","",MONTH($C26)) -> 8 | U26: =IF($B26="","",IF(ABS(K26-H26*0.04)<1000,0,IF(K26>=I26*0.15-1000,I26*0.15,0))) -> 0 | V26: =IF($B26="","",K26-U26) -> 0
A27: =VLOOKUP(E27,$B$66:$B$80,1,0) -> Commscope | B27: DAFE 21 | C27: 46252 | D27: M260703 | E27: {=_xlfn.XLOOKUP($D27,Data!$E:$E,Data!$F:$F,"Revisar",0)} -> Commscope | F27: {=_xlfn.XLOOKUP($D27,Data!$E:$E,Data!$G:$G,"Revisar",0)} -> Maletas VIP | G27: CALA Predictor Prizes Colombia Back Pack | H27: 1309866 | I27: 248874.54 | J27: =IF($B27="","",H27+I27) -> 1558740.5 | K27: 37331.18 | L27: =IF($B27="","",J27-K27) -> 1521409.4 | M27: =IF($B27="","",SUMIFS('Extractos bancarios - Manglar'!$C:$C,'Extractos bancarios - Manglar'!$M:$M,$B27)) -> 1521409.4 | N27: =IF($B27="","",L27-M27) -> 0 | O27: 46282 | P27: =IF($B27="","",IF(N27<=0,0,MAX(0,TODAY()-O27))) -> 0 | Q27: =IF($B27="","",IF(N27<=0,"Al dia",IF(P27=0,"Vigente",IF(P27<=30,"1-30",IF(P27<=60,"31-60",IF(P27<=90,"61-90",">90")))))) -> Al dia | R27: =IF($B27="","",IF(N27<=0,"Cobrada",IF(M27=0,"Pendiente","Parcial"))) -> Cobrada | S27: Orden de compra PR369334 | T27: =IF($C27="","",MONTH($C27)) -> 8 | U27: =IF($B27="","",IF(ABS(K27-H27*0.04)<1000,0,IF(K27>=I27*0.15-1000,I27*0.15,0))) -> 37331.181 | V27: =IF($B27="","",K27-U27) -> -0.0010000001
A28: =VLOOKUP(E28,$B$66:$B$80,1,0) -> ANIXTER | B28: DAFE 22 | C28: 46253 | D28: M260603 | E28: {=_xlfn.XLOOKUP($D28,Data!$E:$E,Data!$F:$F,"Revisar",0)} -> ANIXTER | F28: {=_xlfn.XLOOKUP($D28,Data!$E:$E,Data!$G:$G,"Revisar",0)} -> Almuerzo Evento Corferias ESS+ | G28: Almuerzo feria ESS+ | H28: 22146348 | I28: 4207806.1 | J28: =IF($B28="","",H28+I28) -> 26354154 | K28: 631170.92 | L28: =IF($B28="","",J28-K28) -> 25722983 | M28: =IF($B28="","",SUMIFS('Extractos bancarios - Manglar'!$C:$C,'Extractos bancarios - Manglar'!$M:$M,$B28)) -> 25722983 | N28: =IF($B28="","",L28-M28) -> 0 | O28: 46282 | P28: =IF($B28="","",IF(N28<=0,0,MAX(0,TODAY()-O28))) -> 0 | Q28: =IF($B28="","",IF(N28<=0,"Al dia",IF(P28=0,"Vigente",IF(P28<=30,"1-30",IF(P28<=60,"31-60",IF(P28<=90,"61-90",">90")))))) -> Al dia | R28: =IF($B28="","",IF(N28<=0,"Cobrada",IF(M28=0,"Pendiente","Parcial"))) -> Cobrada | T28: =IF($C28="","",MONTH($C28)) -> 8 | U28: =IF($B28="","",IF(ABS(K28-H28*0.04)<1000,0,IF(K28>=I28*0.15-1000,I28*0.15,0))) -> 631170.92 | V28: =IF($B28="","",K28-U28) -> 0.0020000001
A29: =VLOOKUP(E29,$B$66:$B$80,1,0) -> AXIS | B29: DAFE 23 | C29: 46255 | D29: M260107 | E29: {=_xlfn.XLOOKUP($D29,Data!$E:$E,Data!$F:$F,"Revisar",0)} -> AXIS | F29: {=_xlfn.XLOOKUP($D29,Data!$E:$E,Data!$G:$G,"Revisar",0)} -> Catering ESS | G29: Mezzanine - ESS+ | H29: 33582650 | I29: 6380703.5 | J29: =IF($B29="","",H29+I29) -> 39963354 | K29: 957105.53 | L29: =IF($B29="","",J29-K29) -> 39006248 | M29: =IF($B29="","",SUMIFS('Extractos bancarios - Manglar'!$C:$C,'Extractos bancarios - Manglar'!$M:$M,$B29)) -> 39343373 | N29: =IF($B29="","",L29-M29) -> -337125.03 | O29: 46285 | P29: =IF($B29="","",IF(N29<=0,0,MAX(0,TODAY()-O29))) -> 0 | Q29: =IF($B29="","",IF(N29<=0,"Al dia",IF(P29=0,"Vigente",IF(P29<=30,"1-30",IF(P29<=60,"31-60",IF(P29<=90,"61-90",">90")))))) -> Al dia | R29: =IF($B29="","",IF(N29<=0,"Cobrada",IF(M29=0,"Pendiente","Parcial"))) -> Cobrada | T29: =IF($C29="","",MONTH($C29)) -> 8 | U29: =IF($B29="","",IF(ABS(K29-H29*0.04)<1000,0,IF(K29>=I29*0.15-1000,I29*0.15,0))) -> 957105.52 | V29: =IF($B29="","",K29-U29) -> 0.0050000001
A30: =VLOOKUP(E30,$B$66:$B$80,1,0) -> Konrad Adenauer Stiftung | B30: DAFE 24 | C30: 46266 | D30: M260202 | E30: {=_xlfn.XLOOKUP($D30,Data!$E:$E,Data!$F:$F,"Revisar",0)} -> Konrad Adenauer Stiftung | F30: {=_xlfn.XLOOKUP($D30,Data!$E:$E,Data!$G:$G,"Revisar",0)} -> Morrales y letras KAS | G30: Produccion de 60 maletas marcadas y letras KAS en MDF | H30: 8510000 | I30: 1616900 | J30: =IF($B30="","",H30+I30) -> 10126900 | K30: 0 | L30: =IF($B30="","",J30-K30) -> 10126900 | M30: =IF($B30="","",SUMIFS('Extractos bancarios - Manglar'!$C:$C,'Extractos bancarios - Manglar'!$M:$M,$B30)) -> 10126900 | N30: =IF($B30="","",L30-M30) -> 0 | O30: 46296 | P30: =IF($B30="","",IF(N30<=0,0,MAX(0,TODAY()-O30))) -> 0 | Q30: =IF($B30="","",IF(N30<=0,"Al dia",IF(P30=0,"Vigente",IF(P30<=30,"1-30",IF(P30<=60,"31-60",IF(P30<=90,"61-90",">90")))))) -> Al dia | R30: =IF($B30="","",IF(N30<=0,"Cobrada",IF(M30=0,"Pendiente","Parcial"))) -> Cobrada | T30: =IF($C30="","",MONTH($C30)) -> 9 | U30: =IF($B30="","",IF(ABS(K30-H30*0.04)<1000,0,IF(K30>=I30*0.15-1000,I30*0.15,0))) -> 0 | V30: =IF($B30="","",K30-U30) -> 0
A31: =VLOOKUP(E31,$B$66:$B$80,1,0) -> Kaspersky | B31: DAFE 25 | C31: 46267 | D31: M260402 | E31: {=_xlfn.XLOOKUP($D31,Data!$E:$E,Data!$F:$F,"Revisar",0)} -> Kaspersky | F31: {=_xlfn.XLOOKUP($D31,Data!$E:$E,Data!$G:$G,"Revisar",0)} -> Actividades Kaspersky Sep | G31: EBC Bogota, Hotel EBC Bogota | H31: 16527804 | I31: 3140282.8 | J31: =IF($B31="","",H31+I31) -> 19668087 | K31: 471042.41 | L31: =IF($B31="","",J31-K31) -> 19197044 | M31: =IF($B31="","",SUMIFS('Extractos bancarios - Manglar'!$C:$C,'Extractos bancarios - Manglar'!$M:$M,$B31)) -> 19197044 | N31: 0 | O31: 46297 | P31: =IF($B31="","",IF(N31<=0,0,MAX(0,TODAY()-O31))) -> 0 | Q31: =IF($B31="","",IF(N31<=0,"Al dia",IF(P31=0,"Vigente",IF(P31<=30,"1-30",IF(P31<=60,"31-60",IF(P31<=90,"61-90",">90")))))) -> Al dia | R31: =IF($B31="","",IF(N31<=0,"Cobrada",IF(M31=0,"Pendiente","Parcial"))) -> Cobrada | T31: =IF($C31="","",MONTH($C31)) -> 9 | U31: =IF($B31="","",IF(ABS(K31-H31*0.04)<1000,0,IF(K31>=I31*0.15-1000,I31*0.15,0))) -> 471042.41 | V31: =IF($B31="","",K31-U31) -> -0.004
A32: =VLOOKUP(E32,$B$66:$B$80,1,0) -> AXIS | B32: DAFE 26 | C32: 46267 | D32: M260108 | E32: {=_xlfn.XLOOKUP($D32,Data!$E:$E,Data!$F:$F,"Revisar",0)} -> AXIS | F32: {=_xlfn.XLOOKUP($D32,Data!$E:$E,Data!$G:$G,"Revisar",0)} -> Adicionales Mezanine ESS+ | G32: Adicionales Feria ESS+ Bogota | H32: 4391660 | I32: 834415.4 | J32: =IF($B32="","",H32+I32) -> 5226075.4 | K32: 125162.31 | L32: =IF($B32="","",J32-K32) -> 5100913.1 | M32: =IF($B32="","",SUMIFS('Extractos bancarios - Manglar'!$C:$C,'Extractos bancarios - Manglar'!$M:$M,$B32)) -> 5100913.1 | N32: 0 | O32: 46297 | P32: =IF($B32="","",IF(N32<=0,0,MAX(0,TODAY()-O32))) -> 0 | Q32: =IF($B32="","",IF(N32<=0,"Al dia",IF(P32=0,"Vigente",IF(P32<=30,"1-30",IF(P32<=60,"31-60",IF(P32<=90,"61-90",">90")))))) -> Al dia | R32: =IF($B32="","",IF(N32<=0,"Cobrada",IF(M32=0,"Pendiente","Parcial"))) -> Cobrada | S32: ReteIVA 15% | T32: =IF($C32="","",MONTH($C32)) -> 9 | U32: =IF($B32="","",IF(ABS(K32-H32*0.04)<1000,0,IF(K32>=I32*0.15-1000,I32*0.15,0))) -> 125162.31 | V32: =IF($B32="","",K32-U32) -> 0
A33: =VLOOKUP(E33,$B$66:$B$80,1,0) -> AXIS | B33: DAFE 27 | C33: 46268 | D33: M260109 | E33: {=_xlfn.XLOOKUP($D33,Data!$E:$E,Data!$F:$F,"Revisar",0)} -> AXIS | F33: {=_xlfn.XLOOKUP($D33,Data!$E:$E,Data!$G:$G,"Revisar",0)} -> Recarga Router | G33: Recarga para equipos de Feria | H33: 350000 | I33: 66500 | J33: =IF($B33="","",H33+I33) -> 416500 | K33: 0 | L33: =IF($B33="","",J33-K33) -> 416500 | M33: =IF($B33="","",SUMIFS('Extractos bancarios - Manglar'!$C:$C,'Extractos bancarios - Manglar'!$M:$M,$B33)) -> 416500 | N33: =IF($B33="","",L33-M33) -> 0 | O33: 46298 | P33: =IF($B33="","",IF(N33<=0,0,MAX(0,TODAY()-O33))) -> 0 | Q33: =IF($B33="","",IF(N33<=0,"Al dia",IF(P33=0,"Vigente",IF(P33<=30,"1-30",IF(P33<=60,"31-60",IF(P33<=90,"61-90",">90")))))) -> Al dia | R33: =IF($B33="","",IF(N33<=0,"Cobrada",IF(M33=0,"Pendiente","Parcial"))) -> Cobrada | S33: Centro nuevo, ver notas | T33: =IF($C33="","",MONTH($C33)) -> 9 | U33: =IF($B33="","",IF(ABS(K33-H33*0.04)<1000,0,IF(K33>=I33*0.15-1000,I33*0.15,0))) -> 0 | V33: =IF($B33="","",K33-U33) -> 0
A34: =VLOOKUP(E34,$B$66:$B$80,1,0) -> ANIXTER | B34: DAFE 28 | C34: 46272 | D34: M260604 | E34: {=_xlfn.XLOOKUP($D34,Data!$E:$E,Data!$F:$F,"Revisar",0)} -> ANIXTER | F34: {=_xlfn.XLOOKUP($D34,Data!$E:$E,Data!$G:$G,"Revisar",0)} -> Adicionales Almuerzo ESS+ | G34: Extras Almuerzo Hotel Hilton Bogota | H34: 4339753 | I34: 824553.07 | J34: =IF($B34="","",H34+I34) -> 5164306.1 | K34: 123682.96 | L34: =IF($B34="","",J34-K34) -> 5040623.1 | M34: =IF($B34="","",SUMIFS('Extractos bancarios - Manglar'!$C:$C,'Extractos bancarios - Manglar'!$M:$M,$B34)) -> 5040623.1 | N34: =IF($B34="","",L34-M34) -> 0 | O34: 46302 | P34: =IF($B34="","",IF(N34<=0,0,MAX(0,TODAY()-O34))) -> 0 | Q34: =IF($B34="","",IF(N34<=0,"Al dia",IF(P34=0,"Vigente",IF(P34<=30,"1-30",IF(P34<=60,"31-60",IF(P34<=90,"61-90",">90")))))) -> Al dia | R34: =IF($B34="","",IF(N34<=0,"Cobrada",IF(M34=0,"Pendiente","Parcial"))) -> Cobrada | S34: ReteIVA 15% | T34: =IF($C34="","",MONTH($C34)) -> 9 | U34: =IF($B34="","",IF(ABS(K34-H34*0.04)<1000,0,IF(K34>=I34*0.15-1000,I34*0.15,0))) -> 123682.96 | V34: =IF($B34="","",K34-U34) -> -0.00049999998
A35: =VLOOKUP(E35,$B$66:$B$80,1,0) -> Kaspersky | B35: DAFE 29 | C35: 46279 | D35: M260403 | E35: {=_xlfn.XLOOKUP($D35,Data!$E:$E,Data!$F:$F,"Revisar",0)} -> Kaspersky | F35: {=_xlfn.XLOOKUP($D35,Data!$E:$E,Data!$G:$G,"Revisar",0)} -> Alojamiento 24 a 27 de septiembre | G35: Bogota, Hotel EBC Bogota | H35: 12705000 | I35: 2413950 | J35: =IF($B35="","",H35+I35) -> 15118950 | K35: 362092.5 | L35: =IF($B35="","",J35-K35) -> 14756858 | M35: =IF($B35="","",SUMIFS('Extractos bancarios - Manglar'!$C:$C,'Extractos bancarios - Manglar'!$M:$M,$B35)) -> 14756858 | N35: =IF($B35="","",L35-M35) -> -0.5 | O35: 46309 | P35: =IF($B35="","",IF(N35<=0,0,MAX(0,TODAY()-O35))) -> 0 | Q35: =IF($B35="","",IF(N35<=0,"Al dia",IF(P35=0,"Vigente",IF(P35<=30,"1-30",IF(P35<=60,"31-60",IF(P35<=90,"61-90",">90")))))) -> Al dia | R35: =IF($B35="","",IF(N35<=0,"Cobrada",IF(M35=0,"Pendiente","Parcial"))) -> Cobrada | S35: ReteIVA 15% | T35: =IF($C35="","",MONTH($C35)) -> 9 | U35: =IF($B35="","",IF(ABS(K35-H35*0.04)<1000,0,IF(K35>=I35*0.15-1000,I35*0.15,0))) -> 362092.5 | V35: =IF($B35="","",K35-U35) -> 0
A36: =VLOOKUP(E36,$B$66:$B$80,1,0) -> AXIS | B36: DAFE 30 | C36: 46286 | D36: M260110 | E36: {=_xlfn.XLOOKUP($D36,Data!$E:$E,Data!$F:$F,"Revisar",0)} -> AXIS | F36: {=_xlfn.XLOOKUP($D36,Data!$E:$E,Data!$G:$G,"Revisar",0)} -> Bono Amazon | G36: Spiff Axis GURO + ESS | H36: 705000 | I36: 133950 | J36: =IF($B36="","",H36+I36) -> 838950 | K36: 20092.5 | L36: =IF($B36="","",J36-K36) -> 818857.5 | M36: =IF($B36="","",SUMIFS('Extractos bancarios - Manglar'!$C:$C,'Extractos bancarios - Manglar'!$M:$M,$B36)) -> 808882.91 | N36: =IF($B36="","",L36-M36) -> 9974.59 | O36: 46316 | P36: =IF($B36="","",IF(N36<=0,0,MAX(0,TODAY()-O36))) -> 7 | Q36: =IF($B36="","",IF(N36<=0,"Al dia",IF(P36=0,"Vigente",IF(P36<=30,"1-30",IF(P36<=60,"31-60",IF(P36<=90,"61-90",">90")))))) -> 1-30 | R36: =IF($B36="","",IF(N36<=0,"Cobrada",IF(M36=0,"Pendiente","Parcial"))) -> Parcial | S36: ReteIVA 15% | T36: =IF($C36="","",MONTH($C36)) -> 9 | U36: =IF($B36="","",IF(ABS(K36-H36*0.04)<1000,0,IF(K36>=I36*0.15-1000,I36*0.15,0))) -> 20092.5 | V36: =IF($B36="","",K36-U36) -> 0
A37: =VLOOKUP(E37,$B$66:$B$80,1,0) -> Innovaitors | B37: DAFE 31 | C37: 46300 | D37: M260303 | E37: {=_xlfn.XLOOKUP($D37,Data!$E:$E,Data!$F:$F,"Revisar",0)} -> INNOVAITORS | F37: {=_xlfn.XLOOKUP($D37,Data!$E:$E,Data!$G:$G,"Revisar",0)} -> Kits Octubre | G37: Kits Octubre | H37: 1020000 | I37: 193800 | J37: =IF($B37="","",H37+I37) -> 1213800 | K37: 29070 | L37: =IF($B37="","",J37-K37) -> 1184730 | M37: =IF($B37="","",SUMIFS('Extractos bancarios - Manglar'!$C:$C,'Extractos bancarios - Manglar'!$M:$M,$B37)) -> 0 | N37: =IF($B37="","",L37-M37) -> 1184730 | O37: 46330 | P37: =IF($B37="","",IF(N37<=0,0,MAX(0,TODAY()-O37))) -> 0 | Q37: =IF($B37="","",IF(N37<=0,"Al dia",IF(P37=0,"Vigente",IF(P37<=30,"1-30",IF(P37<=60,"31-60",IF(P37<=90,"61-90",">90")))))) -> Vigente | R37: =IF($B37="","",IF(N37<=0,"Cobrada",IF(M37=0,"Pendiente","Parcial"))) -> Pendiente | S37: Innovaitors. ReteIVA 15% | T37: =IF($C37="","",MONTH($C37)) -> 10 | U37: =IF($B37="","",IF(ABS(K37-H37*0.04)<1000,0,IF(K37>=I37*0.15-1000,I37*0.15,0))) -> 29070 | V37: =IF($B37="","",K37-U37) -> 0
A38: =VLOOKUP(E38,$B$66:$B$80,1,0) -> AXIS | B38: DAFE 32 | C38: 46300 | D38: M260111 | E38: {=_xlfn.XLOOKUP($D38,Data!$E:$E,Data!$F:$F,"Revisar",0)} -> AXIS | F38: {=_xlfn.XLOOKUP($D38,Data!$E:$E,Data!$G:$G,"Revisar",0)} -> Bono amazon 100 USD ARG | G38: Amazon Gift Card - Interconnected Wesco Argentina | H38: 405838 | I38: 77109.22 | J38: =IF($B38="","",H38+I38) -> 482947.22 | K38: 11566.22 | L38: =IF($B38="","",J38-K38) -> 471381 | M38: =IF($B38="","",SUMIFS('Extractos bancarios - Manglar'!$C:$C,'Extractos bancarios - Manglar'!$M:$M,$B38)) -> 471381 | N38: =IF($B38="","",L38-M38) -> 0 | O38: 46330 | P38: =IF($B38="","",IF(N38<=0,0,MAX(0,TODAY()-O38))) -> 0 | Q38: =IF($B38="","",IF(N38<=0,"Al dia",IF(P38=0,"Vigente",IF(P38<=30,"1-30",IF(P38<=60,"31-60",IF(P38<=90,"61-90",">90")))))) -> Al dia | R38: =IF($B38="","",IF(N38<=0,"Cobrada",IF(M38=0,"Pendiente","Parcial"))) -> Cobrada | S38: AXIS. Sin ReteIVA. Centro nuevo, ver hoja 6 | T38: =IF($C38="","",MONTH($C38)) -> 10 | U38: =IF($B38="","",IF(ABS(K38-H38*0.04)<1000,0,IF(K38>=I38*0.15-1000,I38*0.15,0))) -> 11566.383 | V38: =IF($B38="","",K38-U38) -> -0.163
A39: =VLOOKUP(E39,$B$66:$B$80,1,0) -> MOTOROLA | B39: DAFE 34 | C39: 46301 | D39: M260802 | E39: {=_xlfn.XLOOKUP($D39,Data!$E:$E,Data!$F:$F,"Revisar",0)} -> MOTOROLA | F39: {=_xlfn.XLOOKUP($D39,Data!$E:$E,Data!$G:$G,"Revisar",0)} -> Entrepartners CALI | G39: Entrepartners Cali | H39: 7449400 | I39: 1415386 | J39: =IF($B39="","",H39+I39) -> 8864786 | K39: 212307.9 | L39: =IF($B39="","",J39-K39) -> 8652478.1 | M39: =IF($B39="","",SUMIFS('Extractos bancarios - Manglar'!$C:$C,'Extractos bancarios - Manglar'!$M:$M,$B39)) -> 0 | N39: =IF($B39="","",L39-M39) -> 8652478.1 | O39: 46331 | P39: =IF($B39="","",IF(N39<=0,0,MAX(0,TODAY()-O39))) -> 0 | Q39: =IF($B39="","",IF(N39<=0,"Al dia",IF(P39=0,"Vigente",IF(P39<=30,"1-30",IF(P39<=60,"31-60",IF(P39<=90,"61-90",">90")))))) -> Vigente | R39: =IF($B39="","",IF(N39<=0,"Cobrada",IF(M39=0,"Pendiente","Parcial"))) -> Pendiente | S39: MOTOROLA. ReteIVA 15% | T39: =IF($C39="","",MONTH($C39)) -> 10 | U39: =IF($B39="","",IF(ABS(K39-H39*0.04)<1000,0,IF(K39>=I39*0.15-1000,I39*0.15,0))) -> 212307.9 | V39: =IF($B39="","",K39-U39) -> 0
A40: =VLOOKUP(E40,$B$66:$B$80,1,0) -> MOTOROLA | B40: DAFE 35 | C40: 46301 | D40: M260803 | E40: {=_xlfn.XLOOKUP($D40,Data!$E:$E,Data!$F:$F,"Revisar",0)} -> MOTOROLA | F40: {=_xlfn.XLOOKUP($D40,Data!$E:$E,Data!$G:$G,"Revisar",0)} -> Entrepartners MEDELLIN | G40: Entrepartners Medellin | H40: 11815900 | I40: 2245021 | J40: =IF($B40="","",H40+I40) -> 14060921 | K40: 336753.15 | L40: =IF($B40="","",J40-K40) -> 13724168 | M40: =IF($B40="","",SUMIFS('Extractos bancarios - Manglar'!$C:$C,'Extractos bancarios - Manglar'!$M:$M,$B40)) -> 0 | N40: =IF($B40="","",L40-M40) -> 13724168 | O40: 46331 | P40: =IF($B40="","",IF(N40<=0,0,MAX(0,TODAY()-O40))) -> 0 | Q40: =IF($B40="","",IF(N40<=0,"Al dia",IF(P40=0,"Vigente",IF(P40<=30,"1-30",IF(P40<=60,"31-60",IF(P40<=90,"61-90",">90")))))) -> Vigente | R40: =IF($B40="","",IF(N40<=0,"Cobrada",IF(M40=0,"Pendiente","Parcial"))) -> Pendiente | S40: MOTOROLA. ReteIVA 15% | T40: =IF($C40="","",MONTH($C40)) -> 10 | U40: =IF($B40="","",IF(ABS(K40-H40*0.04)<1000,0,IF(K40>=I40*0.15-1000,I40*0.15,0))) -> 336753.15 | V40: =IF($B40="","",K40-U40) -> 5.8207661e-11
A41: =VLOOKUP(E41,$B$66:$B$80,1,0) -> MOTOROLA | B41: DAFE 36 | C41: 46301 | D41: M260801 | E41: {=_xlfn.XLOOKUP($D41,Data!$E:$E,Data!$F:$F,"Revisar",0)} -> MOTOROLA | F41: {=_xlfn.XLOOKUP($D41,Data!$E:$E,Data!$G:$G,"Revisar",0)} -> Entrepartners BOGOTA | G41: Entrepartners Bogota | H41: 15723750 | I41: 2987512.5 | J41: =IF($B41="","",H41+I41) -> 18711262 | K41: 448126.88 | L41: =IF($B41="","",J41-K41) -> 18263136 | M41: =IF($B41="","",SUMIFS('Extractos bancarios - Manglar'!$C:$C,'Extractos bancarios - Manglar'!$M:$M,$B41)) -> 17411595 | N41: =IF($B41="","",L41-M41) -> 851540.64 | O41: 46331 | P41: =IF($B41="","",IF(N41<=0,0,MAX(0,TODAY()-O41))) -> 0 | Q41: =IF($B41="","",IF(N41<=0,"Al dia",IF(P41=0,"Vigente",IF(P41<=30,"1-30",IF(P41<=60,"31-60",IF(P41<=90,"61-90",">90")))))) -> Vigente | R41: =IF($B41="","",IF(N41<=0,"Cobrada",IF(M41=0,"Pendiente","Parcial"))) -> Parcial | S41: MOTOROLA. Reemplaza a DAFE 33. ReteIVA 15% | T41: =IF($C41="","",MONTH($C41)) -> 10 | U41: =IF($B41="","",IF(ABS(K41-H41*0.04)<1000,0,IF(K41>=I41*0.15-1000,I41*0.15,0))) -> 448126.88 | V41: =IF($B41="","",K41-U41) -> 0.005
A42: =VLOOKUP(E42,$B$66:$B$80,1,0) -> #N/A | E42: {=_xlfn.XLOOKUP($D42,Data!$E:$E,Data!$F:$F,"Revisar",0)} -> 0 | F42: {=_xlfn.XLOOKUP($D42,Data!$E:$E,Data!$G:$G,"Revisar",0)} -> 0 | J42: =IF($B42="","",H42+I42) | L42: =IF($B42="","",J42-K42) | M42: =IF($B42="","",SUMIFS('Extractos bancarios - Manglar'!$C:$C,'Extractos bancarios - Manglar'!$M:$M,$B42)) | N42: =IF($B42="","",L42-M42) | P42: =IF($B42="","",IF(N42<=0,0,MAX(0,TODAY()-O42))) | Q42: =IF($B42="","",IF(N42<=0,"Al dia",IF(P42=0,"Vigente",IF(P42<=30,"1-30",IF(P42<=60,"31-60",IF(P42<=90,"61-90",">90")))))) | R42: =IF($B42="","",IF(N42<=0,"Cobrada",IF(M42=0,"Pendiente","Parcial"))) | T42: =IF($C42="","",MONTH($C42)) | U42: =IF($B42="","",IF(ABS(K42-H42*0.04)<1000,0,IF(K42>=I42*0.15-1000,I42*0.15,0))) | V42: =IF($B42="","",K42-U42)
A43: =VLOOKUP(E43,$B$66:$B$80,1,0) -> #N/A | E43: {=_xlfn.XLOOKUP($D43,Data!$E:$E,Data!$F:$F,"Revisar",0)} -> 0 | F43: {=_xlfn.XLOOKUP($D43,Data!$E:$E,Data!$G:$G,"Revisar",0)} -> 0 | J43: =IF($B43="","",H43+I43) | L43: =IF($B43="","",J43-K43) | M43: =IF($B43="","",SUMIFS('Extractos bancarios - Manglar'!$C:$C,'Extractos bancarios - Manglar'!$M:$M,$B43)) | N43: =IF($B43="","",L43-M43) | P43: =IF($B43="","",IF(N43<=0,0,MAX(0,TODAY()-O43))) | Q43: =IF($B43="","",IF(N43<=0,"Al dia",IF(P43=0,"Vigente",IF(P43<=30,"1-30",IF(P43<=60,"31-60",IF(P43<=90,"61-90",">90")))))) | R43: =IF($B43="","",IF(N43<=0,"Cobrada",IF(M43=0,"Pendiente","Parcial"))) | T43: =IF($C43="","",MONTH($C43)) | U43: =IF($B43="","",IF(ABS(K43-H43*0.04)<1000,0,IF(K43>=I43*0.15-1000,I43*0.15,0))) | V43: =IF($B43="","",K43-U43)
A44: =VLOOKUP(E44,$B$66:$B$80,1,0) -> #N/A | E44: {=_xlfn.XLOOKUP($D44,Data!$E:$E,Data!$F:$F,"Revisar",0)} -> 0 | F44: {=_xlfn.XLOOKUP($D44,Data!$E:$E,Data!$G:$G,"Revisar",0)} -> 0 | J44: =IF($B44="","",H44+I44) | L44: =IF($B44="","",J44-K44) | M44: =IF($B44="","",SUMIFS('Extractos bancarios - Manglar'!$C:$C,'Extractos bancarios - Manglar'!$M:$M,$B44)) | N44: =IF($B44="","",L44-M44) | P44: =IF($B44="","",IF(N44<=0,0,MAX(0,TODAY()-O44))) | Q44: =IF($B44="","",IF(N44<=0,"Al dia",IF(P44=0,"Vigente",IF(P44<=30,"1-30",IF(P44<=60,"31-60",IF(P44<=90,"61-90",">90")))))) | R44: =IF($B44="","",IF(N44<=0,"Cobrada",IF(M44=0,"Pendiente","Parcial"))) | T44: =IF($C44="","",MONTH($C44)) | U44: =IF($B44="","",IF(ABS(K44-H44*0.04)<1000,0,IF(K44>=I44*0.15-1000,I44*0.15,0))) | V44: =IF($B44="","",K44-U44)
A45: =VLOOKUP(E45,$B$66:$B$80,1,0) -> #N/A | E45: {=_xlfn.XLOOKUP($D45,Data!$E:$E,Data!$F:$F,"Revisar",0)} -> 0 | F45: {=_xlfn.XLOOKUP($D45,Data!$E:$E,Data!$G:$G,"Revisar",0)} -> 0 | J45: =IF($B45="","",H45+I45) | L45: =IF($B45="","",J45-K45) | M45: =IF($B45="","",SUMIFS('Extractos bancarios - Manglar'!$C:$C,'Extractos bancarios - Manglar'!$M:$M,$B45)) | N45: =IF($B45="","",L45-M45) | P45: =IF($B45="","",IF(N45<=0,0,MAX(0,TODAY()-O45))) | Q45: =IF($B45="","",IF(N45<=0,"Al dia",IF(P45=0,"Vigente",IF(P45<=30,"1-30",IF(P45<=60,"31-60",IF(P45<=90,"61-90",">90")))))) | R45: =IF($B45="","",IF(N45<=0,"Cobrada",IF(M45=0,"Pendiente","Parcial"))) | T45: =IF($C45="","",MONTH($C45)) | U45: =IF($B45="","",IF(ABS(K45-H45*0.04)<1000,0,IF(K45>=I45*0.15-1000,I45*0.15,0))) | V45: =IF($B45="","",K45-U45)
A46: =VLOOKUP(E46,$B$66:$B$80,1,0) -> #N/A | E46: {=_xlfn.XLOOKUP($D46,Data!$E:$E,Data!$F:$F,"Revisar",0)} -> 0 | F46: {=_xlfn.XLOOKUP($D46,Data!$E:$E,Data!$G:$G,"Revisar",0)} -> 0 | J46: =IF($B46="","",H46+I46) | L46: =IF($B46="","",J46-K46) | M46: =IF($B46="","",SUMIFS('Extractos bancarios - Manglar'!$C:$C,'Extractos bancarios - Manglar'!$M:$M,$B46)) | N46: =IF($B46="","",L46-M46) | P46: =IF($B46="","",IF(N46<=0,0,MAX(0,TODAY()-O46))) | Q46: =IF($B46="","",IF(N46<=0,"Al dia",IF(P46=0,"Vigente",IF(P46<=30,"1-30",IF(P46<=60,"31-60",IF(P46<=90,"61-90",">90")))))) | R46: =IF($B46="","",IF(N46<=0,"Cobrada",IF(M46=0,"Pendiente","Parcial"))) | T46: =IF($C46="","",MONTH($C46)) | U46: =IF($B46="","",IF(ABS(K46-H46*0.04)<1000,0,IF(K46>=I46*0.15-1000,I46*0.15,0))) | V46: =IF($B46="","",K46-U46)
A47: =VLOOKUP(E47,$B$66:$B$80,1,0) -> #N/A | E47: {=_xlfn.XLOOKUP($D47,Data!$E:$E,Data!$F:$F,"Revisar",0)} -> 0 | F47: {=_xlfn.XLOOKUP($D47,Data!$E:$E,Data!$G:$G,"Revisar",0)} -> 0 | J47: =IF($B47="","",H47+I47) | L47: =IF($B47="","",J47-K47) | M47: =IF($B47="","",SUMIFS('Extractos bancarios - Manglar'!$C:$C,'Extractos bancarios - Manglar'!$M:$M,$B47)) | N47: =IF($B47="","",L47-M47) | P47: =IF($B47="","",IF(N47<=0,0,MAX(0,TODAY()-O47))) | Q47: =IF($B47="","",IF(N47<=0,"Al dia",IF(P47=0,"Vigente",IF(P47<=30,"1-30",IF(P47<=60,"31-60",IF(P47<=90,"61-90",">90")))))) | R47: =IF($B47="","",IF(N47<=0,"Cobrada",IF(M47=0,"Pendiente","Parcial"))) | T47: =IF($C47="","",MONTH($C47)) | U47: =IF($B47="","",IF(ABS(K47-H47*0.04)<1000,0,IF(K47>=I47*0.15-1000,I47*0.15,0))) | V47: =IF($B47="","",K47-U47)
A48: =VLOOKUP(E48,$B$66:$B$80,1,0) -> #N/A | E48: {=_xlfn.XLOOKUP($D48,Data!$E:$E,Data!$F:$F,"Revisar",0)} -> 0 | F48: {=_xlfn.XLOOKUP($D48,Data!$E:$E,Data!$G:$G,"Revisar",0)} -> 0 | J48: =IF($B48="","",H48+I48) | L48: =IF($B48="","",J48-K48) | M48: =IF($B48="","",SUMIFS('Extractos bancarios - Manglar'!$C:$C,'Extractos bancarios - Manglar'!$M:$M,$B48)) | N48: =IF($B48="","",L48-M48) | P48: =IF($B48="","",IF(N48<=0,0,MAX(0,TODAY()-O48))) | Q48: =IF($B48="","",IF(N48<=0,"Al dia",IF(P48=0,"Vigente",IF(P48<=30,"1-30",IF(P48<=60,"31-60",IF(P48<=90,"61-90",">90")))))) | R48: =IF($B48="","",IF(N48<=0,"Cobrada",IF(M48=0,"Pendiente","Parcial"))) | T48: =IF($C48="","",MONTH($C48)) | U48: =IF($B48="","",IF(ABS(K48-H48*0.04)<1000,0,IF(K48>=I48*0.15-1000,I48*0.15,0))) | V48: =IF($B48="","",K48-U48)
A49: =VLOOKUP(E49,$B$66:$B$80,1,0) -> #N/A | E49: {=_xlfn.XLOOKUP($D49,Data!$E:$E,Data!$F:$F,"Revisar",0)} -> 0 | F49: {=_xlfn.XLOOKUP($D49,Data!$E:$E,Data!$G:$G,"Revisar",0)} -> 0 | J49: =IF($B49="","",H49+I49) | L49: =IF($B49="","",J49-K49) | M49: =IF($B49="","",SUMIFS('Extractos bancarios - Manglar'!$C:$C,'Extractos bancarios - Manglar'!$M:$M,$B49)) | N49: =IF($B49="","",L49-M49) | P49: =IF($B49="","",IF(N49<=0,0,MAX(0,TODAY()-O49))) | Q49: =IF($B49="","",IF(N49<=0,"Al dia",IF(P49=0,"Vigente",IF(P49<=30,"1-30",IF(P49<=60,"31-60",IF(P49<=90,"61-90",">90")))))) | R49: =IF($B49="","",IF(N49<=0,"Cobrada",IF(M49=0,"Pendiente","Parcial"))) | T49: =IF($C49="","",MONTH($C49)) | U49: =IF($B49="","",IF(ABS(K49-H49*0.04)<1000,0,IF(K49>=I49*0.15-1000,I49*0.15,0))) | V49: =IF($B49="","",K49-U49)
A50: =VLOOKUP(E50,$B$66:$B$80,1,0) -> #N/A | E50: {=_xlfn.XLOOKUP($D50,Data!$E:$E,Data!$F:$F,"Revisar",0)} -> 0 | F50: {=_xlfn.XLOOKUP($D50,Data!$E:$E,Data!$G:$G,"Revisar",0)} -> 0 | J50: =IF($B50="","",H50+I50) | L50: =IF($B50="","",J50-K50) | M50: =IF($B50="","",SUMIFS('Extractos bancarios - Manglar'!$C:$C,'Extractos bancarios - Manglar'!$M:$M,$B50)) | N50: =IF($B50="","",L50-M50) | P50: =IF($B50="","",IF(N50<=0,0,MAX(0,TODAY()-O50))) | Q50: =IF($B50="","",IF(N50<=0,"Al dia",IF(P50=0,"Vigente",IF(P50<=30,"1-30",IF(P50<=60,"31-60",IF(P50<=90,"61-90",">90")))))) | R50: =IF($B50="","",IF(N50<=0,"Cobrada",IF(M50=0,"Pendiente","Parcial"))) | T50: =IF($C50="","",MONTH($C50)) | U50: =IF($B50="","",IF(ABS(K50-H50*0.04)<1000,0,IF(K50>=I50*0.15-1000,I50*0.15,0))) | V50: =IF($B50="","",K50-U50)
A51: =VLOOKUP(E51,$B$66:$B$80,1,0) -> #N/A | E51: {=_xlfn.XLOOKUP($D51,Data!$E:$E,Data!$F:$F,"Revisar",0)} -> 0 | F51: {=_xlfn.XLOOKUP($D51,Data!$E:$E,Data!$G:$G,"Revisar",0)} -> 0 | J51: =IF($B51="","",H51+I51) | L51: =IF($B51="","",J51-K51) | M51: =IF($B51="","",SUMIFS('Extractos bancarios - Manglar'!$C:$C,'Extractos bancarios - Manglar'!$M:$M,$B51)) | N51: =IF($B51="","",L51-M51) | P51: =IF($B51="","",IF(N51<=0,0,MAX(0,TODAY()-O51))) | Q51: =IF($B51="","",IF(N51<=0,"Al dia",IF(P51=0,"Vigente",IF(P51<=30,"1-30",IF(P51<=60,"31-60",IF(P51<=90,"61-90",">90")))))) | R51: =IF($B51="","",IF(N51<=0,"Cobrada",IF(M51=0,"Pendiente","Parcial"))) | T51: =IF($C51="","",MONTH($C51)) | U51: =IF($B51="","",IF(ABS(K51-H51*0.04)<1000,0,IF(K51>=I51*0.15-1000,I51*0.15,0))) | V51: =IF($B51="","",K51-U51)
B52: TOTAL | H52: =SUM(H11:H51) -> 486681543 | I52: =SUM(I11:I51) -> 92469493 | J52: =SUM(J11:J51) -> 5.7915104e+08 | K52: =SUM(K11:K51) -> 13189919 | L52: =SUM(L11:L51) -> 5.6596112e+08 | M52: =SUM(M11:M51) -> 5.4156595e+08 | N52: =SUM(N11:N51) -> 24395166 | U52: =SUM(U11:U51) -> 7594007.8 | V52: =SUM(V11:V51) -> 5595910.8
B54: Notas credito
B55: Nota | C55: Fecha | E55: Cliente | F55: Concepto | G55: Base sin IVA | H55: IVA 19% | I55: Total | S55: Anula
B56: NC 2-1 | C56: 46140 | E56: Konrad Adenauer Stiftung | F56: Tacos, mugs y envio | G56: -8032857 | H56: -1526242.8 | I56: =IF($B56="","",G56+H56) -> -9559099.8 | S56: DAFE 2
B57: NC 2-2 | C57: 46206 | E57: AXIS | F57: Hoodies premio reto wellness | G57: -2744000 | H57: -521360 | I57: =IF($B57="","",G57+H57) -> -3265360 | S57: DAFE 11
B58: NC 2-3 | C58: 46206 | E58: AXIS | F58: Transporte y props cena Feria ESS | G58: -10875250 | H58: -2066297.5 | I58: =IF($B58="","",G58+H58) -> -12941548 | S58: DAFE 12
B59: NC 2-4 | C59: 46301 | E59: MOTOROLA | F59: Entrepartners Bogota - anula DAFE 33 | G59: -15723750 | H59: -2987512.5 | I59: =IF($B59="","",G59+H59) -> -18711262
I60: =IF($B60="","",G60+H60)
I61: =IF($B61="","",G61+H61)
B62: TOTAL | G62: =SUM(G56:G61) -> -37375857 | H62: =SUM(H56:H61) -> -7101412.8 | I62: =SUM(I56:I61) -> -44477270
B64: Cartera por cliente
B65: Cliente | C65: Total Facturado | E65: Retenciones | F65: Cobrado | G65: Cartera Pendiente | H65: % Cobrado
B66: ANIXTER | C66: =SUMIFS($J$11:$J$51,$E$11:$E$51,$B66) -> 61202603 | E66: =SUMIFS($K$11:$K$51,$E$11:$E$51,$B66) -> 1465776.6 | F66: =SUMIFS($M$11:$M$51,$E$11:$E$51,$B66) -> 59736827 | G66: =SUMIFS($N$11:$N$51,$E$11:$E$51,$B66) -> 0 | H66: =IFERROR(F66/C66,0) -> 0.97605042
B67: AXIS | C67: =SUMIFS($J$11:$J$51,$E$11:$E$51,$B67) -> 1.0799395e+08 | E67: =SUMIFS($K$11:$K$51,$E$11:$E$51,$B67) -> 2410308.3 | F67: =SUMIFS($M$11:$M$51,$E$11:$E$51,$B67) -> 105910788 | G67: =SUMIFS($N$11:$N$51,$E$11:$E$51,$B67) -> -327150.44 | H67: =IFERROR(F67/C67,0) -> 0.98071042
B68: Commscope | C68: =SUMIFS($J$11:$J$51,$E$11:$E$51,$B68) -> 8991140.2 | E68: =SUMIFS($K$11:$K$51,$E$11:$E$51,$B68) -> 215334.03 | F68: =SUMIFS($M$11:$M$51,$E$11:$E$51,$B68) -> 8775806.2 | G68: =SUMIFS($N$11:$N$51,$E$11:$E$51,$B68) -> 0 | H68: =IFERROR(F68/C68,0) -> 0.97605042
B69: Innovaitors | C69: =SUMIFS($J$11:$J$51,$E$11:$E$51,$B69) -> 3617600 | E69: =SUMIFS($K$11:$K$51,$E$11:$E$51,$B69) -> 55700 | F69: =SUMIFS($M$11:$M$51,$E$11:$E$51,$B69) -> 2067770 | G69: =SUMIFS($N$11:$N$51,$E$11:$E$51,$B69) -> 1494130 | H69: =IFERROR(F69/C69,0) -> 0.57158613
B70: Kaspersky | C70: =SUMIFS($J$11:$J$51,$E$11:$E$51,$B70) -> 1.0666304e+08 | E70: =SUMIFS($K$11:$K$51,$E$11:$E$51,$B70) -> 2554534.9 | F70: =SUMIFS($M$11:$M$51,$E$11:$E$51,$B70) -> 104108508 | G70: =SUMIFS($N$11:$N$51,$E$11:$E$51,$B70) -> -0.5 | H70: =IFERROR(F70/C70,0) -> 0.97605042
B71: Konrad Adenauer Stiftung | C71: =SUMIFS($J$11:$J$51,$E$11:$E$51,$B71) -> 19769181 | E71: =SUMIFS($K$11:$K$51,$E$11:$E$51,$B71) -> 0 | F71: =SUMIFS($M$11:$M$51,$E$11:$E$51,$B71) -> 19769181 | G71: =SUMIFS($N$11:$N$51,$E$11:$E$51,$B71) -> 0 | H71: =IFERROR(F71/C71,0) -> 1
B72: Psiconometrics | C72: =SUMIFS($J$11:$J$51,$E$11:$E$51,$B72) -> 2.2927655e+08 | E72: =SUMIFS($K$11:$K$51,$E$11:$E$51,$B72) -> 5491076.9 | F72: =SUMIFS($M$11:$M$51,$E$11:$E$51,$B72) -> 223785477 | G72: =SUMIFS($N$11:$N$51,$E$11:$E$51,$B72) -> 0 | H72: =IFERROR(F72/C72,0) -> 0.97605042
B73: MOTOROLA | C73: =SUMIFS($J$11:$J$51,$E$11:$E$51,$B73) -> 41636970 | E73: =SUMIFS($K$11:$K$51,$E$11:$E$51,$B73) -> 997187.93 | F73: =SUMIFS($M$11:$M$51,$E$11:$E$51,$B73) -> 17411595 | G73: =SUMIFS($N$11:$N$51,$E$11:$E$51,$B73) -> 23228187 | H73: =IFERROR(F73/C73,0) -> 0.41817633
C74: =SUMIFS($J$11:$J$51,$E$11:$E$51,$B74) -> 0 | E74: =SUMIFS($K$11:$K$51,$E$11:$E$51,$B74) -> 0 | F74: =SUMIFS($M$11:$M$51,$E$11:$E$51,$B74) -> 0 | G74: =SUMIFS($N$11:$N$51,$E$11:$E$51,$B74) -> 0 | H74: =IFERROR(F74/C74,0) -> 0
C75: =SUMIFS($J$11:$J$51,$E$11:$E$51,$B75) -> 0 | E75: =SUMIFS($K$11:$K$51,$E$11:$E$51,$B75) -> 0 | F75: =SUMIFS($M$11:$M$51,$E$11:$E$51,$B75) -> 0 | G75: =SUMIFS($N$11:$N$51,$E$11:$E$51,$B75) -> 0 | H75: =IFERROR(F75/C75,0) -> 0
C76: =SUMIFS($J$11:$J$51,$E$11:$E$51,$B76) -> 0 | E76: =SUMIFS($K$11:$K$51,$E$11:$E$51,$B76) -> 0 | F76: =SUMIFS($M$11:$M$51,$E$11:$E$51,$B76) -> 0 | G76: =SUMIFS($N$11:$N$51,$E$11:$E$51,$B76) -> 0 | H76: =IFERROR(F76/C76,0) -> 0
C77: =SUMIFS($J$11:$J$51,$E$11:$E$51,$B77) -> 0 | E77: =SUMIFS($K$11:$K$51,$E$11:$E$51,$B77) -> 0 | F77: =SUMIFS($M$11:$M$51,$E$11:$E$51,$B77) -> 0 | G77: =SUMIFS($N$11:$N$51,$E$11:$E$51,$B77) -> 0 | H77: =IFERROR(F77/C77,0) -> 0
C78: =SUMIFS($J$11:$J$51,$E$11:$E$51,$B78) -> 0 | E78: =SUMIFS($K$11:$K$51,$E$11:$E$51,$B78) -> 0 | F78: =SUMIFS($M$11:$M$51,$E$11:$E$51,$B78) -> 0 | G78: =SUMIFS($N$11:$N$51,$E$11:$E$51,$B78) -> 0 | H78: =IFERROR(F78/C78,0) -> 0
C79: =SUMIFS($J$11:$J$51,$E$11:$E$51,$B79) -> 0 | E79: =SUMIFS($K$11:$K$51,$E$11:$E$51,$B79) -> 0 | F79: =SUMIFS($M$11:$M$51,$E$11:$E$51,$B79) -> 0 | G79: =SUMIFS($N$11:$N$51,$E$11:$E$51,$B79) -> 0 | H79: =IFERROR(F79/C79,0) -> 0
B81: TOTAL | C81: =SUM(C66:C72) -> 5.3751407e+08 | E81: =SUM(E66:E80) -> 13189919 | F81: =SUM(F66:F80) -> 5.4156595e+08 | G81: =SUM(G66:G80) -> 24395166 | H81: =IFERROR(F81/C81,0) -> 1.0075382
B83: Controles
B84: Detalle contra resumen por cliente | G84: =N52-G81 -> 0
B85: Ingresos del extracto sin factura asignada | G85: =SUMIFS('Extractos bancarios - Manglar'!$C:$C,'Extractos bancarios - Manglar'!$G:$G,"Ingresos")-M52 -> 1730.59
B87: Pendientes
B88: Falta el documento DAFE 8.
B89: El pago de Innovaitors de julio no cuadra con las retenciones de DAFE 4 y DAFE 7.
B90: Las facturas nuevas van en las filas libres de arriba. La columna Mes alimenta el ingreso del P&G.

Sheet CxP
B1: CUENTAS POR PAGAR (CxP) — MANGLAR | H1: {=_xlfn.XLOOKUP($G1,Data!$E:$E,Data!$F:$F,"Revisar",0)} -> 0 | I1: {=_xlfn.XLOOKUP($G1,Data!$E:$E,Data!$G:$G,"Revisar",0)} -> 0
B2: Una fila por documento recibido. Las notas credito van en negativo. El Valor Producto ya incluye el INC, que no se recupera.
B3: Total facturado | E3: IVA descontable | I3: Pagado | L3: Por pagar
B4: =O164 -> 4.0935112e+08 | E4: =L164 -> 46606097 | I4: =P164 -> 3.9818549e+08 | L4: =Q164 -> 11092133
B5: Fecha Recepción | C5: Fecha Pago | D5: Estado | E5: Proveedor | F5: NIT/CC | G5: Centro de costo | H5: Cliente | I5: Proyecto | J5: Concepto/Rubro | K5: Valor Producto | L5: IVA | M5: Otros impuestos | N5: Retenciones | O5: Valor Total | P5: Pagado | Q5: Saldo | R5: Factura | S5: Vence | T5: Notas | U5: Días | V5: Alerta | W5: Dashboard | X5: Cuenta | Y5: Aplica al P&G
A6: =VLOOKUP(E6,$B$168:$B$255,1,0) -> LEXGRA CONSULTING S.A.S. | B6: 46083 | C6: 46104 | D6: =IF($R6="","",IF(ABS(Q6)<1,"Pagada",IF(Q6<0,IF(O6<0,"Nota credito","Saldo a favor"),IF(P6<>0,"Parcial","Pendiente")))) -> Pagada | E6: LEXGRA CONSULTING S.A.S. | F6: 901615566 | G6: NA | H6: {=_xlfn.XLOOKUP($G6,Data!$E:$E,Data!$F:$F,"Revisar",0)} -> NA | I6: {=_xlfn.XLOOKUP($G6,Data!$E:$E,Data!$G:$G,"Revisar",0)} -> NA | J6: SERVICIOS DE CONSULT SER001 94 | K6: 667854 | L6: 95000 | N6: 14250 | O6: =IF($R6="","",K6+L6+M6) -> 762854 | P6: =IF($R6="","",-SUMIFS('Extractos bancarios - Manglar'!$C:$C,'Extractos bancarios - Manglar'!$M:$M,$R6)) -> 748604 | Q6: =IF($R6="","",O6-N6-P6) -> 0 | R6: LXFE-420 | S6: 46098 | U6: =IF($R6="","",IF($S6="","",$S6-TODAY())) -> -225 | V6: =IF($R6="","",IF(ISNUMBER(SEARCH("Anula",$T6)),"Anulada",IF($Q6<=1000,"Al dia",IF($S6="","Sin fecha",IF($U6<0,"Vencida",IF($U6<=15,"Por vencer","Vigente")))))) -> Al dia | W6: =IF($R6="","",IF($V6="Anulada","No","Si")) -> Si | X6: =IF($R6="","",IF($H6="NA","Costos Operacionales",IF(OR($H6="",$H6="Revisar",$H6="Por asignar"),"Por clasificar","Costo Ventas"))) -> Costos Operacionales | Y6: =IF($R6="","","Si") -> Si
A7: =VLOOKUP(E7,$B$168:$B$255,1,0) -> STG CAFES SAS | B7: 46100 | C7: 46100 | D7: =IF($R7="","",IF(ABS(Q7)<1,"Pagada",IF(Q7<0,IF(O7<0,"Nota credito","Saldo a favor"),IF(P7<>0,"Parcial","Pendiente")))) -> Pagada | E7: STG CAFES SAS | F7: 901148230 | H7: Kaspersky | I7: Gastos Representacion | J7: SAND JOSECITO 94 2 GASEOSA 94 2 Cargo | K7: 96100 | L7: 0 | O7: =IF($R7="","",K7+L7+M7) -> 96100 | P7: =IF($R7="","",-SUMIFS('Extractos bancarios - Manglar'!$C:$C,'Extractos bancarios - Manglar'!$M:$M,$R7)) -> 96100 | Q7: =IF($R7="","",O7-N7-P7) -> 0 | R7: FEST-4442 | T7: Incluye INC | U7: =IF($R7="","",IF($S7="","",$S7-TODAY())) | V7: =IF($R7="","",IF(ISNUMBER(SEARCH("Anula",$T7)),"Anulada",IF($Q7<=1000,"Al dia",IF($S7="","Sin fecha",IF($U7<0,"Vencida",IF($U7<=15,"Por vencer","Vigente")))))) -> Al dia | W7: =IF($R7="","",IF($V7="Anulada","No","Si")) -> Si | X7: =IF($R7="","",IF($H7="NA","Costos Operacionales",IF(OR($H7="",$H7="Revisar",$H7="Por asignar"),"Por clasificar","Costo Ventas"))) -> Costo Ventas | Y7: =IF($R7="","","Si") -> Si
A8: =VLOOKUP(E8,$B$168:$B$255,1,0) -> SIIGO S.A.S | B8: 46118 | C8: 46118 | D8: =IF($R8="","",IF(ABS(Q8)<1,"Pagada",IF(Q8<0,IF(O8<0,"Nota credito","Saldo a favor"),IF(P8<>0,"Parcial","Pendiente")))) -> Pagada | E8: SIIGO S.A.S | F8: 830048145 | G8: NA | H8: {=_xlfn.XLOOKUP($G8,Data!$E:$E,Data!$F:$F,"Revisar",0)} -> NA | I8: {=_xlfn.XLOOKUP($G8,Data!$E:$E,Data!$G:$G,"Revisar",0)} -> NA | J8: Facturación electrónica 12 FE por WhatsApp USO CERTIFICADO D | K8: 222529 | L8: 0 | O8: =IF($R8="","",K8+L8+M8) -> 222529 | P8: =IF($R8="","",-SUMIFS('Extractos bancarios - Manglar'!$C:$C,'Extractos bancarios - Manglar'!$M:$M,$R8)) -> 222529 | Q8: =IF($R8="","",O8-N8-P8) -> 0 | R8: 93- | S8: 46118 | T8: Sin cruce uno a uno con el banco | U8: =IF($R8="","",IF($S8="","",$S8-TODAY())) -> -205 | V8: =IF($R8="","",IF(ISNUMBER(SEARCH("Anula",$T8)),"Anulada",IF($Q8<=1000,"Al dia",IF($S8="","Sin fecha",IF($U8<0,"Vencida",IF($U8<=15,"Por vencer","Vigente")))))) -> Al dia | W8: =IF($R8="","",IF($V8="Anulada","No","Si")) -> Si | X8: =IF($R8="","",IF($H8="NA","Costos Operacionales",IF(OR($H8="",$H8="Revisar",$H8="Por asignar"),"Por clasificar","Costo Ventas"))) -> Costos Operacionales | Y8: =IF($R8="","","Si") -> Si
A9: =VLOOKUP(E9,$B$168:$B$255,1,0) -> GRUPO EMPRESARIAL KOJAK GRAPHIC S.A.S | B9: 46122 | C9: 46121 | D9: =IF($R9="","",IF(ABS(Q9)<1,"Pagada",IF(Q9<0,IF(O9<0,"Nota credito","Saldo a favor"),IF(P9<>0,"Parcial","Pendiente")))) -> Pagada | E9: GRUPO EMPRESARIAL KOJAK GRAPHIC S.A.S | F9: 901805686 | G9: M260101 | H9: {=_xlfn.XLOOKUP($G9,Data!$E:$E,Data!$F:$F,"Revisar",0)} -> AXIS | I9: {=_xlfn.XLOOKUP($G9,Data!$E:$E,Data!$G:$G,"Revisar",0)} -> Evento mundial de fútbol y merchandising | J9: LLAVERO COPA DEL MUN DO PREMIUM - DOMICILIO DE ENVÍO - 94 | K9: 1027730.7 | L9: 195268.91 | O9: =IF($R9="","",K9+L9+M9) -> 1222999.6 | P9: =IF($R9="","",-SUMIFS('Extractos bancarios - Manglar'!$C:$C,'Extractos bancarios - Manglar'!$M:$M,$R9)) -> 1223000 | Q9: =IF($R9="","",O9-N9-P9) -> -0.36 | R9: 2604 | S9: 46122 | T9: Sin cruce uno a uno con el banco | U9: =IF($R9="","",IF($S9="","",$S9-TODAY())) -> -201 | V9: =IF($R9="","",IF(ISNUMBER(SEARCH("Anula",$T9)),"Anulada",IF($Q9<=1000,"Al dia",IF($S9="","Sin fecha",IF($U9<0,"Vencida",IF($U9<=15,"Por vencer","Vigente")))))) -> Al dia | W9: =IF($R9="","",IF($V9="Anulada","No","Si")) -> Si | X9: =IF($R9="","",IF($H9="NA","Costos Operacionales",IF(OR($H9="",$H9="Revisar",$H9="Por asignar"),"Por clasificar","Costo Ventas"))) -> Costo Ventas | Y9: =IF($R9="","","Si") -> Si
A10: =VLOOKUP(E10,$B$168:$B$255,1,0) -> ADIDAS COLOMBIA LTDA | B10: 46126 | C10: 46126 | D10: =IF($R10="","",IF(ABS(Q10)<1,"Pagada",IF(Q10<0,IF(O10<0,"Nota credito","Saldo a favor"),IF(P10<>0,"Parcial","Pendiente")))) -> Pagada | E10: ADIDAS COLOMBIA LTDA | F10: 805011074 | G10: M260101 | H10: {=_xlfn.XLOOKUP($G10,Data!$E:$E,Data!$F:$F,"Revisar",0)} -> AXIS | I10: {=_xlfn.XLOOKUP($G10,Data!$E:$E,Data!$G:$G,"Revisar",0)} -> Evento mundial de fútbol y merchandising | J10: JD8034 WC MINI NIU 10 JD8034 WC M | K10: 5175125.9 | L10: 983273.92 | O10: =IF($R10="","",K10+L10+M10) -> 6158399.8 | P10: =IF($R10="","",-SUMIFS('Extractos bancarios - Manglar'!$C:$C,'Extractos bancarios - Manglar'!$M:$M,$R10)) -> 6158400 | Q10: =IF($R10="","",O10-N10-P10) -> -0.16 | R10: 030A-47518 | T10: Sin cruce uno a uno con el banco | U10: =IF($R10="","",IF($S10="","",$S10-TODAY())) | V10: =IF($R10="","",IF(ISNUMBER(SEARCH("Anula",$T10)),"Anulada",IF($Q10<=1000,"Al dia",IF($S10="","Sin fecha",IF($U10<0,"Vencida",IF($U10<=15,"Por vencer","Vigente")))))) -> Al dia | W10: =IF($R10="","",IF($V10="Anulada","No","Si")) -> Si | X10: =IF($R10="","",IF($H10="NA","Costos Operacionales",IF(OR($H10="",$H10="Revisar",$H10="Por asignar"),"Por clasificar","Costo Ventas"))) -> Costo Ventas | Y10: =IF($R10="","","Si") -> Si
A11: =VLOOKUP(E11,$B$168:$B$255,1,0) -> CAJA DE COMPENSACION FAMILIAR COMPENSAR | B11: 46128 | C11: NA | D11: =IF($R11="","",IF(ABS(Q11)<1,"Pagada",IF(Q11<0,IF(O11<0,"Nota credito","Saldo a favor"),IF(P11<>0,"Parcial","Pendiente")))) -> Pagada | E11: CAJA DE COMPENSACION FAMILIAR COMPENSAR | F11: 860066942 | G11: NA | H11: {=_xlfn.XLOOKUP($G11,Data!$E:$E,Data!$F:$F,"Revisar",0)} -> NA | I11: {=_xlfn.XLOOKUP($G11,Data!$E:$E,Data!$G:$G,"Revisar",0)} -> NA | J11: Evento Educación Colombia Excelente | K11: 20799.99 | L11: 0 | O11: =IF($R11="","",K11+L11+M11) -> 20799.99 | P11: 20799.99 | Q11: =IF($R11="","",O11-N11-P11) -> 0 | R11: AM20-148849 | T11: Pagado con medios diferentes a los de Manglar | U11: =IF($R11="","",IF($S11="","",$S11-TODAY())) | V11: =IF($R11="","",IF(ISNUMBER(SEARCH("Anula",$T11)),"Anulada",IF($Q11<=1000,"Al dia",IF($S11="","Sin fecha",IF($U11<0,"Vencida",IF($U11<=15,"Por vencer","Vigente")))))) -> Al dia | W11: No | X11: =IF($R11="","",IF($H11="NA","Costos Operacionales",IF(OR($H11="",$H11="Revisar",$H11="Por asignar"),"Por clasificar","Costo Ventas"))) -> Costos Operacionales | Y11: No
A12: =VLOOKUP(E12,$B$168:$B$255,1,0) -> IKSO SAS | B12: 46132 | C12: 46132 | D12: =IF($R12="","",IF(ABS(Q12)<1,"Pagada",IF(Q12<0,IF(O12<0,"Nota credito","Saldo a favor"),IF(P12<>0,"Parcial","Pendiente")))) -> Pagada | E12: IKSO SAS | F12: 901331844 | G12: M260201 | H12: {=_xlfn.XLOOKUP($G12,Data!$E:$E,Data!$F:$F,"Revisar",0)} -> Konrad Adenauer Stiftung | I12: {=_xlfn.XLOOKUP($G12,Data!$E:$E,Data!$G:$G,"Revisar",0)} -> Material KAS - Tacos y pocillos | J12: FRAKTA BOLSA 55X37X35 NIU 1 CM/71 L AZUL N STELNA POCILL | K12: 240042.02 | L12: 45607.98 | O12: =IF($R12="","",K12+L12+M12) -> 285650 | P12: =IF($R12="","",-SUMIFS('Extractos bancarios - Manglar'!$C:$C,'Extractos bancarios - Manglar'!$M:$M,$R12)) -> 285650 | Q12: =IF($R12="","",O12-N12-P12) -> 0 | R12: F109-118706 | S12: 46132 | U12: =IF($R12="","",IF($S12="","",$S12-TODAY())) -> -191 | V12: =IF($R12="","",IF(ISNUMBER(SEARCH("Anula",$T12)),"Anulada",IF($Q12<=1000,"Al dia",IF($S12="","Sin fecha",IF($U12<0,"Vencida",IF($U12<=15,"Por vencer","Vigente")))))) -> Al dia | W12: =IF($R12="","",IF($V12="Anulada","No","Si")) -> Si | X12: =IF($R12="","",IF($H12="NA","Costos Operacionales",IF(OR($H12="",$H12="Revisar",$H12="Por asignar"),"Por clasificar","Costo Ventas"))) -> Costo Ventas | Y12: =IF($R12="","","Si") -> Si
A13: =VLOOKUP(E13,$B$168:$B$255,1,0) -> Linemarketing & Eventos | B13: 46133 | C13: 46163 | D13: =IF($R13="","",IF(ABS(Q13)<1,"Pagada",IF(Q13<0,IF(O13<0,"Nota credito","Saldo a favor"),IF(P13<>0,"Parcial","Pendiente")))) -> Pagada | E13: Linemarketing & Eventos | F13: 900299878 | G13: M260101 | H13: {=_xlfn.XLOOKUP($G13,Data!$E:$E,Data!$F:$F,"Revisar",0)} -> AXIS | I13: {=_xlfn.XLOOKUP($G13,Data!$E:$E,Data!$G:$G,"Revisar",0)} -> Evento mundial de fútbol y merchandising | J13: VA-114 Sporty Bag Sencilla 94 100 Botilito Me | K13: 3940000 | L13: 748600 | O13: =IF($R13="","",K13+L13+M13) -> 4688600 | P13: =IF($R13="","",-SUMIFS('Extractos bancarios - Manglar'!$C:$C,'Extractos bancarios - Manglar'!$M:$M,$R13)) -> 4688600 | Q13: =IF($R13="","",O13-N13-P13) -> 0 | R13: FE-538 | S13: 46133 | U13: =IF($R13="","",IF($S13="","",$S13-TODAY())) -> -190 | V13: =IF($R13="","",IF(ISNUMBER(SEARCH("Anula",$T13)),"Anulada",IF($Q13<=1000,"Al dia",IF($S13="","Sin fecha",IF($U13<0,"Vencida",IF($U13<=15,"Por vencer","Vigente")))))) -> Al dia | W13: =IF($R13="","",IF($V13="Anulada","No","Si")) -> Si | X13: =IF($R13="","",IF($H13="NA","Costos Operacionales",IF(OR($H13="",$H13="Revisar",$H13="Por asignar"),"Por clasificar","Costo Ventas"))) -> Costo Ventas | Y13: =IF($R13="","","Si") -> Si
A14: =VLOOKUP(E14,$B$168:$B$255,1,0) -> SMART DESIGN PUBLICIDAD SAS | B14: 46135 | C14: 46139 | D14: =IF($R14="","",IF(ABS(Q14)<1,"Pagada",IF(Q14<0,IF(O14<0,"Nota credito","Saldo a favor"),IF(P14<>0,"Parcial","Pendiente")))) -> Pagada | E14: SMART DESIGN PUBLICIDAD SAS | F14: 901764188 | G14: M260301 | H14: {=_xlfn.XLOOKUP($G14,Data!$E:$E,Data!$F:$F,"Revisar",0)} -> Innovaitors | I14: {=_xlfn.XLOOKUP($G14,Data!$E:$E,Data!$G:$G,"Revisar",0)} -> Kits Innovaitors | J14: Set de libreta cubierta de ZZ 35 Caja de regalo i | K14: 1225000 | L14: 232750 | O14: =IF($R14="","",K14+L14+M14) -> 1457750 | P14: =IF($R14="","",-SUMIFS('Extractos bancarios - Manglar'!$C:$C,'Extractos bancarios - Manglar'!$M:$M,$R14)) -> 1457750 | Q14: =IF($R14="","",O14-N14-P14) -> 0 | R14: SD-404 | S14: 46135 | U14: =IF($R14="","",IF($S14="","",$S14-TODAY())) -> -188 | V14: =IF($R14="","",IF(ISNUMBER(SEARCH("Anula",$T14)),"Anulada",IF($Q14<=1000,"Al dia",IF($S14="","Sin fecha",IF($U14<0,"Vencida",IF($U14<=15,"Por vencer","Vigente")))))) -> Al dia | W14: =IF($R14="","",IF($V14="Anulada","No","Si")) -> Si | X14: =IF($R14="","",IF($H14="NA","Costos Operacionales",IF(OR($H14="",$H14="Revisar",$H14="Por asignar"),"Por clasificar","Costo Ventas"))) -> Costo Ventas | Y14: =IF($R14="","","Si") -> Si
A15: =VLOOKUP(E15,$B$168:$B$255,1,0) -> ALVARO ORTIZ GUERRERO | B15: 46136 | C15: 46136 | D15: =IF($R15="","",IF(ABS(Q15)<1,"Pagada",IF(Q15<0,IF(O15<0,"Nota credito","Saldo a favor"),IF(P15<>0,"Parcial","Pendiente")))) -> Pagada | E15: ALVARO ORTIZ GUERRERO | F15: 79333384 | G15: M260201 | H15: {=_xlfn.XLOOKUP($G15,Data!$E:$E,Data!$F:$F,"Revisar",0)} -> Konrad Adenauer Stiftung | I15: {=_xlfn.XLOOKUP($G15,Data!$E:$E,Data!$G:$G,"Revisar",0)} -> Material KAS - Tacos y pocillos | J15: SERVICIO MAR SERVICIO DE MARCA 94 20 Notas Finales | K15: 200000 | L15: 38000 | O15: =IF($R15="","",K15+L15+M15) -> 238000 | P15: =IF($R15="","",-SUMIFS('Extractos bancarios - Manglar'!$C:$C,'Extractos bancarios - Manglar'!$M:$M,$R15)) -> 238000 | Q15: =IF($R15="","",O15-N15-P15) -> 0 | R15: AOG-810 | S15: 46136 | T15: Sin cruce uno a uno con el banco | U15: =IF($R15="","",IF($S15="","",$S15-TODAY())) -> -187 | V15: =IF($R15="","",IF(ISNUMBER(SEARCH("Anula",$T15)),"Anulada",IF($Q15<=1000,"Al dia",IF($S15="","Sin fecha",IF($U15<0,"Vencida",IF($U15<=15,"Por vencer","Vigente")))))) -> Al dia | W15: =IF($R15="","",IF($V15="Anulada","No","Si")) -> Si | X15: =IF($R15="","",IF($H15="NA","Costos Operacionales",IF(OR($H15="",$H15="Revisar",$H15="Por asignar"),"Por clasificar","Costo Ventas"))) -> Costo Ventas | Y15: =IF($R15="","","Si") -> Si
A16: =VLOOKUP(E16,$B$168:$B$255,1,0) -> COLOMBIANA DE COMERCIO S.A. | B16: 46146 | C16: 46146 | D16: =IF($R16="","",IF(ABS(Q16)<1,"Pagada",IF(Q16<0,IF(O16<0,"Nota credito","Saldo a favor"),IF(P16<>0,"Parcial","Pendiente")))) -> Pagada | E16: COLOMBIANA DE COMERCIO S.A. | F16: 890900943 | G16: M260101 | H16: {=_xlfn.XLOOKUP($G16,Data!$E:$E,Data!$F:$F,"Revisar",0)} -> AXIS | I16: {=_xlfn.XLOOKUP($G16,Data!$E:$E,Data!$G:$G,"Revisar",0)} -> Evento mundial de fútbol y merchandising | J16: Album Pblanda Copa Mund Album Pblanda Copa Mund Album Pbland | K16: 1252101 | L16: 237899 | O16: =IF($R16="","",K16+L16+M16) -> 1490000 | P16: =IF($R16="","",-SUMIFS('Extractos bancarios - Manglar'!$C:$C,'Extractos bancarios - Manglar'!$M:$M,$R16)) -> 1490000 | Q16: =IF($R16="","",O16-N16-P16) -> 0 | R16: X711-2506067 | U16: =IF($R16="","",IF($S16="","",$S16-TODAY())) | V16: =IF($R16="","",IF(ISNUMBER(SEARCH("Anula",$T16)),"Anulada",IF($Q16<=1000,"Al dia",IF($S16="","Sin fecha",IF($U16<0,"Vencida",IF($U16<=15,"Por vencer","Vigente")))))) -> Al dia | W16: =IF($R16="","",IF($V16="Anulada","No","Si")) -> Si | X16: =IF($R16="","",IF($H16="NA","Costos Operacionales",IF(OR($H16="",$H16="Revisar",$H16="Por asignar"),"Por clasificar","Costo Ventas"))) -> Costo Ventas | Y16: =IF($R16="","","Si") -> Si
A17: =VLOOKUP(E17,$B$168:$B$255,1,0) -> COLOMBIANA DE COMERCIO S.A. | B17: 46146 | C17: 46146 | D17: =IF($R17="","",IF(ABS(Q17)<1,"Pagada",IF(Q17<0,IF(O17<0,"Nota credito","Saldo a favor"),IF(P17<>0,"Parcial","Pendiente")))) -> Pagada | E17: COLOMBIANA DE COMERCIO S.A. | F17: 890900943 | G17: M260101 | H17: {=_xlfn.XLOOKUP($G17,Data!$E:$E,Data!$F:$F,"Revisar",0)} -> AXIS | I17: {=_xlfn.XLOOKUP($G17,Data!$E:$E,Data!$G:$G,"Revisar",0)} -> Evento mundial de fútbol y merchandising | J17: Display Sob Copa Mu Notas Finales Responsable I.V.A. Somos G | K17: 2621848.7 | L17: 498151.26 | O17: =IF($R17="","",K17+L17+M17) -> 3120000 | P17: =IF($R17="","",-SUMIFS('Extractos bancarios - Manglar'!$C:$C,'Extractos bancarios - Manglar'!$M:$M,$R17)) -> 3120000 | Q17: =IF($R17="","",O17-N17-P17) -> 0 | R17: X711-2506066 | U17: =IF($R17="","",IF($S17="","",$S17-TODAY())) | V17: =IF($R17="","",IF(ISNUMBER(SEARCH("Anula",$T17)),"Anulada",IF($Q17<=1000,"Al dia",IF($S17="","Sin fecha",IF($U17<0,"Vencida",IF($U17<=15,"Por vencer","Vigente")))))) -> Al dia | W17: =IF($R17="","",IF($V17="Anulada","No","Si")) -> Si | X17: =IF($R17="","",IF($H17="NA","Costos Operacionales",IF(OR($H17="",$H17="Revisar",$H17="Por asignar"),"Por clasificar","Costo Ventas"))) -> Costo Ventas | Y17: =IF($R17="","","Si") -> Si
A18: =VLOOKUP(E18,$B$168:$B$255,1,0) -> ADIDAS COLOMBIA LTDA | B18: 46154 | C18: NA | D18: =IF($R18="","",IF(ABS(Q18)<1,"Pagada",IF(Q18<0,IF(O18<0,"Nota credito","Saldo a favor"),IF(P18<>0,"Parcial","Pendiente")))) -> Nota credito | E18: ADIDAS COLOMBIA LTDA | F18: 805011074 | G18: NA | H18: {=_xlfn.XLOOKUP($G18,Data!$E:$E,Data!$F:$F,"Revisar",0)} -> NA | I18: {=_xlfn.XLOOKUP($G18,Data!$E:$E,Data!$G:$G,"Revisar",0)} -> NA | J18: JZ0736 FMF A JSY D NIU 1 | K18: -319285.71 | L18: -60664.28 | O18: =IF($R18="","",K18+L18+M18) -> -379949.99 | P18: =IF($R18="","",-SUMIFS('Extractos bancarios - Manglar'!$C:$C,'Extractos bancarios - Manglar'!$M:$M,$R18)) -> 0 | Q18: =IF($R18="","",O18-N18-P18) -> -379949.99 | R18: NC055A6689 | T18: Anula 055A-47328 | U18: =IF($R18="","",IF($S18="","",$S18-TODAY())) | V18: =IF($R18="","",IF(ISNUMBER(SEARCH("Anula",$T18)),"Anulada",IF($Q18<=1000,"Al dia",IF($S18="","Sin fecha",IF($U18<0,"Vencida",IF($U18<=15,"Por vencer","Vigente")))))) -> Anulada | W18: =IF($R18="","",IF($V18="Anulada","No","Si")) -> No | X18: =IF($R18="","",IF($H18="NA","Costos Operacionales",IF(OR($H18="",$H18="Revisar",$H18="Por asignar"),"Por clasificar","Costo Ventas"))) -> Costos Operacionales | Y18: No
A19: =VLOOKUP(E19,$B$168:$B$255,1,0) -> ADIDAS COLOMBIA LTDA | B19: 46154 | C19: NA | D19: =IF($R19="","",IF(ABS(Q19)<1,"Pagada",IF(Q19<0,IF(O19<0,"Nota credito","Saldo a favor"),IF(P19<>0,"Parcial","Pendiente")))) -> Pendiente | E19: ADIDAS COLOMBIA LTDA | F19: 805011074 | G19: NA | H19: {=_xlfn.XLOOKUP($G19,Data!$E:$E,Data!$F:$F,"Revisar",0)} -> NA | I19: {=_xlfn.XLOOKUP($G19,Data!$E:$E,Data!$G:$G,"Revisar",0)} -> NA | J19: JZ0736 FMF A JSY D NIU 1 | K19: 319285.71 | L19: 60664.28 | O19: =IF($R19="","",K19+L19+M19) -> 379949.99 | P19: =IF($R19="","",-SUMIFS('Extractos bancarios - Manglar'!$C:$C,'Extractos bancarios - Manglar'!$M:$M,$R19)) -> 0 | Q19: =IF($R19="","",O19-N19-P19) -> 379949.99 | R19: 055A-47328 | T19: Anulada por NC055A6689 | U19: =IF($R19="","",IF($S19="","",$S19-TODAY())) | V19: =IF($R19="","",IF(ISNUMBER(SEARCH("Anula",$T19)),"Anulada",IF($Q19<=1000,"Al dia",IF($S19="","Sin fecha",IF($U19<0,"Vencida",IF($U19<=15,"Por vencer","Vigente")))))) -> Anulada | W19: =IF($R19="","",IF($V19="Anulada","No","Si")) -> No | X19: =IF($R19="","",IF($H19="NA","Costos Operacionales",IF(OR($H19="",$H19="Revisar",$H19="Por asignar"),"Por clasificar","Costo Ventas"))) -> Costos Operacionales | Y19: No
A20: =VLOOKUP(E20,$B$168:$B$255,1,0) -> ADIDAS COLOMBIA LTDA | B20: 46154 | C20: NA | D20: =IF($R20="","",IF(ABS(Q20)<1,"Pagada",IF(Q20<0,IF(O20<0,"Nota credito","Saldo a favor"),IF(P20<>0,"Parcial","Pendiente")))) -> Nota credito | E20: ADIDAS COLOMBIA LTDA | F20: 805011074 | G20: NA | H20: {=_xlfn.XLOOKUP($G20,Data!$E:$E,Data!$F:$F,"Revisar",0)} -> NA | I20: {=_xlfn.XLOOKUP($G20,Data!$E:$E,Data!$G:$G,"Revisar",0)} -> NA | J20: JL6972 FCF H JSY NIU 1 | K20: -319285.71 | L20: -60664.28 | O20: =IF($R20="","",K20+L20+M20) -> -379949.99 | P20: =IF($R20="","",-SUMIFS('Extractos bancarios - Manglar'!$C:$C,'Extractos bancarios - Manglar'!$M:$M,$R20)) -> 0 | Q20: =IF($R20="","",O20-N20-P20) -> -379949.99 | R20: NC055A6687 | T20: Anula 055A-47337 | U20: =IF($R20="","",IF($S20="","",$S20-TODAY())) | V20: =IF($R20="","",IF(ISNUMBER(SEARCH("Anula",$T20)),"Anulada",IF($Q20<=1000,"Al dia",IF($S20="","Sin fecha",IF($U20<0,"Vencida",IF($U20<=15,"Por vencer","Vigente")))))) -> Anulada | W20: =IF($R20="","",IF($V20="Anulada","No","Si")) -> No | X20: =IF($R20="","",IF($H20="NA","Costos Operacionales",IF(OR($H20="",$H20="Revisar",$H20="Por asignar"),"Por clasificar","Costo Ventas"))) -> Costos Operacionales | Y20: No
A21: =VLOOKUP(E21,$B$168:$B$255,1,0) -> ADIDAS COLOMBIA LTDA | B21: 46154 | C21: NA | D21: =IF($R21="","",IF(ABS(Q21)<1,"Pagada",IF(Q21<0,IF(O21<0,"Nota credito","Saldo a favor"),IF(P21<>0,"Parcial","Pendiente")))) -> Pendiente | E21: ADIDAS COLOMBIA LTDA | F21: 805011074 | G21: NA | H21: {=_xlfn.XLOOKUP($G21,Data!$E:$E,Data!$F:$F,"Revisar",0)} -> NA | I21: {=_xlfn.XLOOKUP($G21,Data!$E:$E,Data!$G:$G,"Revisar",0)} -> NA | J21: JZ0736 FMF A JSY D NIU 1 | K21: 319285.71 | L21: 60664.28 | O21: =IF($R21="","",K21+L21+M21) -> 379949.99 | P21: =IF($R21="","",-SUMIFS('Extractos bancarios - Manglar'!$C:$C,'Extractos bancarios - Manglar'!$M:$M,$R21)) -> 0 | Q21: =IF($R21="","",O21-N21-P21) -> 379949.99 | R21: 055A-47337 | T21: Anulada por NC055A6687 | U21: =IF($R21="","",IF($S21="","",$S21-TODAY())) | V21: =IF($R21="","",IF(ISNUMBER(SEARCH("Anula",$T21)),"Anulada",IF($Q21<=1000,"Al dia",IF($S21="","Sin fecha",IF($U21<0,"Vencida",IF($U21<=15,"Por vencer","Vigente")))))) -> Anulada | W21: =IF($R21="","",IF($V21="Anulada","No","Si")) -> No | X21: =IF($R21="","",IF($H21="NA","Costos Operacionales",IF(OR($H21="",$H21="Revisar",$H21="Por asignar"),"Por clasificar","Costo Ventas"))) -> Costos Operacionales | Y21: No
A22: =VLOOKUP(E22,$B$168:$B$255,1,0) -> TRANSPARENTE AGENCIA GRAFICA S.A.S | B22: 46162 | C22: 46167 | D22: =IF($R22="","",IF(ABS(Q22)<1,"Pagada",IF(Q22<0,IF(O22<0,"Nota credito","Saldo a favor"),IF(P22<>0,"Parcial","Pendiente")))) -> Pagada | E22: TRANSPARENTE AGENCIA GRAFICA S.A.S | F22: 901909925 | G22: M260201 | H22: {=_xlfn.XLOOKUP($G22,Data!$E:$E,Data!$F:$F,"Revisar",0)} -> Konrad Adenauer Stiftung | I22: {=_xlfn.XLOOKUP($G22,Data!$E:$E,Data!$G:$G,"Revisar",0)} -> Material KAS - Tacos y pocillos | J22: TACO EN HOJAS BOND 7 GR IMPRESO FULL COL PORTA T OR 1 CARA T | K22: =4830000/1.19 -> 4058823.5 | L22: =K22*0.19 -> 771176.47 | O22: =IF($R22="","",K22+L22+M22) -> 4830000 | P22: =+O22 -> 4830000 | Q22: =IF($R22="","",O22-N22-P22) -> 0 | R22: FE-285 | S22: 46162 | T22: Factura dividida para alinear costos por proyecto. Valor ajustado manual en pagado | U22: =IF($R22="","",IF($S22="","",$S22-TODAY())) -> -161 | V22: =IF($R22="","",IF(ISNUMBER(SEARCH("Anula",$T22)),"Anulada",IF($Q22<=1000,"Al dia",IF($S22="","Sin fecha",IF($U22<0,"Vencida",IF($U22<=15,"Por vencer","Vigente")))))) -> Al dia | W22: =IF($R22="","",IF($V22="Anulada","No","Si")) -> Si | X22: =IF($R22="","",IF($H22="NA","Costos Operacionales",IF(OR($H22="",$H22="Revisar",$H22="Por asignar"),"Por clasificar","Costo Ventas"))) -> Costo Ventas | Y22: =IF($R22="","","Si") -> Si
A23: =VLOOKUP(E23,$B$168:$B$255,1,0) -> TRANSPARENTE AGENCIA GRAFICA S.A.S | B23: 46162 | C23: 46167 | D23: =IF($R23="","",IF(ABS(Q23)<1,"Pagada",IF(Q23<0,IF(O23<0,"Nota credito","Saldo a favor"),IF(P23<>0,"Parcial","Pendiente")))) -> Pagada | E23: TRANSPARENTE AGENCIA GRAFICA S.A.S | F23: 901909925 | G23: M260302 | H23: {=_xlfn.XLOOKUP($G23,Data!$E:$E,Data!$F:$F,"Revisar",0)} -> Innovaitors | I23: {=_xlfn.XLOOKUP($G23,Data!$E:$E,Data!$G:$G,"Revisar",0)} -> Banners Rollup | J23: TACO EN HOJAS BOND 7 GR IMPRESO FULL COL PORTA T OR 1 CARA T | K23: =214200/1.19 -> 180000 | L23: =K23*0.19 -> 34200 | O23: =IF($R23="","",K23+L23+M23) -> 214200 | P23: =+O23 -> 214200 | Q23: =IF($R23="","",O23-N23-P23) -> 0 | R23: FE-285 | S23: 46162 | T23: Factura dividida para alinear costos por proyecto. Valor ajustado manual en pagado | U23: =IF($R23="","",IF($S23="","",$S23-TODAY())) -> -161 | V23: =IF($R23="","",IF(ISNUMBER(SEARCH("Anula",$T23)),"Anulada",IF($Q23<=1000,"Al dia",IF($S23="","Sin fecha",IF($U23<0,"Vencida",IF($U23<=15,"Por vencer","Vigente")))))) -> Al dia | W23: =IF($R23="","",IF($V23="Anulada","No","Si")) -> Si | X23: =IF($R23="","",IF($H23="NA","Costos Operacionales",IF(OR($H23="",$H23="Revisar",$H23="Por asignar"),"Por clasificar","Costo Ventas"))) -> Costo Ventas | Y23: =IF($R23="","","Si") -> Si
A24: =VLOOKUP(E24,$B$168:$B$255,1,0) -> TRANSPARENTE AGENCIA GRAFICA S.A.S | B24: 46162 | C24: 46167 | D24: =IF($R24="","",IF(ABS(Q24)<1,"Pagada",IF(Q24<0,IF(O24<0,"Nota credito","Saldo a favor"),IF(P24<>0,"Parcial","Pendiente")))) -> Pagada | E24: TRANSPARENTE AGENCIA GRAFICA S.A.S | F24: 901909925 | G24: M260401 | H24: {=_xlfn.XLOOKUP($G24,Data!$E:$E,Data!$F:$F,"Revisar",0)} -> Kaspersky | I24: {=_xlfn.XLOOKUP($G24,Data!$E:$E,Data!$G:$G,"Revisar",0)} -> Bolsa Incentivos 2026 | J24: TACO EN HOJAS BOND 7 GR IMPRESO FULL COL PORTA T OR 1 CARA T | K24: =1071000/1.19 -> 900000 | L24: =K24*0.19 -> 171000 | O24: =IF($R24="","",K24+L24+M24) -> 1071000 | P24: =+O24 -> 1071000 | Q24: =IF($R24="","",O24-N24-P24) -> 0 | R24: FE-285 | S24: 46162 | T24: Factura dividida para alinear costos por proyecto. Valor ajustado manual en pagado | U24: =IF($R24="","",IF($S24="","",$S24-TODAY())) -> -161 | V24: =IF($R24="","",IF(ISNUMBER(SEARCH("Anula",$T24)),"Anulada",IF($Q24<=1000,"Al dia",IF($S24="","Sin fecha",IF($U24<0,"Vencida",IF($U24<=15,"Por vencer","Vigente")))))) -> Al dia | W24: =IF($R24="","",IF($V24="Anulada","No","Si")) -> Si | X24: =IF($R24="","",IF($H24="NA","Costos Operacionales",IF(OR($H24="",$H24="Revisar",$H24="Por asignar"),"Por clasificar","Costo Ventas"))) -> Costo Ventas | Y24: =IF($R24="","","Si") -> Si
A25: =VLOOKUP(E25,$B$168:$B$255,1,0) -> DISTRIBUIDORA DE COMBUSTIBLES SAN FELIPE | B25: 46162 | C25: 46162 | D25: =IF($R25="","",IF(ABS(Q25)<1,"Pagada",IF(Q25<0,IF(O25<0,"Nota credito","Saldo a favor"),IF(P25<>0,"Parcial","Pendiente")))) -> Pagada | E25: DISTRIBUIDORA DE COMBUSTIBLES SAN FELIPE | F25: 901626025 | G25: NA | H25: {=_xlfn.XLOOKUP($G25,Data!$E:$E,Data!$F:$F,"Revisar",0)} -> NA | I25: {=_xlfn.XLOOKUP($G25,Data!$E:$E,Data!$G:$G,"Revisar",0)} -> NA | J25: CORRIENTE EA 14 Notas Finales | K25: 237214 | L25: 0 | O25: =IF($R25="","",K25+L25+M25) -> 237214 | P25: =IF($R25="","",-SUMIFS('Extractos bancarios - Manglar'!$C:$C,'Extractos bancarios - Manglar'!$M:$M,$R25)) -> 237214 | Q25: =IF($R25="","",O25-N25-P25) -> 0 | R25: TSFB-145699 | S25: 46162 | U25: =IF($R25="","",IF($S25="","",$S25-TODAY())) -> -161 | V25: =IF($R25="","",IF(ISNUMBER(SEARCH("Anula",$T25)),"Anulada",IF($Q25<=1000,"Al dia",IF($S25="","Sin fecha",IF($U25<0,"Vencida",IF($U25<=15,"Por vencer","Vigente")))))) -> Al dia | W25: =IF($R25="","",IF($V25="Anulada","No","Si")) -> Si | X25: =IF($R25="","",IF($H25="NA","Costos Operacionales",IF(OR($H25="",$H25="Revisar",$H25="Por asignar"),"Por clasificar","Costo Ventas"))) -> Costos Operacionales | Y25: =IF($R25="","","Si") -> Si
A26: =VLOOKUP(E26,$B$168:$B$255,1,0) -> MEDIA RES STEAKHOUSE S.A.S. | B26: 46167 | C26: NA | D26: =IF($R26="","",IF(ABS(Q26)<1,"Pagada",IF(Q26<0,IF(O26<0,"Nota credito","Saldo a favor"),IF(P26<>0,"Parcial","Pendiente")))) -> Pagada | E26: MEDIA RES STEAKHOUSE S.A.S. | F26: 901161636 | G26: NA | H26: {=_xlfn.XLOOKUP($G26,Data!$E:$E,Data!$F:$F,"Revisar",0)} -> NA | I26: {=_xlfn.XLOOKUP($G26,Data!$E:$E,Data!$G:$G,"Revisar",0)} -> NA | J26: ASADO DE VACIO WSD 1 COCA COLA ZERO WSD 1 COCA | K26: 328998.24 | L26: 0 | O26: =IF($R26="","",K26+L26+M26) -> 328998.24 | P26: 328998.24 | Q26: =IF($R26="","",O26-N26-P26) -> 0 | R26: MRFE-55498 | T26: Pagado con medios diferentes a los de Manglar | U26: =IF($R26="","",IF($S26="","",$S26-TODAY())) | V26: =IF($R26="","",IF(ISNUMBER(SEARCH("Anula",$T26)),"Anulada",IF($Q26<=1000,"Al dia",IF($S26="","Sin fecha",IF($U26<0,"Vencida",IF($U26<=15,"Por vencer","Vigente")))))) -> Al dia | W26: No | X26: =IF($R26="","",IF($H26="NA","Costos Operacionales",IF(OR($H26="",$H26="Revisar",$H26="Por asignar"),"Por clasificar","Costo Ventas"))) -> Costos Operacionales | Y26: No
A27: =VLOOKUP(E27,$B$168:$B$255,1,0) -> LIVEEX S.A.S. | B27: 46169 | C27: 46169 | D27: =IF($R27="","",IF(ABS(Q27)<1,"Pagada",IF(Q27<0,IF(O27<0,"Nota credito","Saldo a favor"),IF(P27<>0,"Parcial","Pendiente")))) -> Pagada | E27: LIVEEX S.A.S. | F27: 901820420 | H27: AXIS | I27: Gastos Representacion | J27: AGUA 94 1 AGUA GAS 94 1 PEPSI CE | K27: 290252.54 | L27: 50134.46 | O27: =IF($R27="","",K27+L27+M27) -> 340387 | P27: =IF($R27="","",-SUMIFS('Extractos bancarios - Manglar'!$C:$C,'Extractos bancarios - Manglar'!$M:$M,$R27)) -> 340387 | Q27: =IF($R27="","",O27-N27-P27) -> 0 | R27: FVSE-27735 | S27: 46169 | T27: Incluye INC | U27: =IF($R27="","",IF($S27="","",$S27-TODAY())) -> -154 | V27: =IF($R27="","",IF(ISNUMBER(SEARCH("Anula",$T27)),"Anulada",IF($Q27<=1000,"Al dia",IF($S27="","Sin fecha",IF($U27<0,"Vencida",IF($U27<=15,"Por vencer","Vigente")))))) -> Al dia | W27: =IF($R27="","",IF($V27="Anulada","No","Si")) -> Si | X27: =IF($R27="","",IF($H27="NA","Costos Operacionales",IF(OR($H27="",$H27="Revisar",$H27="Por asignar"),"Por clasificar","Costo Ventas"))) -> Costo Ventas | Y27: =IF($R27="","","Si") -> Si
A28: =VLOOKUP(E28,$B$168:$B$255,1,0) -> LEXGRA CONSULTING S.A.S. | B28: 46169 | C28: 46195 | D28: =IF($R28="","",IF(ABS(Q28)<1,"Pagada",IF(Q28<0,IF(O28<0,"Nota credito","Saldo a favor"),IF(P28<>0,"Parcial","Pendiente")))) -> Pagada | E28: LEXGRA CONSULTING S.A.S. | F28: 901615566 | G28: M260501 | H28: {=_xlfn.XLOOKUP($G28,Data!$E:$E,Data!$F:$F,"Revisar",0)} -> Psiconometrics | I28: {=_xlfn.XLOOKUP($G28,Data!$E:$E,Data!$G:$G,"Revisar",0)} -> Evento Camara Comercio | J28: SERV011 REVISION CONTRATOS 94 1 Notas Finales REVISIO | K28: 600000 | L28: 114000 | N28: 17100 | O28: =IF($R28="","",K28+L28+M28) -> 714000 | P28: =IF($R28="","",-SUMIFS('Extractos bancarios - Manglar'!$C:$C,'Extractos bancarios - Manglar'!$M:$M,$R28)) -> 696900 | Q28: =IF($R28="","",O28-N28-P28) -> 0 | R28: LXFE-580 | S28: 46184 | U28: =IF($R28="","",IF($S28="","",$S28-TODAY())) -> -139 | V28: =IF($R28="","",IF(ISNUMBER(SEARCH("Anula",$T28)),"Anulada",IF($Q28<=1000,"Al dia",IF($S28="","Sin fecha",IF($U28<0,"Vencida",IF($U28<=15,"Por vencer","Vigente")))))) -> Al dia | W28: =IF($R28="","",IF($V28="Anulada","No","Si")) -> Si | X28: =IF($R28="","",IF($H28="NA","Costos Operacionales",IF(OR($H28="",$H28="Revisar",$H28="Por asignar"),"Por clasificar","Costo Ventas"))) -> Costo Ventas | Y28: =IF($R28="","","Si") -> Si
A29: =VLOOKUP(E29,$B$168:$B$255,1,0) -> IKSO SAS | B29: 46170 | C29: 46170 | D29: =IF($R29="","",IF(ABS(Q29)<1,"Pagada",IF(Q29<0,IF(O29<0,"Nota credito","Saldo a favor"),IF(P29<>0,"Parcial","Pendiente")))) -> Pagada | E29: IKSO SAS | F29: 901331844 | G29: M260501 | H29: {=_xlfn.XLOOKUP($G29,Data!$E:$E,Data!$F:$F,"Revisar",0)} -> Psiconometrics | I29: {=_xlfn.XLOOKUP($G29,Data!$E:$E,Data!$G:$G,"Revisar",0)} -> Evento Camara Comercio | J29: YTBERG LÁMP IL MUE BC NIU 3 O/REG INT LUM CO ANSLUTA TRA | K29: 205882.35 | L29: 39117.65 | O29: =IF($R29="","",K29+L29+M29) -> 245000 | P29: =IF($R29="","",-SUMIFS('Extractos bancarios - Manglar'!$C:$C,'Extractos bancarios - Manglar'!$M:$M,$R29)) -> 245000 | Q29: =IF($R29="","",O29-N29-P29) -> 0 | R29: F107-106504 | S29: 46170 | U29: =IF($R29="","",IF($S29="","",$S29-TODAY())) -> -153 | V29: =IF($R29="","",IF(ISNUMBER(SEARCH("Anula",$T29)),"Anulada",IF($Q29<=1000,"Al dia",IF($S29="","Sin fecha",IF($U29<0,"Vencida",IF($U29<=15,"Por vencer","Vigente")))))) -> Al dia | W29: =IF($R29="","",IF($V29="Anulada","No","Si")) -> Si | X29: =IF($R29="","",IF($H29="NA","Costos Operacionales",IF(OR($H29="",$H29="Revisar",$H29="Por asignar"),"Por clasificar","Costo Ventas"))) -> Costo Ventas | Y29: =IF($R29="","","Si") -> Si
A30: =VLOOKUP(E30,$B$168:$B$255,1,0) -> IKSO SAS | B30: 46170 | C30: 46170 | D30: =IF($R30="","",IF(ABS(Q30)<1,"Pagada",IF(Q30<0,IF(O30<0,"Nota credito","Saldo a favor"),IF(P30<>0,"Parcial","Pendiente")))) -> Pagada | E30: IKSO SAS | F30: 901331844 | G30: M260501 | H30: {=_xlfn.XLOOKUP($G30,Data!$E:$E,Data!$F:$F,"Revisar",0)} -> Psiconometrics | I30: {=_xlfn.XLOOKUP($G30,Data!$E:$E,Data!$G:$G,"Revisar",0)} -> Evento Camara Comercio | J30: BILLY N4 BIBLIOTECA 80X NIU 3 X202 BLANCO OXBERG PUERTA | K30: 1190647.1 | L30: 226222.95 | O30: =IF($R30="","",K30+L30+M30) -> 1416870 | P30: =IF($R30="","",-SUMIFS('Extractos bancarios - Manglar'!$C:$C,'Extractos bancarios - Manglar'!$M:$M,$R30)) -> 1416870 | Q30: =IF($R30="","",O30-N30-P30) -> 0 | R30: F107-106503 | S30: 46170 | U30: =IF($R30="","",IF($S30="","",$S30-TODAY())) -> -153 | V30: =IF($R30="","",IF(ISNUMBER(SEARCH("Anula",$T30)),"Anulada",IF($Q30<=1000,"Al dia",IF($S30="","Sin fecha",IF($U30<0,"Vencida",IF($U30<=15,"Por vencer","Vigente")))))) -> Al dia | W30: =IF($R30="","",IF($V30="Anulada","No","Si")) -> Si | X30: =IF($R30="","",IF($H30="NA","Costos Operacionales",IF(OR($H30="",$H30="Revisar",$H30="Por asignar"),"Por clasificar","Costo Ventas"))) -> Costo Ventas | Y30: =IF($R30="","","Si") -> Si
A31: =VLOOKUP(E31,$B$168:$B$255,1,0) -> COMERCIAL PAPELERA SA | B31: 46172 | C31: 46171 | D31: =IF($R31="","",IF(ABS(Q31)<1,"Pagada",IF(Q31<0,IF(O31<0,"Nota credito","Saldo a favor"),IF(P31<>0,"Parcial","Pendiente")))) -> Pagada | E31: COMERCIAL PAPELERA SA | F31: 860528396 | G31: M260401 | H31: {=_xlfn.XLOOKUP($G31,Data!$E:$E,Data!$F:$F,"Revisar",0)} -> Kaspersky | I31: {=_xlfn.XLOOKUP($G31,Data!$E:$E,Data!$G:$G,"Revisar",0)} -> Bolsa Incentivos 2026 | J31: RESMA PROPAL CARTA 21 RESMA OPALINA CARTA 2 IMPRES/COPIA CAR | K31: 43571 | L31: 8279 | O31: =IF($R31="","",K31+L31+M31) -> 51850 | P31: =IF($R31="","",-SUMIFS('Extractos bancarios - Manglar'!$C:$C,'Extractos bancarios - Manglar'!$M:$M,$R31)) -> 51850 | Q31: =IF($R31="","",O31-N31-P31) -> 0 | R31: FE04-509903 | U31: =IF($R31="","",IF($S31="","",$S31-TODAY())) | V31: =IF($R31="","",IF(ISNUMBER(SEARCH("Anula",$T31)),"Anulada",IF($Q31<=1000,"Al dia",IF($S31="","Sin fecha",IF($U31<0,"Vencida",IF($U31<=15,"Por vencer","Vigente")))))) -> Al dia | W31: =IF($R31="","",IF($V31="Anulada","No","Si")) -> Si | X31: =IF($R31="","",IF($H31="NA","Costos Operacionales",IF(OR($H31="",$H31="Revisar",$H31="Por asignar"),"Por clasificar","Costo Ventas"))) -> Costo Ventas | Y31: =IF($R31="","","Si") -> Si
A32: =VLOOKUP(E32,$B$168:$B$255,1,0) -> COMERCIAL PAPELERA SA | B32: 46172 | C32: 46172 | D32: =IF($R32="","",IF(ABS(Q32)<1,"Pagada",IF(Q32<0,IF(O32<0,"Nota credito","Saldo a favor"),IF(P32<>0,"Parcial","Pendiente")))) -> Pagada | E32: COMERCIAL PAPELERA SA | F32: 860528396 | G32: M260401 | H32: {=_xlfn.XLOOKUP($G32,Data!$E:$E,Data!$F:$F,"Revisar",0)} -> Kaspersky | I32: {=_xlfn.XLOOKUP($G32,Data!$E:$E,Data!$G:$G,"Revisar",0)} -> Bolsa Incentivos 2026 | J32: IMPRES/COPIA CARTA FU LL COLO PRINT XER RESMA PROPAL CARTA 2 | K32: 57143 | L32: 10857 | O32: =IF($R32="","",K32+L32+M32) -> 68000 | P32: =IF($R32="","",-SUMIFS('Extractos bancarios - Manglar'!$C:$C,'Extractos bancarios - Manglar'!$M:$M,$R32)) -> 68000 | Q32: =IF($R32="","",O32-N32-P32) -> 0 | R32: FE03-392527 | U32: =IF($R32="","",IF($S32="","",$S32-TODAY())) | V32: =IF($R32="","",IF(ISNUMBER(SEARCH("Anula",$T32)),"Anulada",IF($Q32<=1000,"Al dia",IF($S32="","Sin fecha",IF($U32<0,"Vencida",IF($U32<=15,"Por vencer","Vigente")))))) -> Al dia | W32: =IF($R32="","",IF($V32="Anulada","No","Si")) -> Si | X32: =IF($R32="","",IF($H32="NA","Costos Operacionales",IF(OR($H32="",$H32="Revisar",$H32="Por asignar"),"Por clasificar","Costo Ventas"))) -> Costo Ventas | Y32: =IF($R32="","","Si") -> Si
A33: =VLOOKUP(E33,$B$168:$B$255,1,0) -> TB PROMOCIONALES SAS | B33: 46174 | C33: 46204 | D33: =IF($R33="","",IF(ABS(Q33)<1,"Pagada",IF(Q33<0,IF(O33<0,"Nota credito","Saldo a favor"),IF(P33<>0,"Parcial","Pendiente")))) -> Pagada | E33: TB PROMOCIONALES SAS | F33: 900474221 | G33: M260102 | H33: {=_xlfn.XLOOKUP($G33,Data!$E:$E,Data!$F:$F,"Revisar",0)} -> AXIS | I33: {=_xlfn.XLOOKUP($G33,Data!$E:$E,Data!$G:$G,"Revisar",0)} -> Camisetas Academy | J33: CAMISETA TIPO POLO C OMPOSICION Lo qu Bordado 1 logo Tamañ | K33: 1494465 | L33: 283948.35 | O33: =IF($R33="","",K33+L33+M33) -> 1778413.4 | P33: =IF($R33="","",-SUMIFS('Extractos bancarios - Manglar'!$C:$C,'Extractos bancarios - Manglar'!$M:$M,$R33)) -> 1778413 | Q33: =IF($R33="","",O33-N33-P33) -> 0.35 | R33: FE-155 | S33: 46204 | T33: Sin cruce uno a uno con el banco | U33: =IF($R33="","",IF($S33="","",$S33-TODAY())) -> -119 | V33: =IF($R33="","",IF(ISNUMBER(SEARCH("Anula",$T33)),"Anulada",IF($Q33<=1000,"Al dia",IF($S33="","Sin fecha",IF($U33<0,"Vencida",IF($U33<=15,"Por vencer","Vigente")))))) -> Al dia | W33: =IF($R33="","",IF($V33="Anulada","No","Si")) -> Si | X33: =IF($R33="","",IF($H33="NA","Costos Operacionales",IF(OR($H33="",$H33="Revisar",$H33="Por asignar"),"Por clasificar","Costo Ventas"))) -> Costo Ventas | Y33: =IF($R33="","","Si") -> Si
A34: =VLOOKUP(E34,$B$168:$B$255,1,0) -> EVENTY EVENT PLANNERS SAS | B34: 46174 | C34: NA | D34: =IF($R34="","",IF(ABS(Q34)<1,"Pagada",IF(Q34<0,IF(O34<0,"Nota credito","Saldo a favor"),IF(P34<>0,"Parcial","Pendiente")))) -> Nota credito | E34: EVENTY EVENT PLANNERS SAS | F34: 901092033 | G34: NA | H34: {=_xlfn.XLOOKUP($G34,Data!$E:$E,Data!$F:$F,"Revisar",0)} -> NA | I34: {=_xlfn.XLOOKUP($G34,Data!$E:$E,Data!$G:$G,"Revisar",0)} -> NA | J34: ALQUILER DE MOBILIARI ZZ 1 O CC SALITRE PERSONAL DE MON | K34: -3119000 | L34: -592610 | O34: =IF($R34="","",K34+L34+M34) -> -3711610 | P34: =IF($R34="","",-SUMIFS('Extractos bancarios - Manglar'!$C:$C,'Extractos bancarios - Manglar'!$M:$M,$R34)) -> 0 | Q34: =IF($R34="","",O34-N34-P34) -> -3711610 | R34: NC2107 | S34: 46174 | T34: Anula FVP-1209 | U34: =IF($R34="","",IF($S34="","",$S34-TODAY())) -> -149 | V34: =IF($R34="","",IF(ISNUMBER(SEARCH("Anula",$T34)),"Anulada",IF($Q34<=1000,"Al dia",IF($S34="","Sin fecha",IF($U34<0,"Vencida",IF($U34<=15,"Por vencer","Vigente")))))) -> Anulada | W34: =IF($R34="","",IF($V34="Anulada","No","Si")) -> No | X34: =IF($R34="","",IF($H34="NA","Costos Operacionales",IF(OR($H34="",$H34="Revisar",$H34="Por asignar"),"Por clasificar","Costo Ventas"))) -> Costos Operacionales | Y34: =IF($R34="","","Si") -> Si
A35: =VLOOKUP(E35,$B$168:$B$255,1,0) -> EVENTY EVENT PLANNERS SAS | B35: 46174 | C35: NA | D35: =IF($R35="","",IF(ABS(Q35)<1,"Pagada",IF(Q35<0,IF(O35<0,"Nota credito","Saldo a favor"),IF(P35<>0,"Parcial","Pendiente")))) -> Pendiente | E35: EVENTY EVENT PLANNERS SAS | F35: 901092033 | G35: NA | H35: {=_xlfn.XLOOKUP($G35,Data!$E:$E,Data!$F:$F,"Revisar",0)} -> NA | I35: {=_xlfn.XLOOKUP($G35,Data!$E:$E,Data!$G:$G,"Revisar",0)} -> NA | J35: ALQUILER DE MOBILIARI O CC SALITRE PERSONAL DE MONTAJE PM1 | K35: 3119000 | L35: 592610 | O35: =IF($R35="","",K35+L35+M35) -> 3711610 | P35: =IF($R35="","",-SUMIFS('Extractos bancarios - Manglar'!$C:$C,'Extractos bancarios - Manglar'!$M:$M,$R35)) -> 0 | Q35: =IF($R35="","",O35-N35-P35) -> 3711610 | R35: FVP-1209 | S35: 46204 | T35: Anulada por NC2107 | U35: =IF($R35="","",IF($S35="","",$S35-TODAY())) -> -119 | V35: =IF($R35="","",IF(ISNUMBER(SEARCH("Anula",$T35)),"Anulada",IF($Q35<=1000,"Al dia",IF($S35="","Sin fecha",IF($U35<0,"Vencida",IF($U35<=15,"Por vencer","Vigente")))))) -> Anulada | W35: =IF($R35="","",IF($V35="Anulada","No","Si")) -> No | X35: =IF($R35="","",IF($H35="NA","Costos Operacionales",IF(OR($H35="",$H35="Revisar",$H35="Por asignar"),"Por clasificar","Costo Ventas"))) -> Costos Operacionales | Y35: =IF($R35="","","Si") -> Si
A36: =VLOOKUP(E36,$B$168:$B$255,1,0) -> EVENTY EVENT PLANNERS SAS | B36: 46174 | C36: 46204 | D36: =IF($R36="","",IF(ABS(Q36)<1,"Pagada",IF(Q36<0,IF(O36<0,"Nota credito","Saldo a favor"),IF(P36<>0,"Parcial","Pendiente")))) -> Pagada | E36: EVENTY EVENT PLANNERS SAS | F36: 901092033 | G36: M260501 | H36: {=_xlfn.XLOOKUP($G36,Data!$E:$E,Data!$F:$F,"Revisar",0)} -> Psiconometrics | I36: {=_xlfn.XLOOKUP($G36,Data!$E:$E,Data!$G:$G,"Revisar",0)} -> Evento Camara Comercio | J36: ALQUILER DE MOBILIARI PERSONAL DE MONTAJE PM1 | K36: 3227000 | L36: 613130 | O36: =IF($R36="","",K36+L36+M36) -> 3840130 | P36: =IF($R36="","",-SUMIFS('Extractos bancarios - Manglar'!$C:$C,'Extractos bancarios - Manglar'!$M:$M,$R36)) -> 3840130 | Q36: =IF($R36="","",O36-N36-P36) -> 0 | R36: FVP-1218 | S36: 46204 | T36: Sin cruce uno a uno con el banco | U36: =IF($R36="","",IF($S36="","",$S36-TODAY())) -> -119 | V36: =IF($R36="","",IF(ISNUMBER(SEARCH("Anula",$T36)),"Anulada",IF($Q36<=1000,"Al dia",IF($S36="","Sin fecha",IF($U36<0,"Vencida",IF($U36<=15,"Por vencer","Vigente")))))) -> Al dia | W36: =IF($R36="","",IF($V36="Anulada","No","Si")) -> Si | X36: =IF($R36="","",IF($H36="NA","Costos Operacionales",IF(OR($H36="",$H36="Revisar",$H36="Por asignar"),"Por clasificar","Costo Ventas"))) -> Costo Ventas | Y36: =IF($R36="","","Si") -> Si
A37: =VLOOKUP(E37,$B$168:$B$255,1,0) -> PLANTICENTER S.A.S | B37: 46174 | C37: NA | D37: =IF($R37="","",IF(ABS(Q37)<1,"Pagada",IF(Q37<0,IF(O37<0,"Nota credito","Saldo a favor"),IF(P37<>0,"Parcial","Pendiente")))) -> Pagada | E37: PLANTICENTER S.A.S | F37: 901578457 | G37: NA | H37: {=_xlfn.XLOOKUP($G37,Data!$E:$E,Data!$F:$F,"Revisar",0)} -> NA | I37: {=_xlfn.XLOOKUP($G37,Data!$E:$E,Data!$G:$G,"Revisar",0)} -> NA | J37: MATERA CEMENTO GOTA TRONCO DEL BRASIL 94 10 TRANSPORT | K37: 1901000 | L37: 203490 | O37: =IF($R37="","",K37+L37+M37) -> 2104490 | P37: 2104490 | Q37: =IF($R37="","",O37-N37-P37) -> 0 | R37: FEV-12274 | S37: 46174 | T37: Pagado con medios diferentes a los de Manglar | U37: =IF($R37="","",IF($S37="","",$S37-TODAY())) -> -149 | V37: =IF($R37="","",IF(ISNUMBER(SEARCH("Anula",$T37)),"Anulada",IF($Q37<=1000,"Al dia",IF($S37="","Sin fecha",IF($U37<0,"Vencida",IF($U37<=15,"Por vencer","Vigente")))))) -> Al dia | W37: No | X37: =IF($R37="","",IF($H37="NA","Costos Operacionales",IF(OR($H37="",$H37="Revisar",$H37="Por asignar"),"Por clasificar","Costo Ventas"))) -> Costos Operacionales | Y37: No
A38: =VLOOKUP(E38,$B$168:$B$255,1,0) -> HOTELES EL SALITRE SAS | B38: 46177 | C38: NA | D38: =IF($R38="","",IF(ABS(Q38)<1,"Pagada",IF(Q38<0,IF(O38<0,"Nota credito","Saldo a favor"),IF(P38<>0,"Parcial","Pendiente")))) -> Pagada | E38: HOTELES EL SALITRE SAS | F38: 800247030 | G38: NA | H38: {=_xlfn.XLOOKUP($G38,Data!$E:$E,Data!$F:$F,"Revisar",0)} -> NA | I38: {=_xlfn.XLOOKUP($G38,Data!$E:$E,Data!$G:$G,"Revisar",0)} -> NA | J38: ROOM SERVICE 94 1 PROPINA - INGRESO DE TERCEROS | K38: 453361.11 | L38: 75240 | O38: =IF($R38="","",K38+L38+M38) -> 528601.11 | P38: 528601.11 | Q38: =IF($R38="","",O38-N38-P38) -> 0 | R38: FRO-167216 | S38: 46207 | T38: Pagado con medios diferentes a los de Manglar | U38: =IF($R38="","",IF($S38="","",$S38-TODAY())) -> -116 | V38: =IF($R38="","",IF(ISNUMBER(SEARCH("Anula",$T38)),"Anulada",IF($Q38<=1000,"Al dia",IF($S38="","Sin fecha",IF($U38<0,"Vencida",IF($U38<=15,"Por vencer","Vigente")))))) -> Al dia | W38: No | X38: =IF($R38="","",IF($H38="NA","Costos Operacionales",IF(OR($H38="",$H38="Revisar",$H38="Por asignar"),"Por clasificar","Costo Ventas"))) -> Costos Operacionales | Y38: No
A39: =VLOOKUP(E39,$B$168:$B$255,1,0) -> LOGIST LATAM S.A.S | B39: 46178 | C39: 46205 | D39: =IF($R39="","",IF(ABS(Q39)<1,"Pagada",IF(Q39<0,IF(O39<0,"Nota credito","Saldo a favor"),IF(P39<>0,"Parcial","Pendiente")))) -> Pagada | E39: LOGIST LATAM S.A.S | F39: 901374586 | G39: M260501 | H39: {=_xlfn.XLOOKUP($G39,Data!$E:$E,Data!$F:$F,"Revisar",0)} -> Psiconometrics | I39: {=_xlfn.XLOOKUP($G39,Data!$E:$E,Data!$G:$G,"Revisar",0)} -> Evento Camara Comercio | J39: TECNICA Y ESCENOGRA L0025 94 1 | K39: 103132500 | L39: 19595175 | O39: =IF($R39="","",K39+L39+M39) -> 122727675 | P39: =IF($R39="","",-SUMIFS('Extractos bancarios - Manglar'!$C:$C,'Extractos bancarios - Manglar'!$M:$M,$R39)) -> 122727675 | Q39: =IF($R39="","",O39-N39-P39) -> 0 | R39: FV-1537 | S39: 46193 | T39: Sin cruce uno a uno con el banco | U39: =IF($R39="","",IF($S39="","",$S39-TODAY())) -> -130 | V39: =IF($R39="","",IF(ISNUMBER(SEARCH("Anula",$T39)),"Anulada",IF($Q39<=1000,"Al dia",IF($S39="","Sin fecha",IF($U39<0,"Vencida",IF($U39<=15,"Por vencer","Vigente")))))) -> Al dia | W39: =IF($R39="","",IF($V39="Anulada","No","Si")) -> Si | X39: =IF($R39="","",IF($H39="NA","Costos Operacionales",IF(OR($H39="",$H39="Revisar",$H39="Por asignar"),"Por clasificar","Costo Ventas"))) -> Costo Ventas | Y39: =IF($R39="","","Si") -> Si
A40: =VLOOKUP(E40,$B$168:$B$255,1,0) -> Mandolina Gourmet LTDA | B40: 46182 | C40: 46195 | D40: =IF($R40="","",IF(ABS(Q40)<1,"Pagada",IF(Q40<0,IF(O40<0,"Nota credito","Saldo a favor"),IF(P40<>0,"Parcial","Pendiente")))) -> Pagada | E40: Mandolina Gourmet LTDA | F40: 900040732 | G40: M260501 | H40: {=_xlfn.XLOOKUP($G40,Data!$E:$E,Data!$F:$F,"Revisar",0)} -> Psiconometrics | I40: {=_xlfn.XLOOKUP($G40,Data!$E:$E,Data!$G:$G,"Revisar",0)} -> Evento Camara Comercio | J40: Estacion de café NIU 500 PASABOCAS NIU 200 ME | K40: 45894040 | L40: 0 | O40: =IF($R40="","",K40+L40+M40) -> 45894040 | P40: =IF($R40="","",-SUMIFS('Extractos bancarios - Manglar'!$C:$C,'Extractos bancarios - Manglar'!$M:$M,$R40)) -> 45894040 | Q40: =IF($R40="","",O40-N40-P40) -> 0 | R40: FE-3225 | S40: 46212 | T40: Sin cruce uno a uno con el banco · Incluye INC | U40: =IF($R40="","",IF($S40="","",$S40-TODAY())) -> -111 | V40: =IF($R40="","",IF(ISNUMBER(SEARCH("Anula",$T40)),"Anulada",IF($Q40<=1000,"Al dia",IF($S40="","Sin fecha",IF($U40<0,"Vencida",IF($U40<=15,"Por vencer","Vigente")))))) -> Al dia | W40: =IF($R40="","",IF($V40="Anulada","No","Si")) -> Si | X40: =IF($R40="","",IF($H40="NA","Costos Operacionales",IF(OR($H40="",$H40="Revisar",$H40="Por asignar"),"Por clasificar","Costo Ventas"))) -> Costo Ventas | Y40: =IF($R40="","","Si") -> Si
A41: =VLOOKUP(E41,$B$168:$B$255,1,0) -> LIVEEX S.A.S. | B41: 46184 | C41: 46271 | D41: =IF($R41="","",IF(ABS(Q41)<1,"Pagada",IF(Q41<0,IF(O41<0,"Nota credito","Saldo a favor"),IF(P41<>0,"Parcial","Pendiente")))) -> Pagada | E41: LIVEEX S.A.S. | F41: 901820420 | G41: M260101 | H41: {=_xlfn.XLOOKUP($G41,Data!$E:$E,Data!$F:$F,"Revisar",0)} -> AXIS | I41: {=_xlfn.XLOOKUP($G41,Data!$E:$E,Data!$G:$G,"Revisar",0)} -> Evento mundial de fútbol y merchandising | J41: AGUA GAS 94 2 AGUA GAS 94 1 AGUA GAS | K41: 279159.5 | L41: 48218.49 | O41: =IF($R41="","",K41+L41+M41) -> 327377.99 | P41: =IF($R41="","",-SUMIFS('Extractos bancarios - Manglar'!$C:$C,'Extractos bancarios - Manglar'!$M:$M,$R41)) -> 327377.99 | Q41: =IF($R41="","",O41-N41-P41) -> 0 | R41: FVSE-28291 | S41: 46184 | T41: Sin cruce uno a uno con el banco · Incluye INC | U41: =IF($R41="","",IF($S41="","",$S41-TODAY())) -> -139 | V41: =IF($R41="","",IF(ISNUMBER(SEARCH("Anula",$T41)),"Anulada",IF($Q41<=1000,"Al dia",IF($S41="","Sin fecha",IF($U41<0,"Vencida",IF($U41<=15,"Por vencer","Vigente")))))) -> Al dia | W41: =IF($R41="","",IF($V41="Anulada","No","Si")) -> Si | X41: =IF($R41="","",IF($H41="NA","Costos Operacionales",IF(OR($H41="",$H41="Revisar",$H41="Por asignar"),"Por clasificar","Costo Ventas"))) -> Costo Ventas | Y41: =IF($R41="","","Si") -> Si
A42: =VLOOKUP(E42,$B$168:$B$255,1,0) -> LIVEEX S.A.S. | B42: 46184 | C42: 46271 | D42: =IF($R42="","",IF(ABS(Q42)<1,"Pagada",IF(Q42<0,IF(O42<0,"Nota credito","Saldo a favor"),IF(P42<>0,"Parcial","Pendiente")))) -> Pagada | E42: LIVEEX S.A.S. | F42: 901820420 | G42: M260101 | H42: {=_xlfn.XLOOKUP($G42,Data!$E:$E,Data!$F:$F,"Revisar",0)} -> AXIS | I42: {=_xlfn.XLOOKUP($G42,Data!$E:$E,Data!$G:$G,"Revisar",0)} -> Evento mundial de fútbol y merchandising | J42: DRAGON ROLL 94 1 Cargo | K42: 43445.8 | L42: 7504.2 | O42: =IF($R42="","",K42+L42+M42) -> 50950 | P42: 50950 | Q42: =IF($R42="","",O42-N42-P42) -> 0 | R42: FVSE-28305 | S42: 46184 | T42: Sin cruce uno a uno con el banco · Incluye INC | U42: =IF($R42="","",IF($S42="","",$S42-TODAY())) -> -139 | V42: =IF($R42="","",IF(ISNUMBER(SEARCH("Anula",$T42)),"Anulada",IF($Q42<=1000,"Al dia",IF($S42="","Sin fecha",IF($U42<0,"Vencida",IF($U42<=15,"Por vencer","Vigente")))))) -> Al dia | W42: =IF($R42="","",IF($V42="Anulada","No","Si")) -> Si | X42: =IF($R42="","",IF($H42="NA","Costos Operacionales",IF(OR($H42="",$H42="Revisar",$H42="Por asignar"),"Por clasificar","Costo Ventas"))) -> Costo Ventas | Y42: =IF($R42="","","Si") -> Si
A43: =VLOOKUP(E43,$B$168:$B$255,1,0) -> COLOMBIANA DE COMERCIO S.A. | B43: 46184 | C43: NA | D43: =IF($R43="","",IF(ABS(Q43)<1,"Pagada",IF(Q43<0,IF(O43<0,"Nota credito","Saldo a favor"),IF(P43<>0,"Parcial","Pendiente")))) -> Pagada | E43: COLOMBIANA DE COMERCIO S.A. | F43: 890900943 | G43: NA | H43: {=_xlfn.XLOOKUP($G43,Data!$E:$E,Data!$F:$F,"Revisar",0)} -> NA | I43: {=_xlfn.XLOOKUP($G43,Data!$E:$E,Data!$G:$G,"Revisar",0)} -> NA | J43: Cable Best HDMI/HDMI4K Notas Finales Responsable I.V.A. Somo | K43: 46134.45 | L43: 8765.55 | O43: =IF($R43="","",K43+L43+M43) -> 54900 | P43: 54900 | Q43: =IF($R43="","",O43-N43-P43) -> 0 | R43: X837-2535638 | T43: Pagado con medios diferentes a los de Manglar | U43: =IF($R43="","",IF($S43="","",$S43-TODAY())) | V43: =IF($R43="","",IF(ISNUMBER(SEARCH("Anula",$T43)),"Anulada",IF($Q43<=1000,"Al dia",IF($S43="","Sin fecha",IF($U43<0,"Vencida",IF($U43<=15,"Por vencer","Vigente")))))) -> Al dia | W43: No | X43: =IF($R43="","",IF($H43="NA","Costos Operacionales",IF(OR($H43="",$H43="Revisar",$H43="Por asignar"),"Por clasificar","Costo Ventas"))) -> Costos Operacionales | Y43: No
A44: =VLOOKUP(E44,$B$168:$B$255,1,0) -> LIVEEX S.A.S. | B44: 46184 | C44: 46182 | D44: =IF($R44="","",IF(ABS(Q44)<1,"Pagada",IF(Q44<0,IF(O44<0,"Nota credito","Saldo a favor"),IF(P44<>0,"Parcial","Pendiente")))) -> Saldo a favor | E44: LIVEEX S.A.S. | F44: 901820420 | G44: M260101 | H44: {=_xlfn.XLOOKUP($G44,Data!$E:$E,Data!$F:$F,"Revisar",0)} -> AXIS | I44: {=_xlfn.XLOOKUP($G44,Data!$E:$E,Data!$G:$G,"Revisar",0)} -> Evento mundial de fútbol y merchandising | J44: CORONA 94 41 BT CHIVAS 12 94 6 AGUA | K44: 7516218.7 | L44: 1299983.2 | O44: =IF($R44="","",K44+L44+M44) -> 8816201.9 | P44: =IF($R44="","",-SUMIFS('Extractos bancarios - Manglar'!$C:$C,'Extractos bancarios - Manglar'!$M:$M,$R44)) -> 8851151 | Q44: =IF($R44="","",O44-N44-P44) -> -34949.11 | R44: FVMR-18762 | S44: 46184 | T44: Sin cruce uno a uno con el banco · Incluye INC | U44: =IF($R44="","",IF($S44="","",$S44-TODAY())) -> -139 | V44: =IF($R44="","",IF(ISNUMBER(SEARCH("Anula",$T44)),"Anulada",IF($Q44<=1000,"Al dia",IF($S44="","Sin fecha",IF($U44<0,"Vencida",IF($U44<=15,"Por vencer","Vigente")))))) -> Al dia | W44: No | X44: =IF($R44="","",IF($H44="NA","Costos Operacionales",IF(OR($H44="",$H44="Revisar",$H44="Por asignar"),"Por clasificar","Costo Ventas"))) -> Costo Ventas | Y44: =IF($R44="","","Si") -> Si
A45: =VLOOKUP(E45,$B$168:$B$255,1,0) -> TRANSPARENTE AGENCIA GRAFICA S.A.S | B45: 46185 | C45: 46189 | D45: =IF($R45="","",IF(ABS(Q45)<1,"Pagada",IF(Q45<0,IF(O45<0,"Nota credito","Saldo a favor"),IF(P45<>0,"Parcial","Pendiente")))) -> Pagada | E45: TRANSPARENTE AGENCIA GRAFICA S.A.S | F45: 901909925 | G45: M260101 | H45: {=_xlfn.XLOOKUP($G45,Data!$E:$E,Data!$F:$F,"Revisar",0)} -> AXIS | I45: {=_xlfn.XLOOKUP($G45,Data!$E:$E,Data!$G:$G,"Revisar",0)} -> Evento mundial de fútbol y merchandising | J45: ROLLUP 2X1 METROS CO N IMPRESION BANNER 13 94 2 CUBO | K45: 1740000 | L45: 330600 | O45: =IF($R45="","",K45+L45+M45) -> 2070600 | P45: =IF($R45="","",-SUMIFS('Extractos bancarios - Manglar'!$C:$C,'Extractos bancarios - Manglar'!$M:$M,$R45)) -> 2070600 | Q45: =IF($R45="","",O45-N45-P45) -> 0 | R45: FE-309 | U45: =IF($R45="","",IF($S45="","",$S45-TODAY())) | V45: =IF($R45="","",IF(ISNUMBER(SEARCH("Anula",$T45)),"Anulada",IF($Q45<=1000,"Al dia",IF($S45="","Sin fecha",IF($U45<0,"Vencida",IF($U45<=15,"Por vencer","Vigente")))))) -> Al dia | W45: =IF($R45="","",IF($V45="Anulada","No","Si")) -> Si | X45: =IF($R45="","",IF($H45="NA","Costos Operacionales",IF(OR($H45="",$H45="Revisar",$H45="Por asignar"),"Por clasificar","Costo Ventas"))) -> Costo Ventas | Y45: =IF($R45="","","Si") -> Si
A46: =VLOOKUP(E46,$B$168:$B$255,1,0) -> ADIDAS COLOMBIA LTDA | B46: 46187 | C46: NA | D46: =IF($R46="","",IF(ABS(Q46)<1,"Pagada",IF(Q46<0,IF(O46<0,"Nota credito","Saldo a favor"),IF(P46<>0,"Parcial","Pendiente")))) -> Pendiente | E46: ADIDAS COLOMBIA LTDA | F46: 805011074 | G46: NA | H46: {=_xlfn.XLOOKUP($G46,Data!$E:$E,Data!$F:$F,"Revisar",0)} -> NA | I46: {=_xlfn.XLOOKUP($G46,Data!$E:$E,Data!$G:$G,"Revisar",0)} -> NA | J46: JL6972 FCF H JSY NIU 1 | K46: 319285.71 | L46: 60664.28 | O46: =IF($R46="","",K46+L46+M46) -> 379949.99 | P46: =IF($R46="","",-SUMIFS('Extractos bancarios - Manglar'!$C:$C,'Extractos bancarios - Manglar'!$M:$M,$R46)) -> 0 | Q46: =IF($R46="","",O46-N46-P46) -> 379949.99 | R46: 080A-39251 | T46: Anulada por NC080A8824 | U46: =IF($R46="","",IF($S46="","",$S46-TODAY())) | V46: =IF($R46="","",IF(ISNUMBER(SEARCH("Anula",$T46)),"Anulada",IF($Q46<=1000,"Al dia",IF($S46="","Sin fecha",IF($U46<0,"Vencida",IF($U46<=15,"Por vencer","Vigente")))))) -> Anulada | W46: =IF($R46="","",IF($V46="Anulada","No","Si")) -> No | X46: =IF($R46="","",IF($H46="NA","Costos Operacionales",IF(OR($H46="",$H46="Revisar",$H46="Por asignar"),"Por clasificar","Costo Ventas"))) -> Costos Operacionales | Y46: No
A47: =VLOOKUP(E47,$B$168:$B$255,1,0) -> ADIDAS COLOMBIA LTDA | B47: 46187 | C47: NA | D47: =IF($R47="","",IF(ABS(Q47)<1,"Pagada",IF(Q47<0,IF(O47<0,"Nota credito","Saldo a favor"),IF(P47<>0,"Parcial","Pendiente")))) -> Nota credito | E47: ADIDAS COLOMBIA LTDA | F47: 805011074 | G47: NA | H47: {=_xlfn.XLOOKUP($G47,Data!$E:$E,Data!$F:$F,"Revisar",0)} -> NA | I47: {=_xlfn.XLOOKUP($G47,Data!$E:$E,Data!$G:$G,"Revisar",0)} -> NA | J47: JL6972 FCF H JSY NIU 1 | K47: -319285.71 | L47: -60664.28 | O47: =IF($R47="","",K47+L47+M47) -> -379949.99 | P47: =IF($R47="","",-SUMIFS('Extractos bancarios - Manglar'!$C:$C,'Extractos bancarios - Manglar'!$M:$M,$R47)) -> 0 | Q47: =IF($R47="","",O47-N47-P47) -> -379949.99 | R47: NC080A8824 | T47: Anula 080A-39251 | U47: =IF($R47="","",IF($S47="","",$S47-TODAY())) | V47: =IF($R47="","",IF(ISNUMBER(SEARCH("Anula",$T47)),"Anulada",IF($Q47<=1000,"Al dia",IF($S47="","Sin fecha",IF($U47<0,"Vencida",IF($U47<=15,"Por vencer","Vigente")))))) -> Anulada | W47: =IF($R47="","",IF($V47="Anulada","No","Si")) -> No | X47: =IF($R47="","",IF($H47="NA","Costos Operacionales",IF(OR($H47="",$H47="Revisar",$H47="Por asignar"),"Por clasificar","Costo Ventas"))) -> Costos Operacionales | Y47: No
A48: =VLOOKUP(E48,$B$168:$B$255,1,0) -> SMART DESIGN PUBLICIDAD SAS | B48: 46190 | C48: 46192 | D48: =IF($R48="","",IF(ABS(Q48)<1,"Pagada",IF(Q48<0,IF(O48<0,"Nota credito","Saldo a favor"),IF(P48<>0,"Parcial","Pendiente")))) -> Pagada | E48: SMART DESIGN PUBLICIDAD SAS | F48: 901764188 | G48: M260401 | H48: {=_xlfn.XLOOKUP($G48,Data!$E:$E,Data!$F:$F,"Revisar",0)} -> Kaspersky | I48: {=_xlfn.XLOOKUP($G48,Data!$E:$E,Data!$G:$G,"Revisar",0)} -> Bolsa Incentivos 2026 | J48: CUADERNOS ZZ 100 Esferos marcados en tam ZZ | K48: 1864000 | L48: 354160 | O48: =IF($R48="","",K48+L48+M48) -> 2218160 | P48: =IF($R48="","",-SUMIFS('Extractos bancarios - Manglar'!$C:$C,'Extractos bancarios - Manglar'!$M:$M,$R48)) -> 2218160 | Q48: =IF($R48="","",O48-N48-P48) -> 0 | R48: SD-457 | S48: 46190 | U48: =IF($R48="","",IF($S48="","",$S48-TODAY())) -> -133 | V48: =IF($R48="","",IF(ISNUMBER(SEARCH("Anula",$T48)),"Anulada",IF($Q48<=1000,"Al dia",IF($S48="","Sin fecha",IF($U48<0,"Vencida",IF($U48<=15,"Por vencer","Vigente")))))) -> Al dia | W48: =IF($R48="","",IF($V48="Anulada","No","Si")) -> Si | X48: =IF($R48="","",IF($H48="NA","Costos Operacionales",IF(OR($H48="",$H48="Revisar",$H48="Por asignar"),"Por clasificar","Costo Ventas"))) -> Costo Ventas | Y48: =IF($R48="","","Si") -> Si
A49: =VLOOKUP(E49,$B$168:$B$255,1,0) -> ADIDAS COLOMBIA LTDA | B49: 46198 | C49: NA | D49: =IF($R49="","",IF(ABS(Q49)<1,"Pagada",IF(Q49<0,IF(O49<0,"Nota credito","Saldo a favor"),IF(P49<>0,"Parcial","Pendiente")))) -> Nota credito | E49: ADIDAS COLOMBIA LTDA | F49: 805011074 | G49: NA | H49: {=_xlfn.XLOOKUP($G49,Data!$E:$E,Data!$F:$F,"Revisar",0)} -> NA | I49: {=_xlfn.XLOOKUP($G49,Data!$E:$E,Data!$G:$G,"Revisar",0)} -> NA | J49: JL6972 FCF H JSY NIU 1 | K49: -319285.71 | L49: -60664.28 | O49: =IF($R49="","",K49+L49+M49) -> -379949.99 | P49: =IF($R49="","",-SUMIFS('Extractos bancarios - Manglar'!$C:$C,'Extractos bancarios - Manglar'!$M:$M,$R49)) -> 0 | Q49: =IF($R49="","",O49-N49-P49) -> -379949.99 | R49: NC77A1123 | T49: Pagado con medios diferentes a los de Manglar | U49: =IF($R49="","",IF($S49="","",$S49-TODAY())) | V49: =IF($R49="","",IF(ISNUMBER(SEARCH("Anula",$T49)),"Anulada",IF($Q49<=1000,"Al dia",IF($S49="","Sin fecha",IF($U49<0,"Vencida",IF($U49<=15,"Por vencer","Vigente")))))) -> Al dia | W49: No | X49: =IF($R49="","",IF($H49="NA","Costos Operacionales",IF(OR($H49="",$H49="Revisar",$H49="Por asignar"),"Por clasificar","Costo Ventas"))) -> Costos Operacionales | Y49: No
A50: =VLOOKUP(E50,$B$168:$B$255,1,0) -> CENTRAL PARKING SYSTEM COLOMBIA SAS | B50: 46203 | C50: 46203 | D50: =IF($R50="","",IF(ABS(Q50)<1,"Pagada",IF(Q50<0,IF(O50<0,"Nota credito","Saldo a favor"),IF(P50<>0,"Parcial","Pendiente")))) -> Pagada | E50: CENTRAL PARKING SYSTEM COLOMBIA SAS | F50: 830087099 | G50: NA | H50: {=_xlfn.XLOOKUP($G50,Data!$E:$E,Data!$F:$F,"Revisar",0)} -> NA | I50: {=_xlfn.XLOOKUP($G50,Data!$E:$E,Data!$G:$G,"Revisar",0)} -> NA | J50: PK Parqueadero 94 1 | K50: 7521.01 | L50: 1428.99 | O50: =IF($R50="","",K50+L50+M50) -> 8950 | P50: =IF($R50="","",-SUMIFS('Extractos bancarios - Manglar'!$C:$C,'Extractos bancarios - Manglar'!$M:$M,$R50)) -> 8950 | Q50: =IF($R50="","",O50-N50-P50) -> 0 | R50: 1VAT-373415 | S50: 46203 | U50: =IF($R50="","",IF($S50="","",$S50-TODAY())) -> -120 | V50: =IF($R50="","",IF(ISNUMBER(SEARCH("Anula",$T50)),"Anulada",IF($Q50<=1000,"Al dia",IF($S50="","Sin fecha",IF($U50<0,"Vencida",IF($U50<=15,"Por vencer","Vigente")))))) -> Al dia | W50: =IF($R50="","",IF($V50="Anulada","No","Si")) -> Si | X50: =IF($R50="","",IF($H50="NA","Costos Operacionales",IF(OR($H50="",$H50="Revisar",$H50="Por asignar"),"Por clasificar","Costo Ventas"))) -> Costos Operacionales | Y50: =IF($R50="","","Si") -> Si
A51: =VLOOKUP(E51,$B$168:$B$255,1,0) -> TAKAMI SA | B51: 46204 | C51: 46204 | D51: =IF($R51="","",IF(ABS(Q51)<1,"Pagada",IF(Q51<0,IF(O51<0,"Nota credito","Saldo a favor"),IF(P51<>0,"Parcial","Pendiente")))) -> Pagada | E51: TAKAMI SA | F51: 830081427 | G51: NA | H51: {=_xlfn.XLOOKUP($G51,Data!$E:$E,Data!$F:$F,"Revisar",0)} -> NA | I51: {=_xlfn.XLOOKUP($G51,Data!$E:$E,Data!$G:$G,"Revisar",0)} -> NA | J51: ARANCINI VECCINA NIU 1 CARPACCIO DE RES VECC NIU | K51: 220480 | L51: 0 | O51: =IF($R51="","",K51+L51+M51) -> 220480 | P51: =IF($R51="","",-SUMIFS('Extractos bancarios - Manglar'!$C:$C,'Extractos bancarios - Manglar'!$M:$M,$R51)) -> 220480 | Q51: =IF($R51="","",O51-N51-P51) -> 0 | R51: V9FE-103170 | T51: Incluye INC | U51: =IF($R51="","",IF($S51="","",$S51-TODAY())) | V51: =IF($R51="","",IF(ISNUMBER(SEARCH("Anula",$T51)),"Anulada",IF($Q51<=1000,"Al dia",IF($S51="","Sin fecha",IF($U51<0,"Vencida",IF($U51<=15,"Por vencer","Vigente")))))) -> Al dia | W51: =IF($R51="","",IF($V51="Anulada","No","Si")) -> Si | X51: =IF($R51="","",IF($H51="NA","Costos Operacionales",IF(OR($H51="",$H51="Revisar",$H51="Por asignar"),"Por clasificar","Costo Ventas"))) -> Costos Operacionales | Y51: =IF($R51="","","Si") -> Si
A52: =VLOOKUP(E52,$B$168:$B$255,1,0) -> COMBUSTIBLES H & R LTDA. | B52: 46204 | C52: 46204 | D52: =IF($R52="","",IF(ABS(Q52)<1,"Pagada",IF(Q52<0,IF(O52<0,"Nota credito","Saldo a favor"),IF(P52<>0,"Parcial","Pendiente")))) -> Pagada | E52: COMBUSTIBLES H & R LTDA. | F52: 900078103 | G52: NA | H52: {=_xlfn.XLOOKUP($G52,Data!$E:$E,Data!$F:$F,"Revisar",0)} -> NA | I52: {=_xlfn.XLOOKUP($G52,Data!$E:$E,Data!$G:$G,"Revisar",0)} -> NA | J52: SHELL SUPER GLL 15 Notas Finales ORDEN DE VENTA EQUI | K52: 235904 | L52: 0 | O52: =IF($R52="","",K52+L52+M52) -> 235904 | P52: =IF($R52="","",-SUMIFS('Extractos bancarios - Manglar'!$C:$C,'Extractos bancarios - Manglar'!$M:$M,$R52)) -> 235904 | Q52: =IF($R52="","",O52-N52-P52) -> 0 | R52: FSEC-471295 | U52: =IF($R52="","",IF($S52="","",$S52-TODAY())) | V52: =IF($R52="","",IF(ISNUMBER(SEARCH("Anula",$T52)),"Anulada",IF($Q52<=1000,"Al dia",IF($S52="","Sin fecha",IF($U52<0,"Vencida",IF($U52<=15,"Por vencer","Vigente")))))) -> Al dia | W52: =IF($R52="","",IF($V52="Anulada","No","Si")) -> Si | X52: =IF($R52="","",IF($H52="NA","Costos Operacionales",IF(OR($H52="",$H52="Revisar",$H52="Por asignar"),"Por clasificar","Costo Ventas"))) -> Costos Operacionales | Y52: =IF($R52="","","Si") -> Si
